Workbook

Sheet README
A1: Barcelona pipeline — how to use this workbook
A2: Generated 2026-09-13 from docs/market/barcelona/. Rebuild with: python3 scripts/market-pipeline-xlsx.py
A4: What this is | B4: 128 construction and renovation firms in the Barcelona area, scored and tiered by the roadmap (05-TARGET-LIST.md), with their contact channels, ordered by priority, and a guided sales process from first call to customer. Everything a seller needs is in this one file.
A5: Start here | B5: 1 · Pipeline sheet, filter Focus = Yes (Tier A and B, 37 firms). 2 · Sort by Priority rank. 3 · For each firm read Next action and Script to use — they change with the Stage. 4 · Log every touch in Activity Log. 5 · Move Stage only when the Exit criterion in Playbook is met. 6 · Dashboard shows where the week stands.
A6: Colour legend | B6: YELLOW fill = you fill this in (tracking columns). BLUE text = an input or lever you may change (probabilities, prices). BLACK text = a formula — do not overwrite. Tier colours: A green · B light green · C amber (investment case, not to contact now) · D grey (do not contact, reason given).
A7: Data caveat 1 — contacts | B7: Contact channels are only those the firm PUBLISHES (website, Google listing, marketplace profile, registry). Where a cell is blank, nothing was found by search — do not guess; enrich from SABI/eInforma or a call to the switchboard, then fill it in. Contact coverage per row and for Tier A+B is on the Dashboard.
A8: Data caveat 2 — scores | B8: Every score is capped at 63.6/100: three of five rubric dimensions could not be observed from public data (04-EXTRACTION-QA.md). Tiering is relative, not absolute. The 'Fact that confirms or demotes' column says what a first call must establish. Municipality was wrong in 30.8% of the audited sample — verify it before you drive there.
A9: Data protection | B9: Company-level, published contacts only. Do not add personal mobiles or personal email addresses. Legal basis is legitimate interest for B2B prospecting on published business data (04a-SOURCE-PLAN.md); anyone who objects is marked Lost with reason 'objected' and never contacted again. Before a pilot, the art. 28 processor agreement in Pricing & Pilot must be signed.
A10: What the product cannot promise yet | B10: It is NOT fully Verifactu-compliant on day one (Objection 9). Never say it is. The deadline for an S.L. is 1 January 2027 (03-TRIGGER-MAP.md §1) — re-check on the day of sending.
A11: A demo on their data | B11: Costs 8–16 engineering hours today (07-TAILORING-ECONOMICS.md §4) and two customers cannot yet share one stack. Book engineering before promising a demo; run at most two pilots at once.
A12: Sheets | B12: Dashboard · Pipeline (the list + tracker) · Playbook (stages, what to do, exit criteria, MEDDPICC) · Scripts (ES/CA copy) · Objections · Triggers (openers) · Pricing & Pilot · Activity Log · Lists (hidden dropdowns).
A13: Sources | B13: 05-TARGET-LIST.md (tiers, scores, reasons) · 04-PROSPECTS.jsonl + 04b-CONTACTS.jsonl (firms, contacts) · 06-VALUE-CASE.md (pricing) · 08-GTM-PLAN.md (stages, objections, MEDDPICC) · 09-OUTREACH-KIT.md (scripts) · 03-TRIGGER-MAP.md (openers) · 10-PILOT-SPEC.md (term sheet) · 12-SYNTHESIS.md (stop conditions).
A15: Swatches | B15: You fill in
B16: Input / lever (blue)
B17: Tier A
B18: Tier B
B19: Tier C
B20: Tier D

Sheet Dashboard
A1: Dashboard — where the pipeline stands
A2: All formulas. Nothing to type here.
A4: Firms by tier | D4: Firms by stage | G4: Value
A5: Tier A | B5: =COUNTIF(Pipeline!$B$2:$B$129,"A") -> 7 | D5: Not started | E5: =COUNTIF(Pipeline!$AF$2:$AF$129,"Not started") -> 128 | G5: Pipeline ACV, Focus firms (€) | H5: =SUMIFS(Pipeline!$AS$2:$AS$129,Pipeline!$C$2:$C$129,"Yes") -> 187920
A6: Tier B | B6: =COUNTIF(Pipeline!$B$2:$B$129,"B") -> 30 | D6: Research | E6: =COUNTIF(Pipeline!$AF$2:$AF$129,"Research") -> 0 | G6: Weighted pipeline (€) | H6: =SUM(Pipeline!$AT$2:$AT$129) -> 0
A7: Tier C | B7: =COUNTIF(Pipeline!$B$2:$B$129,"C") -> 13 | D7: Cold call | E7: =COUNTIF(Pipeline!$AF$2:$AF$129,"Cold call") -> 0 | G7: Customers | H7: =COUNTIF(Pipeline!$AF$2:$AF$129,"Customer") -> 0
A8: Tier D | B8: =COUNTIF(Pipeline!$B$2:$B$129,"D") -> 78 | D8: First-touch email | E8: =COUNTIF(Pipeline!$AF$2:$AF$129,"First-touch email") -> 0 | G8: Customer ACV (€) | H8: =SUMIFS(Pipeline!$AS$2:$AS$129,Pipeline!$AF$2:$AF$129,"Customer") -> 0
A9: Focus (A + B) | B9: =COUNTIF(Pipeline!$C$2:$C$129,"Yes") -> 37 | D9: Follow-up 1 | E9: =COUNTIF(Pipeline!$AF$2:$AF$129,"Follow-up 1") -> 0
A10: Focus firms with NO contact channel | B10: =COUNTIFS(Pipeline!$C$2:$C$129,"Yes",Pipeline!$AD$2:$AD$129,0) -> 20 | D10: Follow-up 2 | E10: =COUNTIF(Pipeline!$AF$2:$AF$129,"Follow-up 2") -> 0 | G10: Activity
A11: Focus firms with a phone | B11: =COUNTIFS(Pipeline!$C$2:$C$129,"Yes",Pipeline!$V$2:$V$129,"<>") -> 16 | D11: Meeting booked | E11: =COUNTIF(Pipeline!$AF$2:$AF$129,"Meeting booked") -> 0 | G11: Touches last 7 days | H11: =COUNTIFS('Activity Log'!$A$4:$A$600,">="&(TODAY()-7),'Activity Log'!$A$4:$A$600,"<="&TODAY()) -> 0
A12: Focus firms with an email | B12: =COUNTIFS(Pipeline!$C$2:$C$129,"Yes",Pipeline!$W$2:$W$129,"<>") -> 9 | D12: Meeting held | E12: =COUNTIF(Pipeline!$AF$2:$AF$129,"Meeting held") -> 0 | G12: Touches last 30 days | H12: =COUNTIFS('Activity Log'!$A$4:$A$600,">="&(TODAY()-30),'Activity Log'!$A$4:$A$600,"<="&TODAY()) -> 1
A13: Overdue next actions | B13: =COUNTIF(Pipeline!$AV$2:$AV$129,"OVERDUE") -> 0 | D13: Demo on their data | E13: =COUNTIF(Pipeline!$AF$2:$AF$129,"Demo on their data") -> 0 | G13: Calls, all time | H13: =COUNTIF('Activity Log'!$C$4:$C$600,"Call") -> 1
D14: Pilot proposed | E14: =COUNTIF(Pipeline!$AF$2:$AF$129,"Pilot proposed") -> 0 | G14: Emails, all time | H14: =COUNTIF('Activity Log'!$C$4:$C$600,"Email") -> 0
D15: Pilot running | E15: =COUNTIF(Pipeline!$AF$2:$AF$129,"Pilot running") -> 0 | G15: LinkedIns, all time | H15: =COUNTIF('Activity Log'!$C$4:$C$600,"LinkedIn") -> 0
D16: Customer | E16: =COUNTIF(Pipeline!$AF$2:$AF$129,"Customer") -> 0 | G16: Meetings, all time | H16: =COUNTIF('Activity Log'!$C$4:$C$600,"Meeting") -> 0
D17: Lost | E17: =COUNTIF(Pipeline!$AF$2:$AF$129,"Lost") -> 0 | G17: Demos, all time | H17: =COUNTIF('Activity Log'!$C$4:$C$600,"Demo") -> 0
D18: Not a fit | E18: =COUNTIF(Pipeline!$AF$2:$AF$129,"Not a fit") -> 0 | G18: Proposals, all time | H18: =COUNTIF('Activity Log'!$C$4:$C$600,"Proposal") -> 0
G19: Others, all time | H19: =COUNTIF('Activity Log'!$C$4:$C$600,"Other") -> 0
A20: Stop conditions (12-SYNTHESIS.md, Falsification) — decided before starting
A21: Condition | D21: Live proxy | E21: Now
A22: The list is not a pipeline. If fewer than 12 of the 37 Tier A+B firms can be reached by telephone and confirmed as trading renovation contractors, all outreach stops and the programme goes no further than re-extraction; the red team's rule is "fail experiment 1 and stop". Two thresholds from the same experiment re-sequence rather than stop: fewer than 8 of 37 with four or more live sites means the ICP band is wrong rather than the prospects, and more than 26 of those reached on an unsupported bank puts the N43 adapter ahead of every sales activity. | D22: A+B firms engaged (Stage past Cold call, not Lost/Not a fit) — threshold: at least 12 of 37 | E22: =COUNTIFS(Pipeline!$C$2:$C$129,"Yes",Pipeline!$AF$2:$AF$129,"<>Not started",Pipeline!$AF$2:$AF$129,"<>Research",Pipeline!$AF$2:$AF$129,"<>Cold call",Pipeline!$AF$2:$AF$129,"<>Lost",Pipeline!$AF$2:$AF$129,"<>Not a fit") -> 0
A23: The value case is not real on customer data. If the measured price spread on committed purchases is below 0.5% of third-party spend on both firms _and_ the unbilled-extras share is below 15%, then S2's captured value falls below €25,000 — a 3.9:1 value-to-price ratio, thinner than the 4.7:1 on which Phase 6 already concedes S3 — and the €540-a-month per-site price is withdrawn and the segment is not sold. A measured gestoría retainer below €250 a month for an S2 firm independently invalidates the price ceiling and Phase 6 §4 is rewritten before it is quoted again. | D23: Pilots running or converted — value case is measured on their data during the pilot | E23: =COUNTIF(Pipeline!$AF$2:$AF$129,"Pilot running")+COUNTIF(Pipeline!$AF$2:$AF$129,"Customer") -> 0
A24: The product cannot be delivered at the measured cost, on the path the customer uses. If total delivered hours on one real end-to-end onboarding exceed 40 — 2.5× the measured central of 16 — the L0 cost model, the €2,400 fee, the fee-positive finding and the 46–58% year-one margins are all false and no second pilot starts. Independently, if that firm's bank export cannot be imported without writing code, or the invoice it would actually issue does not carry the persisted rule identifier, legal basis and pack version, compliance is priced at zero in all three segments and outreach halts until the submission channel has hours and an owner. Any one of the three is a stop, not a learning. | D24: Firms at Demo or beyond — each one costs 8–16 engineering hours to build | E24: =COUNTIF(Pipeline!$AF$2:$AF$129,"Demo on their data")+COUNTIF(Pipeline!$AF$2:$AF$129,"Pilot proposed")+COUNTIF(Pipeline!$AF$2:$AF$129,"Pilot running")+COUNTIF(Pipeline!$AF$2:$AF$129,"Customer") -> 0

Sheet Pipeline
A1: Priority rank | B1: Tier | C1: Focus | D1: Segment | E1: Legal name | F1: Trade name | G1: NIF | H1: CNAE | I1: CNAE label | J1: Legal form | K1: Municipality (verify) | L1: Province | M1: Total score | N1: Confidence | O1: Layer | P1: Driving requirement | Q1: Detected triggers | R1: Rationale | S1: Why citable (Tier A) | T1: Fact that confirms or demotes | U1: Reason we lose them | V1: Phone | W1: Email | X1: Website | Y1: Contact form | Z1: LinkedIn (company) | AA1: Contact person (published) | AB1: Maps rating | AC1: Source URLs | AD1: Contact coverage | AE1: Owner | AF1: Stage | AG1: Stage date | AH1: Contact person | AI1: Role | AJ1: Preferred language | AK1: Trigger observed | AL1: Last contact | AM1: Next action due | AN1: Notes | AO1: Next action | AP1: Script to use | AQ1: Exit criterion | AR1: Probability | AS1: ACV (€) | AT1: Weighted (€) | AU1: Days since last contact | AV1: Overdue | AW1: Status
A2: 1 | B2: A | C2: =IF(OR(B2="A",B2="B"),"Yes","No") -> Yes | D2: S1 | E2: A Barcelona Reformas SL | F2: A Barcelona Reformas | G2: B63839583 | H2: 4399 | I2: Other specialised construction activities | J2: S.L. | K2: Barcelona | L2: Barcelona | M2: 63.6 | N2: Medium | O2: L0–L1 | P2: target 43.3/43.9 finishing family | Q2: Sector-default only; contact email is consumer webmail (QA gray-zone, verify before outreach) | R2: S.L. form matches the reference tenant; CNAE 4399 read as sector-confirming. | S2: Reachable by both phone and an owned domain, CNAE-confirmed, and broad enough branding ("A Barcelona Reformas," not a founder's surname) to suggest an established multi-job operation rather than a single-owner outfit — a stronger reference story for the segment than a firm whose name is one person's. | T2: 04-EXTRACTION-QA.md's whole-file audit flags this row's email (barcelonareformas@yahoo.es) as the grey-zone case the GDPR posture itself anticipates — plausibly the firm's own published contact, plausibly not. A call on the phone number confirming trading status and that the yahoo address is genuinely staffed settles it either way. | U2: The webmail address is itself a soft signal against the sale: a firm that answers commercial enquiries from a free consumer account reads as informal at the exact moment it is being pitched a system that replaces informality with structure, and a first written approach to that address risks never being opened. | V2: 932473304 | W2: barcelonareformas@yahoo.es | X2: http://www.reformasbarcelona.info | AC2: https://empresite.eleconomista.es/BARCELONA-REFORMAS.html, https://infonif.economia3.com/ficha-empresa/a-barcelona-reformas-sl, https://www.axesor.es/Informes-Empresas/3168764/A_BARCELONA_REFORMAS_SL.html, https://www.einforma.com/informacion-empresa/barcelona-reformas, https://www.infoconstruccion.es/empresas/a-barcelona-reformas | AD2: =COUNTA(V2:AA2) -> 3 | AF2: Not started | AO2: =IFERROR(INDEX(Playbook!$C$4:$C$17,MATCH($AF2,Playbook!$A$4:$A$17,0)),"") -> Read the row: tier, segment, trigger, reason we lose them. Check contact coverage; if 0, enrich before anything else. | AP2: =IFERROR(INDEX(Playbook!$D$4:$D$17,MATCH($AF2,Playbook!$A$4:$A$17,0)),"") -> — | AQ2: =IFERROR(INDEX(Playbook!$E$4:$E$17,MATCH($AF2,Playbook!$A$4:$A$17,0)),"") -> Row read and a contact channel exists | AR2: =IFERROR(INDEX(Playbook!$G$4:$G$17,MATCH($AF2,Playbook!$A$4:$A$17,0)),0) -> 0 | AS2: =IFERROR(INDEX('Pricing & Pilot'!$D$4:$D$6,MATCH($D2,'Pricing & Pilot'!$A$4:$A$6,0)),0) -> 3600 | AT2: =AS2*AR2 -> 0 | AU2: =IF(AL2="","",TODAY()-AL2) | AV2: =IF(AM2="","",IF(AND(AM2<TODAY(),$AF2<>"Customer",$AF2<>"Lost",$AF2<>"Not a fit"),"OVERDUE","")) | AW2: =IF(AV2="OVERDUE","RED",IF($AF2="Not started","—",IF($AF2="Customer","GREEN",IF(OR($AF2="Lost",$AF2="Not a fit"),"CLOSED","AMBER")))) -> —
A3: 2 | B3: A | C3: =IF(OR(B3="A",B3="B"),"Yes","No") -> Yes | D3: S2 | E3: Delgado & Dilla Construccions I Reformes Integrals SL | F3: Delgado & Dilla Construccions I Reformes Integrals | G3: B64090798 | H3: 4101 | I3: Construction of buildings (developer-builder) | J3: S.L. | K3: Mollet del Vallès | L3: Barcelona | M3: 63.6 | N3: Medium | O3: L0–L1 | P3: renovation-led 41.2 general construction | Q3: Sector-default only (Verifactu 2027 + quarterly filing cycle; no firm-specific signal in this extraction) | R3: S.L. form matches the reference tenant; CNAE 4101 read as sector-confirming. | S3: Registry-verifiable and CNAE-confirmed like the rest of this cohort, but its registered name is written in Catalan ("Construccions I Reformes Integrals," not the Spanish "Construcciones Y Reformas") — the only one of 128 rows where this is true. legal_name is the one field this audit trusts at 0% error, so this is a genuinely observed fact, not an inference, even though it cannot be scored against the rubric's Cultural dimension without a live conversation. | T3: Whether legally binding customer documents must themselves be issued in Catalan — which, if so, triggers the rubric's Catalan-reviewer soft cap (§A.5, soft gate 10) at 80 points, a fact worth knowing before pricing rather than after a contract is signed. | U3: No contact channel of any kind was recovered; a Catalan-first, two-partner firm this size is easy to reach once found, but nothing in this extraction provides the way in. | AC3: https://www.einforma.com/informacion-empresa/delgado-dilla-construccions-reformes-integrals | AD3: =COUNTA(V3:AA3) -> 0 | AF3: Not started | AO3: =IFERROR(INDEX(Playbook!$C$4:$C$17,MATCH($AF3,Playbook!$A$4:$A$17,0)),"") -> Read the row: tier, segment, trigger, reason we lose them. Check contact coverage; if 0, enrich before anything else. | AP3: =IFERROR(INDEX(Playbook!$D$4:$D$17,MATCH($AF3,Playbook!$A$4:$A$17,0)),"") -> — | AQ3: =IFERROR(INDEX(Playbook!$E$4:$E$17,MATCH($AF3,Playbook!$A$4:$A$17,0)),"") -> Row read and a contact channel exists | AR3: =IFERROR(INDEX(Playbook!$G$4:$G$17,MATCH($AF3,Playbook!$A$4:$A$17,0)),0) -> 0 | AS3: =IFERROR(INDEX('Pricing & Pilot'!$D$4:$D$6,MATCH($D3,'Pricing & Pilot'!$A$4:$A$6,0)),0) -> 6480 | AT3: =AS3*AR3 -> 0 | AU3: =IF(AL3="","",TODAY()-AL3) | AV3: =IF(AM3="","",IF(AND(AM3<TODAY(),$AF3<>"Customer",$AF3<>"Lost",$AF3<>"Not a fit"),"OVERDUE","")) | AW3: =IF(AV3="OVERDUE","RED",IF($AF3="Not started","—",IF($AF3="Customer","GREEN",IF(OR($AF3="Lost",$AF3="Not a fit"),"CLOSED","AMBER")))) -> —
A4: 3 | B4: A | C4: =IF(OR(B4="A",B4="B"),"Yes","No") -> Yes | D4: S2 | E4: Edificaciones Y Reformas Mollet 2000 SL | F4: Edificaciones Y Reformas Mollet 2000 | G4: B62393517 | H4: 4121 | I4: Construction of residential buildings | J4: S.L. | K4: Mollet del Vallès | L4: Barcelona | M4: 63.6 | N4: Medium | O4: L0–L1 | P4: renovation-led 41.2 general construction | Q4: Sector-default only; email field duplicates phone (known extraction defect, QA) | R4: S.L. form matches the reference tenant; CNAE 4121 read as sector-confirming. | S4: Registry-verifiable, CNAE-confirmed renovation-led general construction, and a "2000" in the trading name consistent with two and a half decades of trading — an established-SME story, not a two-year-old shell, if the implied founding year holds up. | T4: 04-EXTRACTION-QA.md's mechanical pass caught this exact row's email field holding the same nine digits as its own phone field — a data-entry defect, not a real address. A single call resolves the correct contact channel and confirms current trading status in one step. | U4: The outreach data itself is the risk here, not the firm: a call to a phone number that has since been reassigned or discontinued is the most likely way this one drops out of the pipeline before anyone at the firm is reached. | V4: 935702566 | W4: 935702566 | AC4: https://www.einforma.com/informacion-empresa/edificaciones-reformas-mollet-2000 | AD4: =COUNTA(V4:AA4) -> 2 | AF4: Not started | AO4: =IFERROR(INDEX(Playbook!$C$4:$C$17,MATCH($AF4,Playbook!$A$4:$A$17,0)),"") -> Read the row: tier, segment, trigger, reason we lose them. Check contact coverage; if 0, enrich before anything else. | AP4: =IFERROR(INDEX(Playbook!$D$4:$D$17,MATCH($AF4,Playbook!$A$4:$A$17,0)),"") -> — | AQ4: =IFERROR(INDEX(Playbook!$E$4:$E$17,MATCH($AF4,Playbook!$A$4:$A$17,0)),"") -> Row read and a contact channel exists | AR4: =IFERROR(INDEX(Playbook!$G$4:$G$17,MATCH($AF4,Playbook!$A$4:$A$17,0)),0) -> 0 | AS4: =IFERROR(INDEX('Pricing & Pilot'!$D$4:$D$6,MATCH($D4,'Pricing & Pilot'!$A$4:$A$6,0)),0) -> 6480 | AT4: =AS4*AR4 -> 0 | AU4: =IF(AL4="","",TODAY()-AL4) | AV4: =IF(AM4="","",IF(AND(AM4<TODAY(),$AF4<>"Customer",$AF4<>"Lost",$AF4<>"Not a fit"),"OVERDUE","")) | AW4: =IF(AV4="OVERDUE","RED",IF($AF4="Not started","—",IF($AF4="Customer","GREEN",IF(OR($AF4="Lost",$AF4="Not a fit"),"CLOSED","AMBER")))) -> —
A5: 4 | B5: A | C5: =IF(OR(B5="A",B5="B"),"Yes","No") -> Yes | D5: S1 | E5: Gonzvilarsa S.L. | F5: Gonzvilarsa | G5: B66865254 | H5: 4399 | I5: Other specialised construction activities | J5: S.L. | K5: Sant Joan Despí | L5: Barcelona | M5: 63.6 | N5: Medium | O5: L0–L1 | P5: target 43.3/43.9 finishing family | Q5: Sector-default only (Verifactu 2027 + quarterly filing cycle; no firm-specific signal in this extraction) | R5: S.L. form matches the reference tenant; CNAE 4399 read as sector-confirming. | S5: The best-evidenced row in the entire extraction: CNAE confirmed inside the 43.9x finishing family, S.L., a NIF whose B-prefix is consistent with that form, and — uniquely among the top scorers — an owned domain (gonzvilarsa.com) carrying a working contact email rather than a marketplace listing or a directory mirror. That is the one combination in this list that lets a first outreach start from the firm's own material rather than a registry stub. | T5: A quotation sample or a first call establishing the operations/administration split (02-ICP-AND-RUBRIC.md A.4.2), current job count, and quoting method. Demoted if the domain turns out to be a lead-generation or reseller front rather than an operating contractor with its own crews, or if a live incumbent accounting package surfaces (hard gate 4). | U5: The contact email is generic (contacto@…), not addressed to a named person; a cold message to a shared inbox at a firm this size is the easiest kind of outreach to lose to silence. | V5: 639648153 | W5: contacto@gonzvilarsa.com | X5: https://gonzvilarsa.com | Y5: https://gonzvilarsa.com/contacto | AC5: https://empresite.eleconomista.es/GONZVILARSA.html, https://gonzvilarsa.com/contacto, https://gonzvilarsa.com/sobre-nosotros/, https://www.einforma.com/informacion-empresa/gonzvilarsa | AD5: =COUNTA(V5:AA5) -> 4 | AF5: Not started | AO5: =IFERROR(INDEX(Playbook!$C$4:$C$17,MATCH($AF5,Playbook!$A$4:$A$17,0)),"") -> Read the row: tier, segment, trigger, reason we lose them. Check contact coverage; if 0, enrich before anything else. | AP5: =IFERROR(INDEX(Playbook!$D$4:$D$17,MATCH($AF5,Playbook!$A$4:$A$17,0)),"") -> — | AQ5: =IFERROR(INDEX(Playbook!$E$4:$E$17,MATCH($AF5,Playbook!$A$4:$A$17,0)),"") -> Row read and a contact channel exists | AR5: =IFERROR(INDEX(Playbook!$G$4:$G$17,MATCH($AF5,Playbook!$A$4:$A$17,0)),0) -> 0 | AS5: =IFERROR(INDEX('Pricing & Pilot'!$D$4:$D$6,MATCH($D5,'Pricing & Pilot'!$A$4:$A$6,0)),0) -> 3600 | AT5: =AS5*AR5 -> 0 | AU5: =IF(AL5="","",TODAY()-AL5) | AV5: =IF(AM5="","",IF(AND(AM5<TODAY(),$AF5<>"Customer",$AF5<>"Lost",$AF5<>"Not a fit"),"OVERDUE","")) | AW5: =IF(AV5="OVERDUE","RED",IF($AF5="Not started","—",IF($AF5="Customer","GREEN",IF(OR($AF5="Lost",$AF5="Not a fit"),"CLOSED","AMBER")))) -> —
A6: 5 | B6: A | C6: =IF(OR(B6="A",B6="B"),"Yes","No") -> Yes | D6: S1 | E6: Instalaciones Y Reformas De Calidad SL | F6: Instalaciones Y Reformas De Calidad | G6: B65923849 | H6: 4399 | I6: Other specialised construction activities | J6: S.L. | K6: Badalona | L6: Barcelona | M6: 63.6 | N6: Medium | O6: L0–L1 | P6: target 43.3/43.9 finishing family | Q6: Sector-default only (Verifactu 2027 + quarterly filing cycle; no firm-specific signal in this extraction) | R6: S.L. form matches the reference tenant; CNAE 4399 read as sector-confirming. | S6: Registry-verifiable, CNAE lands inside the target finishing family, and it extends the cohort's geography into the Barcelonès coastal belt (if the unverified municipality holds), which the rest of Tier A does not otherwise cover. | T6: The word "Instalaciones" in the trading name against a 43.99 "other specialised construction" code is exactly the ambiguity Phase 2 §A.5 hard gate 5 warns about: a single revenue-mix question — project work versus recurring maintenance contracts — resolves whether this is a genuine Tier A finishing firm or an installer that should sit in the Tier C pack below. | U6: The same ambiguity that makes this firm worth including is the reason it could be lost badly rather than cleanly: skipping the revenue-mix question and discovering the maintenance majority only after a contract is signed is precisely the failure mode the hard gate exists to prevent. | V6: 935334170 | W6: irc@irc-sl.com | X6: http://irc-sl.com | Y6: http://irc-sl.com/1/contactos_478106.html | AC6: http://irc-sl.com/1/contactos_478106.html, https://www.cylex.es/badalona/instalaciones-y-reformas-de-calidad--s-l--13448547.html, https://www.einforma.com/informacion-empresa/instalaciones-reformas-calidad | AD6: =COUNTA(V6:AA6) -> 4 | AF6: Not started | AO6: =IFERROR(INDEX(Playbook!$C$4:$C$17,MATCH($AF6,Playbook!$A$4:$A$17,0)),"") -> Read the row: tier, segment, trigger, reason we lose them. Check contact coverage; if 0, enrich before anything else. | AP6: =IFERROR(INDEX(Playbook!$D$4:$D$17,MATCH($AF6,Playbook!$A$4:$A$17,0)),"") -> — | AQ6: =IFERROR(INDEX(Playbook!$E$4:$E$17,MATCH($AF6,Playbook!$A$4:$A$17,0)),"") -> Row read and a contact channel exists | AR6: =IFERROR(INDEX(Playbook!$G$4:$G$17,MATCH($AF6,Playbook!$A$4:$A$17,0)),0) -> 0 | AS6: =IFERROR(INDEX('Pricing & Pilot'!$D$4:$D$6,MATCH($D6,'Pricing & Pilot'!$A$4:$A$6,0)),0) -> 3600 | AT6: =AS6*AR6 -> 0 | AU6: =IF(AL6="","",TODAY()-AL6) | AV6: =IF(AM6="","",IF(AND(AM6<TODAY(),$AF6<>"Customer",$AF6<>"Lost",$AF6<>"Not a fit"),"OVERDUE","")) | AW6: =IF(AV6="OVERDUE","RED",IF($AF6="Not started","—",IF($AF6="Customer","GREEN",IF(OR($AF6="Lost",$AF6="Not a fit"),"CLOSED","AMBER")))) -> —
A7: 6 | B7: A | C7: =IF(OR(B7="A",B7="B"),"Yes","No") -> Yes | D7: S2 | E7: Reformas Lluca Les Corts SL | F7: Reformas Lluca Les Corts | G7: B65982332 | H7: 4101 | I7: Construction of buildings (developer-builder) | J7: S.L. | K7: Sabadell | L7: Barcelona | M7: 63.6 | N7: Medium | O7: L0–L1 | P7: renovation-led 41.2 general construction | Q7: Sector-default only (Verifactu 2027 + quarterly filing cycle; no firm-specific signal in this extraction) | R7: S.L. form matches the reference tenant; CNAE 4101 read as sector-confirming. | S7: Registry-verifiable, CNAE-confirmed, and — if the unverified municipality holds — the westernmost firm in the cohort, giving Tier A geographic spread into the Vallès Occidental rather than a cluster around Barcelonès/Baix Llobregat alone. A reference here is an additive proof point, not a restatement of the other six. | T7: The name pairs a Barcelona-city neighbourhood ("Les Corts") with a Sabadell registration — worth a direct registry check on its own terms, given that 04-EXTRACTION-QA.md found exactly this shape of name/location mismatch twice already in this file (rows 67 and 110). | U7: No contact channel was recovered, compounded by the naming mismatch above: this is a firm to verify by registry pull before a call is placed, not after. --- | V7: 936241432 | AC7: https://www.einforma.com/informacion-empresa/reformas-lluca-corts | AD7: =COUNTA(V7:AA7) -> 1 | AF7: Not started | AO7: =IFERROR(INDEX(Playbook!$C$4:$C$17,MATCH($AF7,Playbook!$A$4:$A$17,0)),"") -> Read the row: tier, segment, trigger, reason we lose them. Check contact coverage; if 0, enrich before anything else. | AP7: =IFERROR(INDEX(Playbook!$D$4:$D$17,MATCH($AF7,Playbook!$A$4:$A$17,0)),"") -> — | AQ7: =IFERROR(INDEX(Playbook!$E$4:$E$17,MATCH($AF7,Playbook!$A$4:$A$17,0)),"") -> Row read and a contact channel exists | AR7: =IFERROR(INDEX(Playbook!$G$4:$G$17,MATCH($AF7,Playbook!$A$4:$A$17,0)),0) -> 0 | AS7: =IFERROR(INDEX('Pricing & Pilot'!$D$4:$D$6,MATCH($D7,'Pricing & Pilot'!$A$4:$A$6,0)),0) -> 6480 | AT7: =AS7*AR7 -> 0 | AU7: =IF(AL7="","",TODAY()-AL7) | AV7: =IF(AM7="","",IF(AND(AM7<TODAY(),$AF7<>"Customer",$AF7<>"Lost",$AF7<>"Not a fit"),"OVERDUE","")) | AW7: =IF(AV7="OVERDUE","RED",IF($AF7="Not started","—",IF($AF7="Customer","GREEN",IF(OR($AF7="Lost",$AF7="Not a fit"),"CLOSED","AMBER")))) -> —
A8: 7 | B8: A | C8: =IF(OR(B8="A",B8="B"),"Yes","No") -> Yes | D8: S1 | E8: Reformas Y Construcciones Montcada SL | F8: Reformas Y Construcciones Montcada | G8: B09675620 | H8: 4399 | I8: Other specialised construction activities | J8: S.L. | K8: Montcada i Reixac | L8: Barcelona | M8: 63.6 | N8: Medium | O8: L0–L1 | P8: target 43.3/43.9 finishing family | Q8: Sector-default only (Verifactu 2027 + quarterly filing cycle; no firm-specific signal in this extraction) | R8: S.L. form matches the reference tenant; CNAE 4399 read as sector-confirming. | S8: CNAE-confirmed target sector, S.L., NIF present, and two populated (unweighted, unaudited) context fields — employees_band "1–9" and revenue_band_eur "<1M" — that sit exactly on the ICP's lower edge, where Phase 1 §4.3 says thirty firms scored either side would settle the sweet-spot boundary cheaply. This is that boundary case, found rather than constructed. | T8: Current simultaneous job count, not headcount — Phase 2 §A.1 treats a 5–7-employee firm running three or more jobs at once as acceptable, and the same headcount running one or two jobs as below the serving floor. Job count, not the employee band, is the fact that decides which side of the line this firm sits on. | U8: No phone, email or website was recovered for this row at all; outreach depends entirely on a registered name and address, the slowest channel available and the one most likely to stall before contact is made. | X8: https://reformasycontruccionesmontcada.es/es_es/ | AC8: https://reformasycontruccionesmontcada.es/es_es/, https://www.axesor.es/Informes-Empresas/10469769/REFORMAS_Y_CONSTRUCCIONES_MONTCADA_SL.html, https://www.einforma.com/informacion-empresa/reformas-construcciones-montcada | AD8: =COUNTA(V8:AA8) -> 1 | AF8: Not started | AO8: =IFERROR(INDEX(Playbook!$C$4:$C$17,MATCH($AF8,Playbook!$A$4:$A$17,0)),"") -> Read the row: tier, segment, trigger, reason we lose them. Check contact coverage; if 0, enrich before anything else. | AP8: =IFERROR(INDEX(Playbook!$D$4:$D$17,MATCH($AF8,Playbook!$A$4:$A$17,0)),"") -> — | AQ8: =IFERROR(INDEX(Playbook!$E$4:$E$17,MATCH($AF8,Playbook!$A$4:$A$17,0)),"") -> Row read and a contact channel exists | AR8: =IFERROR(INDEX(Playbook!$G$4:$G$17,MATCH($AF8,Playbook!$A$4:$A$17,0)),0) -> 0 | AS8: =IFERROR(INDEX('Pricing & Pilot'!$D$4:$D$6,MATCH($D8,'Pricing & Pilot'!$A$4:$A$6,0)),0) -> 3600 | AT8: =AS8*AR8 -> 0 | AU8: =IF(AL8="","",TODAY()-AL8) | AV8: =IF(AM8="","",IF(AND(AM8<TODAY(),$AF8<>"Customer",$AF8<>"Lost",$AF8<>"Not a fit"),"OVERDUE","")) | AW8: =IF(AV8="OVERDUE","RED",IF($AF8="Not started","—",IF($AF8="Customer","GREEN",IF(OR($AF8="Lost",$AF8="Not a fit"),"CLOSED","AMBER")))) -> —
A9: 8 | B9: B | C9: =IF(OR(B9="A",B9="B"),"Yes","No") -> Yes | D9: S1 | E9: Aislamientos Gramanet SL | F9: Aislamientos Gramanet | H9: 4342 | I9: Division 43 — specialised construction | J9: S.L. | K9: Santa Coloma de Gramenet | L9: Barcelona | M9: 63.6 | N9: Medium | O9: L0–L1 | P9: target 43.3/43.9 finishing family | Q9: Sector-default only (Verifactu 2027 + quarterly filing cycle; no firm-specific signal in this extraction) | R9: S.L. form matches the reference tenant; CNAE 4342 read as sector-confirming. | U9: No differentiator over the Tier A cohort beyond order of contact — pure reachability risk: someone calls it before we do, or the CNAE/legal-form match turns out wrong on registry check | V9: 933918025 | W9: aisgrasl@gmail.com | X9: https://www.aisgrasl.es | AC9: https://empresite.eleconomista.es/AISLAMIENTOS-GRAMANET.html, https://www.aisgrasl.es/, https://www.einforma.com/informacion-empresa/aislamientos-gramanet | AD9: =COUNTA(V9:AA9) -> 3 | AF9: Not started | AO9: =IFERROR(INDEX(Playbook!$C$4:$C$17,MATCH($AF9,Playbook!$A$4:$A$17,0)),"") -> Read the row: tier, segment, trigger, reason we lose them. Check contact coverage; if 0, enrich before anything else. | AP9: =IFERROR(INDEX(Playbook!$D$4:$D$17,MATCH($AF9,Playbook!$A$4:$A$17,0)),"") -> — | AQ9: =IFERROR(INDEX(Playbook!$E$4:$E$17,MATCH($AF9,Playbook!$A$4:$A$17,0)),"") -> Row read and a contact channel exists | AR9: =IFERROR(INDEX(Playbook!$G$4:$G$17,MATCH($AF9,Playbook!$A$4:$A$17,0)),0) -> 0 | AS9: =IFERROR(INDEX('Pricing & Pilot'!$D$4:$D$6,MATCH($D9,'Pricing & Pilot'!$A$4:$A$6,0)),0) -> 3600 | AT9: =AS9*AR9 -> 0 | AU9: =IF(AL9="","",TODAY()-AL9) | AV9: =IF(AM9="","",IF(AND(AM9<TODAY(),$AF9<>"Customer",$AF9<>"Lost",$AF9<>"Not a fit"),"OVERDUE","")) | AW9: =IF(AV9="OVERDUE","RED",IF($AF9="Not started","—",IF($AF9="Customer","GREEN",IF(OR($AF9="Lost",$AF9="Not a fit"),"CLOSED","AMBER")))) -> —
A10: 9 | B10: B | C10: =IF(OR(B10="A",B10="B"),"Yes","No") -> Yes | D10: S2 | E10: Arquitectura Y Konstruccion De Obras Barcelona SL | F10: Arquitectura Y Konstruccion | H10: 4100 | I10: Division 41 — building construction | J10: S.L. | K10: Barcelona | L10: Barcelona | M10: 63.6 | N10: Medium | O10: L0–L1 | P10: renovation-led 41.2 general construction | Q10: Sector-default only (Verifactu 2027 + quarterly filing cycle; no firm-specific signal in this extraction) | R10: S.L. form matches the reference tenant; CNAE 4100 read as sector-confirming. | U10: No differentiator over the Tier A cohort beyond order of contact — pure reachability risk: someone calls it before we do, or the CNAE/legal-form match turns out wrong on registry check | V10: 934106705 | W10: arkobcn@arkobcn.com | X10: https://arkobcn.com | Y10: https://arkobcn.com/contacto/ | Z10: https://www.linkedin.com/company/arkobcn | AC10: https://arkobcn.com/contacto/, https://es.linkedin.com/company/arkobcn, https://ranking-empresas.eleconomista.es/ARQUITECTURA-KONSTRUCCION-OBRAS-BARCELONA.html, https://www.einforma.com/informacion-empresa/arquitectura-konstruccion-obras-barcelona | AD10: =COUNTA(V10:AA10) -> 5 | AF10: Not started | AO10: =IFERROR(INDEX(Playbook!$C$4:$C$17,MATCH($AF10,Playbook!$A$4:$A$17,0)),"") -> Read the row: tier, segment, trigger, reason we lose them. Check contact coverage; if 0, enrich before anything else. | AP10: =IFERROR(INDEX(Playbook!$D$4:$D$17,MATCH($AF10,Playbook!$A$4:$A$17,0)),"") -> — | AQ10: =IFERROR(INDEX(Playbook!$E$4:$E$17,MATCH($AF10,Playbook!$A$4:$A$17,0)),"") -> Row read and a contact channel exists | AR10: =IFERROR(INDEX(Playbook!$G$4:$G$17,MATCH($AF10,Playbook!$A$4:$A$17,0)),0) -> 0 | AS10: =IFERROR(INDEX('Pricing & Pilot'!$D$4:$D$6,MATCH($D10,'Pricing & Pilot'!$A$4:$A$6,0)),0) -> 6480 | AT10: =AS10*AR10 -> 0 | AU10: =IF(AL10="","",TODAY()-AL10) | AV10: =IF(AM10="","",IF(AND(AM10<TODAY(),$AF10<>"Customer",$AF10<>"Lost",$AF10<>"Not a fit"),"OVERDUE","")) | AW10: =IF(AV10="OVERDUE","RED",IF($AF10="Not started","—",IF($AF10="Customer","GREEN",IF(OR($AF10="Lost",$AF10="Not a fit"),"CLOSED","AMBER")))) -> —
A11: 10 | B11: B | C11: =IF(OR(B11="A",B11="B"),"Yes","No") -> Yes | D11: S2 | E11: BCN Portal Reformas SL | F11: BCN Portal Reformas | H11: 4121 | I11: Construction of residential buildings | J11: S.L. | K11: Barcelona | L11: Barcelona | M11: 63.6 | N11: Medium | O11: L0–L1 | P11: renovation-led 41.2 general construction | Q11: Sector-default only (Verifactu 2027 + quarterly filing cycle; no firm-specific signal in this extraction) | R11: S.L. form matches the reference tenant; CNAE 4121 read as sector-confirming. | U11: No differentiator over the Tier A cohort beyond order of contact — pure reachability risk: someone calls it before we do, or the CNAE/legal-form match turns out wrong on registry check | AC11: https://www.einforma.com/informacion-empresa/bcn-portal-reformas | AD11: =COUNTA(V11:AA11) -> 0 | AF11: Not started | AO11: =IFERROR(INDEX(Playbook!$C$4:$C$17,MATCH($AF11,Playbook!$A$4:$A$17,0)),"") -> Read the row: tier, segment, trigger, reason we lose them. Check contact coverage; if 0, enrich before anything else. | AP11: =IFERROR(INDEX(Playbook!$D$4:$D$17,MATCH($AF11,Playbook!$A$4:$A$17,0)),"") -> — | AQ11: =IFERROR(INDEX(Playbook!$E$4:$E$17,MATCH($AF11,Playbook!$A$4:$A$17,0)),"") -> Row read and a contact channel exists | AR11: =IFERROR(INDEX(Playbook!$G$4:$G$17,MATCH($AF11,Playbook!$A$4:$A$17,0)),0) -> 0 | AS11: =IFERROR(INDEX('Pricing & Pilot'!$D$4:$D$6,MATCH($D11,'Pricing & Pilot'!$A$4:$A$6,0)),0) -> 6480 | AT11: =AS11*AR11 -> 0 | AU11: =IF(AL11="","",TODAY()-AL11) | AV11: =IF(AM11="","",IF(AND(AM11<TODAY(),$AF11<>"Customer",$AF11<>"Lost",$AF11<>"Not a fit"),"OVERDUE","")) | AW11: =IF(AV11="OVERDUE","RED",IF($AF11="Not started","—",IF($AF11="Customer","GREEN",IF(OR($AF11="Lost",$AF11="Not a fit"),"CLOSED","AMBER")))) -> —
A12: 11 | B12: B | C12: =IF(OR(B12="A",B12="B"),"Yes","No") -> Yes | D12: S2 | E12: CARMAREFOR S.L. | F12: Carmarefor | H12: 4121 | I12: Construction of residential buildings | J12: S.L. | K12: Sant Feliu de Llobregat | L12: Barcelona | M12: 63.6 | N12: Medium | O12: L0–L1 | P12: renovation-led 41.2 general construction | Q12: Sector-default only (Verifactu 2027 + quarterly filing cycle; no firm-specific signal in this extraction) | R12: S.L. form matches the reference tenant; CNAE 4121 read as sector-confirming. | U12: No differentiator over the Tier A cohort beyond order of contact — pure reachability risk: someone calls it before we do, or the CNAE/legal-form match turns out wrong on registry check | V12: 931295839 | W12: carma.refor@hotmail.es | AC12: https://www.einforma.com/informacion-empresa/carmarefor, https://www.houzz.es/profesionales/empresas-de-reformas/carmarefor-sl-pfvwes-pf~505590728 | AD12: =COUNTA(V12:AA12) -> 2 | AF12: Not started | AO12: =IFERROR(INDEX(Playbook!$C$4:$C$17,MATCH($AF12,Playbook!$A$4:$A$17,0)),"") -> Read the row: tier, segment, trigger, reason we lose them. Check contact coverage; if 0, enrich before anything else. | AP12: =IFERROR(INDEX(Playbook!$D$4:$D$17,MATCH($AF12,Playbook!$A$4:$A$17,0)),"") -> — | AQ12: =IFERROR(INDEX(Playbook!$E$4:$E$17,MATCH($AF12,Playbook!$A$4:$A$17,0)),"") -> Row read and a contact channel exists | AR12: =IFERROR(INDEX(Playbook!$G$4:$G$17,MATCH($AF12,Playbook!$A$4:$A$17,0)),0) -> 0 | AS12: =IFERROR(INDEX('Pricing & Pilot'!$D$4:$D$6,MATCH($D12,'Pricing & Pilot'!$A$4:$A$6,0)),0) -> 6480 | AT12: =AS12*AR12 -> 0 | AU12: =IF(AL12="","",TODAY()-AL12) | AV12: =IF(AM12="","",IF(AND(AM12<TODAY(),$AF12<>"Customer",$AF12<>"Lost",$AF12<>"Not a fit"),"OVERDUE","")) | AW12: =IF(AV12="OVERDUE","RED",IF($AF12="Not started","—",IF($AF12="Customer","GREEN",IF(OR($AF12="Lost",$AF12="Not a fit"),"CLOSED","AMBER")))) -> —
A13: 12 | B13: B | C13: =IF(OR(B13="A",B13="B"),"Yes","No") -> Yes | D13: S2 | E13: Construcciones Gramasat SL | F13: Construcciones Gramasat | G13: B63763551 | H13: 4102 | I13: Division 41 — building construction | J13: S.L. | K13: Santa Coloma de Gramenet | L13: Barcelona | M13: 63.6 | N13: Medium | O13: L0–L1 | P13: renovation-led 41.2 general construction | Q13: Sector-default only (Verifactu 2027 + quarterly filing cycle; no firm-specific signal in this extraction) | R13: S.L. form matches the reference tenant; CNAE 4102 read as sector-confirming. | U13: No differentiator over the Tier A cohort beyond order of contact — pure reachability risk: someone calls it before we do, or the CNAE/legal-form match turns out wrong on registry check | AC13: https://infonif.economia3.com/ficha-empresa/construcciones-gramasat-sl, https://www.einforma.com/informacion-empresa/construcciones-gramasat | AD13: =COUNTA(V13:AA13) -> 0 | AF13: Not started | AO13: =IFERROR(INDEX(Playbook!$C$4:$C$17,MATCH($AF13,Playbook!$A$4:$A$17,0)),"") -> Read the row: tier, segment, trigger, reason we lose them. Check contact coverage; if 0, enrich before anything else. | AP13: =IFERROR(INDEX(Playbook!$D$4:$D$17,MATCH($AF13,Playbook!$A$4:$A$17,0)),"") -> — | AQ13: =IFERROR(INDEX(Playbook!$E$4:$E$17,MATCH($AF13,Playbook!$A$4:$A$17,0)),"") -> Row read and a contact channel exists | AR13: =IFERROR(INDEX(Playbook!$G$4:$G$17,MATCH($AF13,Playbook!$A$4:$A$17,0)),0) -> 0 | AS13: =IFERROR(INDEX('Pricing & Pilot'!$D$4:$D$6,MATCH($D13,'Pricing & Pilot'!$A$4:$A$6,0)),0) -> 6480 | AT13: =AS13*AR13 -> 0 | AU13: =IF(AL13="","",TODAY()-AL13) | AV13: =IF(AM13="","",IF(AND(AM13<TODAY(),$AF13<>"Customer",$AF13<>"Lost",$AF13<>"Not a fit"),"OVERDUE","")) | AW13: =IF(AV13="OVERDUE","RED",IF($AF13="Not started","—",IF($AF13="Customer","GREEN",IF(OR($AF13="Lost",$AF13="Not a fit"),"CLOSED","AMBER")))) -> —
A14: 13 | B14: B | C14: =IF(OR(B14="A",B14="B"),"Yes","No") -> Yes | D14: S2 | E14: Construcciones Reformas Y Servicios Mataro SL | F14: Construcciones Reformas Y Servicios Mataro | G14: B67185942 | H14: 4121 | I14: Construction of residential buildings | J14: S.L. | K14: Mataró | L14: Barcelona | M14: 63.6 | N14: Medium | O14: L0–L1 | P14: renovation-led 41.2 general construction | Q14: Sector-default only (Verifactu 2027 + quarterly filing cycle; no firm-specific signal in this extraction) | R14: S.L. form matches the reference tenant; CNAE 4121 read as sector-confirming. | U14: No differentiator over the Tier A cohort beyond order of contact — pure reachability risk: someone calls it before we do, or the CNAE/legal-form match turns out wrong on registry check | AC14: https://empresite.eleconomista.es/CONSTRUCCIONES-REFORMAS-SERVICIOS-MATARO.html | AD14: =COUNTA(V14:AA14) -> 0 | AF14: Not started | AO14: =IFERROR(INDEX(Playbook!$C$4:$C$17,MATCH($AF14,Playbook!$A$4:$A$17,0)),"") -> Read the row: tier, segment, trigger, reason we lose them. Check contact coverage; if 0, enrich before anything else. | AP14: =IFERROR(INDEX(Playbook!$D$4:$D$17,MATCH($AF14,Playbook!$A$4:$A$17,0)),"") -> — | AQ14: =IFERROR(INDEX(Playbook!$E$4:$E$17,MATCH($AF14,Playbook!$A$4:$A$17,0)),"") -> Row read and a contact channel exists | AR14: =IFERROR(INDEX(Playbook!$G$4:$G$17,MATCH($AF14,Playbook!$A$4:$A$17,0)),0) -> 0 | AS14: =IFERROR(INDEX('Pricing & Pilot'!$D$4:$D$6,MATCH($D14,'Pricing & Pilot'!$A$4:$A$6,0)),0) -> 6480 | AT14: =AS14*AR14 -> 0 | AU14: =IF(AL14="","",TODAY()-AL14) | AV14: =IF(AM14="","",IF(AND(AM14<TODAY(),$AF14<>"Customer",$AF14<>"Lost",$AF14<>"Not a fit"),"OVERDUE","")) | AW14: =IF(AV14="OVERDUE","RED",IF($AF14="Not started","—",IF($AF14="Customer","GREEN",IF(OR($AF14="Lost",$AF14="Not a fit"),"CLOSED","AMBER")))) -> —
A15: 14 | B15: B | C15: =IF(OR(B15="A",B15="B"),"Yes","No") -> Yes | D15: S2 | E15: Construcciones y Reformas Bonilla S.L. | F15: Construcciones y Reformas Bonilla | G15: B63037907 | H15: 4101 | I15: Construction of buildings (developer-builder) | J15: S.L. | K15: Esplugues de Llobregat | L15: Barcelona | M15: 63.6 | N15: Medium | O15: L0–L1 | P15: renovation-led 41.2 general construction | Q15: Sector-default only (Verifactu 2027 + quarterly filing cycle; no firm-specific signal in this extraction) | R15: S.L. form matches the reference tenant; CNAE 4101 read as sector-confirming. | U15: No differentiator over the Tier A cohort beyond order of contact — pure reachability risk: someone calls it before we do, or the CNAE/legal-form match turns out wrong on registry check | AC15: https://www.einforma.com/informacion-empresa/construcciones-reformas-bonilla | AD15: =COUNTA(V15:AA15) -> 0 | AF15: Not started | AO15: =IFERROR(INDEX(Playbook!$C$4:$C$17,MATCH($AF15,Playbook!$A$4:$A$17,0)),"") -> Read the row: tier, segment, trigger, reason we lose them. Check contact coverage; if 0, enrich before anything else. | AP15: =IFERROR(INDEX(Playbook!$D$4:$D$17,MATCH($AF15,Playbook!$A$4:$A$17,0)),"") -> — | AQ15: =IFERROR(INDEX(Playbook!$E$4:$E$17,MATCH($AF15,Playbook!$A$4:$A$17,0)),"") -> Row read and a contact channel exists | AR15: =IFERROR(INDEX(Playbook!$G$4:$G$17,MATCH($AF15,Playbook!$A$4:$A$17,0)),0) -> 0 | AS15: =IFERROR(INDEX('Pricing & Pilot'!$D$4:$D$6,MATCH($D15,'Pricing & Pilot'!$A$4:$A$6,0)),0) -> 6480 | AT15: =AS15*AR15 -> 0 | AU15: =IF(AL15="","",TODAY()-AL15) | AV15: =IF(AM15="","",IF(AND(AM15<TODAY(),$AF15<>"Customer",$AF15<>"Lost",$AF15<>"Not a fit"),"OVERDUE","")) | AW15: =IF(AV15="OVERDUE","RED",IF($AF15="Not started","—",IF($AF15="Customer","GREEN",IF(OR($AF15="Lost",$AF15="Not a fit"),"CLOSED","AMBER")))) -> —
A16: 15 | B16: B | C16: =IF(OR(B16="A",B16="B"),"Yes","No") -> Yes | D16: S2 | E16: Construcciones Y Reformas Decorhogar SL | F16: Construcciones Y Reformas Decorhogar | H16: 4101 | I16: Construction of buildings (developer-builder) | J16: S.L. | K16: Granollers | L16: Barcelona | M16: 63.6 | N16: Medium | O16: L0–L1 | P16: renovation-led 41.2 general construction | Q16: Sector-default only (Verifactu 2027 + quarterly filing cycle; no firm-specific signal in this extraction) | R16: S.L. form matches the reference tenant; CNAE 4101 read as sector-confirming. | U16: No differentiator over the Tier A cohort beyond order of contact — pure reachability risk: someone calls it before we do, or the CNAE/legal-form match turns out wrong on registry check | V16: 938796333 | AC16: https://www.einforma.com/informacion-empresa/construcciones-reformas-decorhogar, https://www.vipreformas.es/empresa/decorhogar/fa14ace7b3ae2d7e7ee6f1bc3129fbec/ | AD16: =COUNTA(V16:AA16) -> 1 | AF16: Not started | AO16: =IFERROR(INDEX(Playbook!$C$4:$C$17,MATCH($AF16,Playbook!$A$4:$A$17,0)),"") -> Read the row: tier, segment, trigger, reason we lose them. Check contact coverage; if 0, enrich before anything else. | AP16: =IFERROR(INDEX(Playbook!$D$4:$D$17,MATCH($AF16,Playbook!$A$4:$A$17,0)),"") -> — | AQ16: =IFERROR(INDEX(Playbook!$E$4:$E$17,MATCH($AF16,Playbook!$A$4:$A$17,0)),"") -> Row read and a contact channel exists | AR16: =IFERROR(INDEX(Playbook!$G$4:$G$17,MATCH($AF16,Playbook!$A$4:$A$17,0)),0) -> 0 | AS16: =IFERROR(INDEX('Pricing & Pilot'!$D$4:$D$6,MATCH($D16,'Pricing & Pilot'!$A$4:$A$6,0)),0) -> 6480 | AT16: =AS16*AR16 -> 0 | AU16: =IF(AL16="","",TODAY()-AL16) | AV16: =IF(AM16="","",IF(AND(AM16<TODAY(),$AF16<>"Customer",$AF16<>"Lost",$AF16<>"Not a fit"),"OVERDUE","")) | AW16: =IF(AV16="OVERDUE","RED",IF($AF16="Not started","—",IF($AF16="Customer","GREEN",IF(OR($AF16="Lost",$AF16="Not a fit"),"CLOSED","AMBER")))) -> —
A17: 16 | B17: B | C17: =IF(OR(B17="A",B17="B"),"Yes","No") -> Yes | D17: S2 | E17: Construmed Bcn SL | F17: Construmed Bcn | H17: 4100 | I17: Division 41 — building construction | J17: S.L. | K17: Barcelona | L17: Barcelona | M17: 63.6 | N17: Medium | O17: L0–L1 | P17: renovation-led 41.2 general construction | Q17: Sector-default only (Verifactu 2027 + quarterly filing cycle; no firm-specific signal in this extraction) | R17: S.L. form matches the reference tenant; CNAE 4100 read as sector-confirming. | U17: No differentiator over the Tier A cohort beyond order of contact — pure reachability risk: someone calls it before we do, or the CNAE/legal-form match turns out wrong on registry check | AC17: https://infonif.economia3.com/ficha-empresa/construmed-bcn-sl, https://www.einforma.com/informacion-empresa/construmed-bcn | AD17: =COUNTA(V17:AA17) -> 0 | AF17: Not started | AO17: =IFERROR(INDEX(Playbook!$C$4:$C$17,MATCH($AF17,Playbook!$A$4:$A$17,0)),"") -> Read the row: tier, segment, trigger, reason we lose them. Check contact coverage; if 0, enrich before anything else. | AP17: =IFERROR(INDEX(Playbook!$D$4:$D$17,MATCH($AF17,Playbook!$A$4:$A$17,0)),"") -> — | AQ17: =IFERROR(INDEX(Playbook!$E$4:$E$17,MATCH($AF17,Playbook!$A$4:$A$17,0)),"") -> Row read and a contact channel exists | AR17: =IFERROR(INDEX(Playbook!$G$4:$G$17,MATCH($AF17,Playbook!$A$4:$A$17,0)),0) -> 0 | AS17: =IFERROR(INDEX('Pricing & Pilot'!$D$4:$D$6,MATCH($D17,'Pricing & Pilot'!$A$4:$A$6,0)),0) -> 6480 | AT17: =AS17*AR17 -> 0 | AU17: =IF(AL17="","",TODAY()-AL17) | AV17: =IF(AM17="","",IF(AND(AM17<TODAY(),$AF17<>"Customer",$AF17<>"Lost",$AF17<>"Not a fit"),"OVERDUE","")) | AW17: =IF(AV17="OVERDUE","RED",IF($AF17="Not started","—",IF($AF17="Customer","GREEN",IF(OR($AF17="Lost",$AF17="Not a fit"),"CLOSED","AMBER")))) -> —
A18: 17 | B18: B | C18: =IF(OR(B18="A",B18="B"),"Yes","No") -> Yes | D18: S2 | E18: Derribos Y Reformas Terrassa SL | F18: Derribos Y Reformas Terrassa | H18: 41 | I18: Division 41 — building construction | J18: S.L. | K18: Terrassa | L18: Barcelona | M18: 63.6 | N18: Medium | O18: L0–L1 | P18: renovation-led 41.2 general construction | Q18: Sector-default only (Verifactu 2027 + quarterly filing cycle; no firm-specific signal in this extraction) | R18: S.L. form matches the reference tenant; CNAE 41 read as sector-confirming. | U18: No differentiator over the Tier A cohort beyond order of contact — pure reachability risk: someone calls it before we do, or the CNAE/legal-form match turns out wrong on registry check | AC18: https://www.axesor.es/Informes-Empresas/9423521/DERRIBOS_Y_REFORMAS_TERRASSA_SL.html, https://www.einforma.com/informacion-empresa/derribos-reformas-terrassa | AD18: =COUNTA(V18:AA18) -> 0 | AF18: Not started | AO18: =IFERROR(INDEX(Playbook!$C$4:$C$17,MATCH($AF18,Playbook!$A$4:$A$17,0)),"") -> Read the row: tier, segment, trigger, reason we lose them. Check contact coverage; if 0, enrich before anything else. | AP18: =IFERROR(INDEX(Playbook!$D$4:$D$17,MATCH($AF18,Playbook!$A$4:$A$17,0)),"") -> — | AQ18: =IFERROR(INDEX(Playbook!$E$4:$E$17,MATCH($AF18,Playbook!$A$4:$A$17,0)),"") -> Row read and a contact channel exists | AR18: =IFERROR(INDEX(Playbook!$G$4:$G$17,MATCH($AF18,Playbook!$A$4:$A$17,0)),0) -> 0 | AS18: =IFERROR(INDEX('Pricing & Pilot'!$D$4:$D$6,MATCH($D18,'Pricing & Pilot'!$A$4:$A$6,0)),0) -> 6480 | AT18: =AS18*AR18 -> 0 | AU18: =IF(AL18="","",TODAY()-AL18) | AV18: =IF(AM18="","",IF(AND(AM18<TODAY(),$AF18<>"Customer",$AF18<>"Lost",$AF18<>"Not a fit"),"OVERDUE","")) | AW18: =IF(AV18="OVERDUE","RED",IF($AF18="Not started","—",IF($AF18="Customer","GREEN",IF(OR($AF18="Lost",$AF18="Not a fit"),"CLOSED","AMBER")))) -> —
A19: 18 | B19: B | C19: =IF(OR(B19="A",B19="B"),"Yes","No") -> Yes | D19: S2 | E19: Estudios-Reformas Y Mantenimientos SL | F19: Estudios-Reformas Y Mantenimientos | H19: 4101 | I19: Construction of buildings (developer-builder) | J19: S.L. | K19: Barcelona | L19: Barcelona | M19: 63.6 | N19: Medium | O19: L0–L1 | P19: renovation-led 41.2 general construction | Q19: Sector-default only (Verifactu 2027 + quarterly filing cycle; no firm-specific signal in this extraction) | R19: S.L. form matches the reference tenant; CNAE 4101 read as sector-confirming. | U19: No differentiator over the Tier A cohort beyond order of contact — pure reachability risk: someone calls it before we do, or the CNAE/legal-form match turns out wrong on registry check | V19: 934511465 | AC19: https://www.einforma.com/informacion-empresa/estudios-reformas-mantenimientos | AD19: =COUNTA(V19:AA19) -> 1 | AF19: Not started | AO19: =IFERROR(INDEX(Playbook!$C$4:$C$17,MATCH($AF19,Playbook!$A$4:$A$17,0)),"") -> Read the row: tier, segment, trigger, reason we lose them. Check contact coverage; if 0, enrich before anything else. | AP19: =IFERROR(INDEX(Playbook!$D$4:$D$17,MATCH($AF19,Playbook!$A$4:$A$17,0)),"") -> — | AQ19: =IFERROR(INDEX(Playbook!$E$4:$E$17,MATCH($AF19,Playbook!$A$4:$A$17,0)),"") -> Row read and a contact channel exists | AR19: =IFERROR(INDEX(Playbook!$G$4:$G$17,MATCH($AF19,Playbook!$A$4:$A$17,0)),0) -> 0 | AS19: =IFERROR(INDEX('Pricing & Pilot'!$D$4:$D$6,MATCH($D19,'Pricing & Pilot'!$A$4:$A$6,0)),0) -> 6480 | AT19: =AS19*AR19 -> 0 | AU19: =IF(AL19="","",TODAY()-AL19) | AV19: =IF(AM19="","",IF(AND(AM19<TODAY(),$AF19<>"Customer",$AF19<>"Lost",$AF19<>"Not a fit"),"OVERDUE","")) | AW19: =IF(AV19="OVERDUE","RED",IF($AF19="Not started","—",IF($AF19="Customer","GREEN",IF(OR($AF19="Lost",$AF19="Not a fit"),"CLOSED","AMBER")))) -> —
A20: 19 | B20: B | C20: =IF(OR(B20="A",B20="B"),"Yes","No") -> Yes | D20: S2 | E20: JV Reformas En General SL | F20: JV Reformas En General | G20: B44928752 | H20: 4101 | I20: Construction of buildings (developer-builder) | J20: S.L. | K20: Barcelona | L20: Barcelona | M20: 63.6 | N20: Medium | O20: L0–L1 | P20: renovation-led 41.2 general construction | Q20: Sector-default only (Verifactu 2027 + quarterly filing cycle; no firm-specific signal in this extraction) | R20: S.L. form matches the reference tenant; CNAE 4101 read as sector-confirming. | U20: No differentiator over the Tier A cohort beyond order of contact — pure reachability risk: someone calls it before we do, or the CNAE/legal-form match turns out wrong on registry check | AC20: https://www.einforma.com/informacion-empresa/jv-reformas-general | AD20: =COUNTA(V20:AA20) -> 0 | AF20: Not started | AO20: =IFERROR(INDEX(Playbook!$C$4:$C$17,MATCH($AF20,Playbook!$A$4:$A$17,0)),"") -> Read the row: tier, segment, trigger, reason we lose them. Check contact coverage; if 0, enrich before anything else. | AP20: =IFERROR(INDEX(Playbook!$D$4:$D$17,MATCH($AF20,Playbook!$A$4:$A$17,0)),"") -> — | AQ20: =IFERROR(INDEX(Playbook!$E$4:$E$17,MATCH($AF20,Playbook!$A$4:$A$17,0)),"") -> Row read and a contact channel exists | AR20: =IFERROR(INDEX(Playbook!$G$4:$G$17,MATCH($AF20,Playbook!$A$4:$A$17,0)),0) -> 0 | AS20: =IFERROR(INDEX('Pricing & Pilot'!$D$4:$D$6,MATCH($D20,'Pricing & Pilot'!$A$4:$A$6,0)),0) -> 6480 | AT20: =AS20*AR20 -> 0 | AU20: =IF(AL20="","",TODAY()-AL20) | AV20: =IF(AM20="","",IF(AND(AM20<TODAY(),$AF20<>"Customer",$AF20<>"Lost",$AF20<>"Not a fit"),"OVERDUE","")) | AW20: =IF(AV20="OVERDUE","RED",IF($AF20="Not started","—",IF($AF20="Customer","GREEN",IF(OR($AF20="Lost",$AF20="Not a fit"),"CLOSED","AMBER")))) -> —
A21: 20 | B21: B | C21: =IF(OR(B21="A",B21="B"),"Yes","No") -> Yes | D21: S1 | E21: LEM Reforma de Espacios S.L. | F21: LEM Reforma de Espacios | H21: 4399 | I21: Other specialised construction activities | J21: S.L. | K21: L'Hospitalet de Llobregat | L21: Barcelona | M21: 63.6 | N21: Medium | O21: L0–L1 | P21: target 43.3/43.9 finishing family | Q21: Sector-default only (Verifactu 2027 + quarterly filing cycle; no firm-specific signal in this extraction) | R21: S.L. form matches the reference tenant; CNAE 4399 read as sector-confirming. | U21: No differentiator over the Tier A cohort beyond order of contact — pure reachability risk: someone calls it before we do, or the CNAE/legal-form match turns out wrong on registry check | AC21: https://www.einforma.com/informacion-empresa/lem-reforma-espacios | AD21: =COUNTA(V21:AA21) -> 0 | AF21: Not started | AO21: =IFERROR(INDEX(Playbook!$C$4:$C$17,MATCH($AF21,Playbook!$A$4:$A$17,0)),"") -> Read the row: tier, segment, trigger, reason we lose them. Check contact coverage; if 0, enrich before anything else. | AP21: =IFERROR(INDEX(Playbook!$D$4:$D$17,MATCH($AF21,Playbook!$A$4:$A$17,0)),"") -> — | AQ21: =IFERROR(INDEX(Playbook!$E$4:$E$17,MATCH($AF21,Playbook!$A$4:$A$17,0)),"") -> Row read and a contact channel exists | AR21: =IFERROR(INDEX(Playbook!$G$4:$G$17,MATCH($AF21,Playbook!$A$4:$A$17,0)),0) -> 0 | AS21: =IFERROR(INDEX('Pricing & Pilot'!$D$4:$D$6,MATCH($D21,'Pricing & Pilot'!$A$4:$A$6,0)),0) -> 3600 | AT21: =AS21*AR21 -> 0 | AU21: =IF(AL21="","",TODAY()-AL21) | AV21: =IF(AM21="","",IF(AND(AM21<TODAY(),$AF21<>"Customer",$AF21<>"Lost",$AF21<>"Not a fit"),"OVERDUE","")) | AW21: =IF(AV21="OVERDUE","RED",IF($AF21="Not started","—",IF($AF21="Customer","GREEN",IF(OR($AF21="Lost",$AF21="Not a fit"),"CLOSED","AMBER")))) -> —
A22: 21 | B22: B | C22: =IF(OR(B22="A",B22="B"),"Yes","No") -> Yes | D22: S2 | E22: NALSUR Reformas S.L. | F22: NALSUR | G22: B01723030 | H22: 4121 | I22: Construction of residential buildings | J22: S.L. | K22: Cornellà de Llobregat | L22: Barcelona | M22: 63.6 | N22: Medium | O22: L0–L1 | P22: renovation-led 41.2 general construction | Q22: Sector-default only (Verifactu 2027 + quarterly filing cycle; no firm-specific signal in this extraction) | R22: S.L. form matches the reference tenant; CNAE 4121 read as sector-confirming. | U22: No differentiator over the Tier A cohort beyond order of contact — pure reachability risk: someone calls it before we do, or the CNAE/legal-form match turns out wrong on registry check | AC22: https://infonif.economia3.com/ficha-empresa/nalsur-reformas-sl, https://www.einforma.com/informacion-empresa/nalsur-reformas | AD22: =COUNTA(V22:AA22) -> 0 | AF22: Not started | AO22: =IFERROR(INDEX(Playbook!$C$4:$C$17,MATCH($AF22,Playbook!$A$4:$A$17,0)),"") -> Read the row: tier, segment, trigger, reason we lose them. Check contact coverage; if 0, enrich before anything else. | AP22: =IFERROR(INDEX(Playbook!$D$4:$D$17,MATCH($AF22,Playbook!$A$4:$A$17,0)),"") -> — | AQ22: =IFERROR(INDEX(Playbook!$E$4:$E$17,MATCH($AF22,Playbook!$A$4:$A$17,0)),"") -> Row read and a contact channel exists | AR22: =IFERROR(INDEX(Playbook!$G$4:$G$17,MATCH($AF22,Playbook!$A$4:$A$17,0)),0) -> 0 | AS22: =IFERROR(INDEX('Pricing & Pilot'!$D$4:$D$6,MATCH($D22,'Pricing & Pilot'!$A$4:$A$6,0)),0) -> 6480 | AT22: =AS22*AR22 -> 0 | AU22: =IF(AL22="","",TODAY()-AL22) | AV22: =IF(AM22="","",IF(AND(AM22<TODAY(),$AF22<>"Customer",$AF22<>"Lost",$AF22<>"Not a fit"),"OVERDUE","")) | AW22: =IF(AV22="OVERDUE","RED",IF($AF22="Not started","—",IF($AF22="Customer","GREEN",IF(OR($AF22="Lost",$AF22="Not a fit"),"CLOSED","AMBER")))) -> —
A23: 22 | B23: B | C23: =IF(OR(B23="A",B23="B"),"Yes","No") -> Yes | D23: S2 | E23: Obralia Reformas Integrales S.L. | F23: Obralia Reformas Integrales | G23: B22605273 | H23: 4101 | I23: Construction of buildings (developer-builder) | J23: S.L. | K23: Cornellà de Llobregat | L23: Barcelona | M23: 63.6 | N23: Medium | O23: L0–L1 | P23: renovation-led 41.2 general construction | Q23: Sector-default only (Verifactu 2027 + quarterly filing cycle; no firm-specific signal in this extraction) | R23: S.L. form matches the reference tenant; CNAE 4101 read as sector-confirming. | U23: No differentiator over the Tier A cohort beyond order of contact — pure reachability risk: someone calls it before we do, or the CNAE/legal-form match turns out wrong on registry check | AC23: https://www.einforma.com/informacion-empresa/obralia-reformas-integrales | AD23: =COUNTA(V23:AA23) -> 0 | AF23: Not started | AO23: =IFERROR(INDEX(Playbook!$C$4:$C$17,MATCH($AF23,Playbook!$A$4:$A$17,0)),"") -> Read the row: tier, segment, trigger, reason we lose them. Check contact coverage; if 0, enrich before anything else. | AP23: =IFERROR(INDEX(Playbook!$D$4:$D$17,MATCH($AF23,Playbook!$A$4:$A$17,0)),"") -> — | AQ23: =IFERROR(INDEX(Playbook!$E$4:$E$17,MATCH($AF23,Playbook!$A$4:$A$17,0)),"") -> Row read and a contact channel exists | AR23: =IFERROR(INDEX(Playbook!$G$4:$G$17,MATCH($AF23,Playbook!$A$4:$A$17,0)),0) -> 0 | AS23: =IFERROR(INDEX('Pricing & Pilot'!$D$4:$D$6,MATCH($D23,'Pricing & Pilot'!$A$4:$A$6,0)),0) -> 6480 | AT23: =AS23*AR23 -> 0 | AU23: =IF(AL23="","",TODAY()-AL23) | AV23: =IF(AM23="","",IF(AND(AM23<TODAY(),$AF23<>"Customer",$AF23<>"Lost",$AF23<>"Not a fit"),"OVERDUE","")) | AW23: =IF(AV23="OVERDUE","RED",IF($AF23="Not started","—",IF($AF23="Customer","GREEN",IF(OR($AF23="Lost",$AF23="Not a fit"),"CLOSED","AMBER")))) -> —
A24: 23 | B24: B | C24: =IF(OR(B24="A",B24="B"),"Yes","No") -> Yes | D24: S1 | E24: Reformas Garriga De Finques Fornell SL | F24: Reformas Garriga De Finques Fornell | H24: 4335 | I24: Division 43 — specialised construction | J24: S.L. | K24: Granollers | L24: Barcelona | M24: 63.6 | N24: Medium | O24: L0–L1 | P24: target 43.3/43.9 finishing family | Q24: Sector-default only (Verifactu 2027 + quarterly filing cycle; no firm-specific signal in this extraction) | R24: S.L. form matches the reference tenant; CNAE 4335 read as sector-confirming. | U24: No differentiator over the Tier A cohort beyond order of contact — pure reachability risk: someone calls it before we do, or the CNAE/legal-form match turns out wrong on registry check | V24: 938404842 | AC24: https://www.einforma.com/informacion-empresa/reformas-garriga-finques-fornell, https://www.paginasamarillas.es/f/bellavista/reformes-garriga-de-finques-fornell_202517280_000000001.html | AD24: =COUNTA(V24:AA24) -> 1 | AF24: Not started | AO24: =IFERROR(INDEX(Playbook!$C$4:$C$17,MATCH($AF24,Playbook!$A$4:$A$17,0)),"") -> Read the row: tier, segment, trigger, reason we lose them. Check contact coverage; if 0, enrich before anything else. | AP24: =IFERROR(INDEX(Playbook!$D$4:$D$17,MATCH($AF24,Playbook!$A$4:$A$17,0)),"") -> — | AQ24: =IFERROR(INDEX(Playbook!$E$4:$E$17,MATCH($AF24,Playbook!$A$4:$A$17,0)),"") -> Row read and a contact channel exists | AR24: =IFERROR(INDEX(Playbook!$G$4:$G$17,MATCH($AF24,Playbook!$A$4:$A$17,0)),0) -> 0 | AS24: =IFERROR(INDEX('Pricing & Pilot'!$D$4:$D$6,MATCH($D24,'Pricing & Pilot'!$A$4:$A$6,0)),0) -> 3600 | AT24: =AS24*AR24 -> 0 | AU24: =IF(AL24="","",TODAY()-AL24) | AV24: =IF(AM24="","",IF(AND(AM24<TODAY(),$AF24<>"Customer",$AF24<>"Lost",$AF24<>"Not a fit"),"OVERDUE","")) | AW24: =IF(AV24="OVERDUE","RED",IF($AF24="Not started","—",IF($AF24="Customer","GREEN",IF(OR($AF24="Lost",$AF24="Not a fit"),"CLOSED","AMBER")))) -> —
A25: 24 | B25: B | C25: =IF(OR(B25="A",B25="B"),"Yes","No") -> Yes | D25: S1 | E25: Reformas Gracia SL | F25: Reformas Gracia | H25: 4399 | I25: Other specialised construction activities | J25: S.L. | K25: Barcelona | L25: Barcelona | M25: 63.6 | N25: Medium | O25: L0–L1 | P25: target 43.3/43.9 finishing family | Q25: Sector-default only (Verifactu 2027 + quarterly filing cycle; no firm-specific signal in this extraction) | R25: S.L. form matches the reference tenant; CNAE 4399 read as sector-confirming. | U25: No differentiator over the Tier A cohort beyond order of contact — pure reachability risk: someone calls it before we do, or the CNAE/legal-form match turns out wrong on registry check | V25: 937459104 | AC25: https://www.einforma.com/informacion-empresa/reformas-gracia | AD25: =COUNTA(V25:AA25) -> 1 | AF25: Not started | AO25: =IFERROR(INDEX(Playbook!$C$4:$C$17,MATCH($AF25,Playbook!$A$4:$A$17,0)),"") -> Read the row: tier, segment, trigger, reason we lose them. Check contact coverage; if 0, enrich before anything else. | AP25: =IFERROR(INDEX(Playbook!$D$4:$D$17,MATCH($AF25,Playbook!$A$4:$A$17,0)),"") -> — | AQ25: =IFERROR(INDEX(Playbook!$E$4:$E$17,MATCH($AF25,Playbook!$A$4:$A$17,0)),"") -> Row read and a contact channel exists | AR25: =IFERROR(INDEX(Playbook!$G$4:$G$17,MATCH($AF25,Playbook!$A$4:$A$17,0)),0) -> 0 | AS25: =IFERROR(INDEX('Pricing & Pilot'!$D$4:$D$6,MATCH($D25,'Pricing & Pilot'!$A$4:$A$6,0)),0) -> 3600 | AT25: =AS25*AR25 -> 0 | AU25: =IF(AL25="","",TODAY()-AL25) | AV25: =IF(AM25="","",IF(AND(AM25<TODAY(),$AF25<>"Customer",$AF25<>"Lost",$AF25<>"Not a fit"),"OVERDUE","")) | AW25: =IF(AV25="OVERDUE","RED",IF($AF25="Not started","—",IF($AF25="Customer","GREEN",IF(OR($AF25="Lost",$AF25="Not a fit"),"CLOSED","AMBER")))) -> —
A26: 25 | B26: B | C26: =IF(OR(B26="A",B26="B"),"Yes","No") -> Yes | D26: S2 | E26: Reformas Y Acabados Zenit SL | F26: Reformas Y Acabados Zenit | G26: B63379713 | H26: 4101 | I26: Construction of buildings (developer-builder) | J26: S.L. | K26: Sabadell | L26: Barcelona | M26: 63.6 | N26: Medium | O26: L0–L1 | P26: renovation-led 41.2 general construction | Q26: Sector-default only (Verifactu 2027 + quarterly filing cycle; no firm-specific signal in this extraction) | R26: S.L. form matches the reference tenant; CNAE 4101 read as sector-confirming. | U26: No differentiator over the Tier A cohort beyond order of contact — pure reachability risk: someone calls it before we do, or the CNAE/legal-form match turns out wrong on registry check | AC26: https://www.axesor.es/Informes-Empresas/7807623/ZENIT_REFORMES_I_REHABILITACIONS_SOCIEDAD_LIMITADA.html, https://www.einforma.com/informacion-empresa/reformas-acabados-zenit | AD26: =COUNTA(V26:AA26) -> 0 | AF26: Not started | AO26: =IFERROR(INDEX(Playbook!$C$4:$C$17,MATCH($AF26,Playbook!$A$4:$A$17,0)),"") -> Read the row: tier, segment, trigger, reason we lose them. Check contact coverage; if 0, enrich before anything else. | AP26: =IFERROR(INDEX(Playbook!$D$4:$D$17,MATCH($AF26,Playbook!$A$4:$A$17,0)),"") -> — | AQ26: =IFERROR(INDEX(Playbook!$E$4:$E$17,MATCH($AF26,Playbook!$A$4:$A$17,0)),"") -> Row read and a contact channel exists | AR26: =IFERROR(INDEX(Playbook!$G$4:$G$17,MATCH($AF26,Playbook!$A$4:$A$17,0)),0) -> 0 | AS26: =IFERROR(INDEX('Pricing & Pilot'!$D$4:$D$6,MATCH($D26,'Pricing & Pilot'!$A$4:$A$6,0)),0) -> 6480 | AT26: =AS26*AR26 -> 0 | AU26: =IF(AL26="","",TODAY()-AL26) | AV26: =IF(AM26="","",IF(AND(AM26<TODAY(),$AF26<>"Customer",$AF26<>"Lost",$AF26<>"Not a fit"),"OVERDUE","")) | AW26: =IF(AV26="OVERDUE","RED",IF($AF26="Not started","—",IF($AF26="Customer","GREEN",IF(OR($AF26="Lost",$AF26="Not a fit"),"CLOSED","AMBER")))) -> —
A27: 26 | B27: B | C27: =IF(OR(B27="A",B27="B"),"Yes","No") -> Yes | D27: S1 | E27: Reformas Y Pinturas Barcelona SL | F27: Reformas Y Pinturas Barcelona | H27: 4339 | I27: Other building completion and finishing | J27: S.L. | K27: Barcelona | L27: Barcelona | M27: 63.6 | N27: Medium | O27: L0–L1 | P27: target 43.3/43.9 finishing family | Q27: Sector-default only (Verifactu 2027 + quarterly filing cycle; no firm-specific signal in this extraction) | R27: S.L. form matches the reference tenant; CNAE 4339 read as sector-confirming. | U27: No differentiator over the Tier A cohort beyond order of contact — pure reachability risk: someone calls it before we do, or the CNAE/legal-form match turns out wrong on registry check | AC27: https://www.einforma.com/informacion-empresa/reformas-pinturas-barcelona | AD27: =COUNTA(V27:AA27) -> 0 | AF27: Not started | AO27: =IFERROR(INDEX(Playbook!$C$4:$C$17,MATCH($AF27,Playbook!$A$4:$A$17,0)),"") -> Read the row: tier, segment, trigger, reason we lose them. Check contact coverage; if 0, enrich before anything else. | AP27: =IFERROR(INDEX(Playbook!$D$4:$D$17,MATCH($AF27,Playbook!$A$4:$A$17,0)),"") -> — | AQ27: =IFERROR(INDEX(Playbook!$E$4:$E$17,MATCH($AF27,Playbook!$A$4:$A$17,0)),"") -> Row read and a contact channel exists | AR27: =IFERROR(INDEX(Playbook!$G$4:$G$17,MATCH($AF27,Playbook!$A$4:$A$17,0)),0) -> 0 | AS27: =IFERROR(INDEX('Pricing & Pilot'!$D$4:$D$6,MATCH($D27,'Pricing & Pilot'!$A$4:$A$6,0)),0) -> 3600 | AT27: =AS27*AR27 -> 0 | AU27: =IF(AL27="","",TODAY()-AL27) | AV27: =IF(AM27="","",IF(AND(AM27<TODAY(),$AF27<>"Customer",$AF27<>"Lost",$AF27<>"Not a fit"),"OVERDUE","")) | AW27: =IF(AV27="OVERDUE","RED",IF($AF27="Not started","—",IF($AF27="Customer","GREEN",IF(OR($AF27="Lost",$AF27="Not a fit"),"CLOSED","AMBER")))) -> —
A28: 27 | B28: B | C28: =IF(OR(B28="A",B28="B"),"Yes","No") -> Yes | D28: S1 | E28: REFORMES LAP GRUP NOVA CASA S.L. | F28: Reformes LAP Grup Nova Casa | H28: 4399 | I28: Other specialised construction activities | J28: S.L. | K28: Esplugues de Llobregat | L28: Barcelona | M28: 63.6 | N28: Medium | O28: L0–L1 | P28: target 43.3/43.9 finishing family | Q28: Sector-default only (Verifactu 2027 + quarterly filing cycle; no firm-specific signal in this extraction) | R28: S.L. form matches the reference tenant; CNAE 4399 read as sector-confirming. | U28: No differentiator over the Tier A cohort beyond order of contact — pure reachability risk: someone calls it before we do, or the CNAE/legal-form match turns out wrong on registry check | AC28: https://www.einforma.com/informacion-empresa/reformes-lap-grup-nova-casa | AD28: =COUNTA(V28:AA28) -> 0 | AF28: Not started | AO28: =IFERROR(INDEX(Playbook!$C$4:$C$17,MATCH($AF28,Playbook!$A$4:$A$17,0)),"") -> Read the row: tier, segment, trigger, reason we lose them. Check contact coverage; if 0, enrich before anything else. | AP28: =IFERROR(INDEX(Playbook!$D$4:$D$17,MATCH($AF28,Playbook!$A$4:$A$17,0)),"") -> — | AQ28: =IFERROR(INDEX(Playbook!$E$4:$E$17,MATCH($AF28,Playbook!$A$4:$A$17,0)),"") -> Row read and a contact channel exists | AR28: =IFERROR(INDEX(Playbook!$G$4:$G$17,MATCH($AF28,Playbook!$A$4:$A$17,0)),0) -> 0 | AS28: =IFERROR(INDEX('Pricing & Pilot'!$D$4:$D$6,MATCH($D28,'Pricing & Pilot'!$A$4:$A$6,0)),0) -> 3600 | AT28: =AS28*AR28 -> 0 | AU28: =IF(AL28="","",TODAY()-AL28) | AV28: =IF(AM28="","",IF(AND(AM28<TODAY(),$AF28<>"Customer",$AF28<>"Lost",$AF28<>"Not a fit"),"OVERDUE","")) | AW28: =IF(AV28="OVERDUE","RED",IF($AF28="Not started","—",IF($AF28="Customer","GREEN",IF(OR($AF28="Lost",$AF28="Not a fit"),"CLOSED","AMBER")))) -> —
A29: 28 | B29: B | C29: =IF(OR(B29="A",B29="B"),"Yes","No") -> Yes | D29: S2 | E29: Reformes N.V.A. SL | F29: Reformes N.V.A. | G29: B66449034 | H29: 4101 | I29: Construction of buildings (developer-builder) | J29: S.L. | K29: Mollet del Vallès | L29: Barcelona | M29: 63.6 | N29: Medium | O29: L0–L1 | P29: renovation-led 41.2 general construction | Q29: Sector-default only (Verifactu 2027 + quarterly filing cycle; no firm-specific signal in this extraction) | R29: S.L. form matches the reference tenant; CNAE 4101 read as sector-confirming. | U29: No differentiator over the Tier A cohort beyond order of contact — pure reachability risk: someone calls it before we do, or the CNAE/legal-form match turns out wrong on registry check | V29: 930104337 | W29: info@nvareformes.com | X29: https://www.nvareformes.es | AC29: https://www.comarcaactiva.com/mollet-del-valles/nva-reformas, https://www.einforma.com/informacion-empresa/reformes-nva, https://www.puntosona.cat/guia-comercial/5956/nva-reformas-mollet-del-mollet | AD29: =COUNTA(V29:AA29) -> 3 | AF29: Not started | AO29: =IFERROR(INDEX(Playbook!$C$4:$C$17,MATCH($AF29,Playbook!$A$4:$A$17,0)),"") -> Read the row: tier, segment, trigger, reason we lose them. Check contact coverage; if 0, enrich before anything else. | AP29: =IFERROR(INDEX(Playbook!$D$4:$D$17,MATCH($AF29,Playbook!$A$4:$A$17,0)),"") -> — | AQ29: =IFERROR(INDEX(Playbook!$E$4:$E$17,MATCH($AF29,Playbook!$A$4:$A$17,0)),"") -> Row read and a contact channel exists | AR29: =IFERROR(INDEX(Playbook!$G$4:$G$17,MATCH($AF29,Playbook!$A$4:$A$17,0)),0) -> 0 | AS29: =IFERROR(INDEX('Pricing & Pilot'!$D$4:$D$6,MATCH($D29,'Pricing & Pilot'!$A$4:$A$6,0)),0) -> 6480 | AT29: =AS29*AR29 -> 0 | AU29: =IF(AL29="","",TODAY()-AL29) | AV29: =IF(AM29="","",IF(AND(AM29<TODAY(),$AF29<>"Customer",$AF29<>"Lost",$AF29<>"Not a fit"),"OVERDUE","")) | AW29: =IF(AV29="OVERDUE","RED",IF($AF29="Not started","—",IF($AF29="Customer","GREEN",IF(OR($AF29="Lost",$AF29="Not a fit"),"CLOSED","AMBER")))) -> —
A30: 29 | B30: B | C30: =IF(OR(B30="A",B30="B"),"Yes","No") -> Yes | D30: S1 | E30: Reformes Vic 58 SL | F30: Reformes Vic 58 | H30: 4399 | I30: Other specialised construction activities | J30: S.L. | K30: Vic | L30: Barcelona | M30: 63.6 | N30: Medium | O30: L0–L1 | P30: target 43.3/43.9 finishing family | Q30: Sector-default only (Verifactu 2027 + quarterly filing cycle; no firm-specific signal in this extraction) | R30: S.L. form matches the reference tenant; CNAE 4399 read as sector-confirming. | U30: No differentiator over the Tier A cohort beyond order of contact — pure reachability risk: someone calls it before we do, or the CNAE/legal-form match turns out wrong on registry check | AC30: https://empresite.eleconomista.es/REFORMES-VIC-58.html | AD30: =COUNTA(V30:AA30) -> 0 | AF30: Not started | AO30: =IFERROR(INDEX(Playbook!$C$4:$C$17,MATCH($AF30,Playbook!$A$4:$A$17,0)),"") -> Read the row: tier, segment, trigger, reason we lose them. Check contact coverage; if 0, enrich before anything else. | AP30: =IFERROR(INDEX(Playbook!$D$4:$D$17,MATCH($AF30,Playbook!$A$4:$A$17,0)),"") -> — | AQ30: =IFERROR(INDEX(Playbook!$E$4:$E$17,MATCH($AF30,Playbook!$A$4:$A$17,0)),"") -> Row read and a contact channel exists | AR30: =IFERROR(INDEX(Playbook!$G$4:$G$17,MATCH($AF30,Playbook!$A$4:$A$17,0)),0) -> 0 | AS30: =IFERROR(INDEX('Pricing & Pilot'!$D$4:$D$6,MATCH($D30,'Pricing & Pilot'!$A$4:$A$6,0)),0) -> 3600 | AT30: =AS30*AR30 -> 0 | AU30: =IF(AL30="","",TODAY()-AL30) | AV30: =IF(AM30="","",IF(AND(AM30<TODAY(),$AF30<>"Customer",$AF30<>"Lost",$AF30<>"Not a fit"),"OVERDUE","")) | AW30: =IF(AV30="OVERDUE","RED",IF($AF30="Not started","—",IF($AF30="Customer","GREEN",IF(OR($AF30="Lost",$AF30="Not a fit"),"CLOSED","AMBER")))) -> —
A31: 30 | B31: B | C31: =IF(OR(B31="A",B31="B"),"Yes","No") -> Yes | D31: S2 | E31: Reparaciones Y Obras Molins RJ S.L. | F31: Reparaciones Y Obras Molins RJ | H31: 4121 | I31: Construction of residential buildings | J31: S.L. | K31: Molins de Rei | L31: Barcelona | M31: 63.6 | N31: Medium | O31: L0–L1 | P31: renovation-led 41.2 general construction | Q31: Sector-default only (Verifactu 2027 + quarterly filing cycle; no firm-specific signal in this extraction) | R31: S.L. form matches the reference tenant; CNAE 4121 read as sector-confirming. | U31: No differentiator over the Tier A cohort beyond order of contact — pure reachability risk: someone calls it before we do, or the CNAE/legal-form match turns out wrong on registry check | V31: 936803674 | W31: administración@bcrhabitat.es | AC31: https://www.einforma.com/informacion-empresa/reparaciones-obras-molins-rj | AD31: =COUNTA(V31:AA31) -> 2 | AF31: Not started | AO31: =IFERROR(INDEX(Playbook!$C$4:$C$17,MATCH($AF31,Playbook!$A$4:$A$17,0)),"") -> Read the row: tier, segment, trigger, reason we lose them. Check contact coverage; if 0, enrich before anything else. | AP31: =IFERROR(INDEX(Playbook!$D$4:$D$17,MATCH($AF31,Playbook!$A$4:$A$17,0)),"") -> — | AQ31: =IFERROR(INDEX(Playbook!$E$4:$E$17,MATCH($AF31,Playbook!$A$4:$A$17,0)),"") -> Row read and a contact channel exists | AR31: =IFERROR(INDEX(Playbook!$G$4:$G$17,MATCH($AF31,Playbook!$A$4:$A$17,0)),0) -> 0 | AS31: =IFERROR(INDEX('Pricing & Pilot'!$D$4:$D$6,MATCH($D31,'Pricing & Pilot'!$A$4:$A$6,0)),0) -> 6480 | AT31: =AS31*AR31 -> 0 | AU31: =IF(AL31="","",TODAY()-AL31) | AV31: =IF(AM31="","",IF(AND(AM31<TODAY(),$AF31<>"Customer",$AF31<>"Lost",$AF31<>"Not a fit"),"OVERDUE","")) | AW31: =IF(AV31="OVERDUE","RED",IF($AF31="Not started","—",IF($AF31="Customer","GREEN",IF(OR($AF31="Lost",$AF31="Not a fit"),"CLOSED","AMBER")))) -> —
A32: 31 | B32: B | C32: =IF(OR(B32="A",B32="B"),"Yes","No") -> Yes | D32: S1 | E32: Reparaciones Y Reformas Badalona SL | F32: Reparaciones Y Reformas Badalona | G32: B67396820 | H32: 4339 | I32: Other building completion and finishing | J32: S.L. | K32: Badalona | L32: Barcelona | M32: 63.6 | N32: Medium | O32: L0–L1 | P32: target 43.3/43.9 finishing family | Q32: Sector-default only (Verifactu 2027 + quarterly filing cycle; no firm-specific signal in this extraction) | R32: S.L. form matches the reference tenant; CNAE 4339 read as sector-confirming. | U32: No differentiator over the Tier A cohort beyond order of contact — pure reachability risk: someone calls it before we do, or the CNAE/legal-form match turns out wrong on registry check | AC32: https://www.einforma.com/informacion-empresa/reparaciones-reformas-badalona | AD32: =COUNTA(V32:AA32) -> 0 | AF32: Not started | AO32: =IFERROR(INDEX(Playbook!$C$4:$C$17,MATCH($AF32,Playbook!$A$4:$A$17,0)),"") -> Read the row: tier, segment, trigger, reason we lose them. Check contact coverage; if 0, enrich before anything else. | AP32: =IFERROR(INDEX(Playbook!$D$4:$D$17,MATCH($AF32,Playbook!$A$4:$A$17,0)),"") -> — | AQ32: =IFERROR(INDEX(Playbook!$E$4:$E$17,MATCH($AF32,Playbook!$A$4:$A$17,0)),"") -> Row read and a contact channel exists | AR32: =IFERROR(INDEX(Playbook!$G$4:$G$17,MATCH($AF32,Playbook!$A$4:$A$17,0)),0) -> 0 | AS32: =IFERROR(INDEX('Pricing & Pilot'!$D$4:$D$6,MATCH($D32,'Pricing & Pilot'!$A$4:$A$6,0)),0) -> 3600 | AT32: =AS32*AR32 -> 0 | AU32: =IF(AL32="","",TODAY()-AL32) | AV32: =IF(AM32="","",IF(AND(AM32<TODAY(),$AF32<>"Customer",$AF32<>"Lost",$AF32<>"Not a fit"),"OVERDUE","")) | AW32: =IF(AV32="OVERDUE","RED",IF($AF32="Not started","—",IF($AF32="Customer","GREEN",IF(OR($AF32="Lost",$AF32="Not a fit"),"CLOSED","AMBER")))) -> —
A33: 32 | B33: B | C33: =IF(OR(B33="A",B33="B"),"Yes","No") -> Yes | D33: S2 | E33: Construccions Castelldefels S.A. | F33: Construccions Castelldefels | G33: A08213530 | H33: 4121 | I33: Construction of residential buildings | J33: S.A. | K33: Castelldefels | L33: Barcelona | M33: 62 | N33: Medium | O33: L0–L1 | P33: renovation-led 41.2 general construction | Q33: Sector-default only (Verifactu 2027 + quarterly filing cycle; no firm-specific signal in this extraction) | R33: S.A. form, acceptable only if small; CNAE 4121 read as sector-confirming. | U33: Administrative distance from the S.L. reference form (governance/liability question the pitch has to answer first) | V33: 932150226 | X33: http://www.construccionscastelldefels.com | AC33: https://www.einforma.com/informacion-empresa/construccions-castelldefels, https://www.paginasamarillas.es/f/barcelona/construccions-castelldefels-sa_200746600_000000001.html | AD33: =COUNTA(V33:AA33) -> 2 | AF33: Not started | AO33: =IFERROR(INDEX(Playbook!$C$4:$C$17,MATCH($AF33,Playbook!$A$4:$A$17,0)),"") -> Read the row: tier, segment, trigger, reason we lose them. Check contact coverage; if 0, enrich before anything else. | AP33: =IFERROR(INDEX(Playbook!$D$4:$D$17,MATCH($AF33,Playbook!$A$4:$A$17,0)),"") -> — | AQ33: =IFERROR(INDEX(Playbook!$E$4:$E$17,MATCH($AF33,Playbook!$A$4:$A$17,0)),"") -> Row read and a contact channel exists | AR33: =IFERROR(INDEX(Playbook!$G$4:$G$17,MATCH($AF33,Playbook!$A$4:$A$17,0)),0) -> 0 | AS33: =IFERROR(INDEX('Pricing & Pilot'!$D$4:$D$6,MATCH($D33,'Pricing & Pilot'!$A$4:$A$6,0)),0) -> 6480 | AT33: =AS33*AR33 -> 0 | AU33: =IF(AL33="","",TODAY()-AL33) | AV33: =IF(AM33="","",IF(AND(AM33<TODAY(),$AF33<>"Customer",$AF33<>"Lost",$AF33<>"Not a fit"),"OVERDUE","")) | AW33: =IF(AV33="OVERDUE","RED",IF($AF33="Not started","—",IF($AF33="Customer","GREEN",IF(OR($AF33="Lost",$AF33="Not a fit"),"CLOSED","AMBER")))) -> —
A34: 33 | B34: B | C34: =IF(OR(B34="A",B34="B"),"Yes","No") -> Yes | D34: S3 | E34: Construcciones Reycons S.C.C.L. | F34: Construcciones Reycons | H34: 4341 | I34: Division 43 — specialised construction | J34: S.C.C.L. | K34: Sant Cugat del Vallès | L34: Barcelona | M34: 60.4 | N34: Medium | O34: L0–L1 | P34: target 43.3/43.9 finishing family | Q34: Sector-default only (Verifactu 2027 + quarterly filing cycle; no firm-specific signal in this extraction) | R34: cooperative form — dispersed-governance anchor applies; CNAE 4341 read as sector-confirming. | U34: Administrative distance from the S.L. reference form (governance/liability question the pitch has to answer first) | V34: 935441671 | AC34: https://www.einforma.com/informacion-empresa/construcciones-reycons | AD34: =COUNTA(V34:AA34) -> 1 | AF34: Not started | AO34: =IFERROR(INDEX(Playbook!$C$4:$C$17,MATCH($AF34,Playbook!$A$4:$A$17,0)),"") -> Read the row: tier, segment, trigger, reason we lose them. Check contact coverage; if 0, enrich before anything else. | AP34: =IFERROR(INDEX(Playbook!$D$4:$D$17,MATCH($AF34,Playbook!$A$4:$A$17,0)),"") -> — | AQ34: =IFERROR(INDEX(Playbook!$E$4:$E$17,MATCH($AF34,Playbook!$A$4:$A$17,0)),"") -> Row read and a contact channel exists | AR34: =IFERROR(INDEX(Playbook!$G$4:$G$17,MATCH($AF34,Playbook!$A$4:$A$17,0)),0) -> 0 | AS34: =IFERROR(INDEX('Pricing & Pilot'!$D$4:$D$6,MATCH($D34,'Pricing & Pilot'!$A$4:$A$6,0)),0) -> 2160 | AT34: =AS34*AR34 -> 0 | AU34: =IF(AL34="","",TODAY()-AL34) | AV34: =IF(AM34="","",IF(AND(AM34<TODAY(),$AF34<>"Customer",$AF34<>"Lost",$AF34<>"Not a fit"),"OVERDUE","")) | AW34: =IF(AV34="OVERDUE","RED",IF($AF34="Not started","—",IF($AF34="Customer","GREEN",IF(OR($AF34="Lost",$AF34="Not a fit"),"CLOSED","AMBER")))) -> —
A35: 34 | B35: B | C35: =IF(OR(B35="A",B35="B"),"Yes","No") -> Yes | D35: S3 | E35: Estructuras Rubi S.C.P. | F35: Estructuras Rubi | H35: 4399 | I35: Other specialised construction activities | J35: S.C.P. | K35: Rubí | L35: Barcelona | M35: 58.8 | N35: Medium | O35: L0–L1 | P35: target 43.3/43.9 finishing family | Q35: Sector-default only (Verifactu 2027 + quarterly filing cycle; no firm-specific signal in this extraction) | R35: civil-partnership form, distant from the S.L. reference; CNAE 4399 read as sector-confirming. | U35: Administrative distance from the S.L. reference form (governance/liability question the pitch has to answer first) | AC35: https://www.einforma.com/informacion-empresa/estructuras-rubi | AD35: =COUNTA(V35:AA35) -> 0 | AF35: Not started | AO35: =IFERROR(INDEX(Playbook!$C$4:$C$17,MATCH($AF35,Playbook!$A$4:$A$17,0)),"") -> Read the row: tier, segment, trigger, reason we lose them. Check contact coverage; if 0, enrich before anything else. | AP35: =IFERROR(INDEX(Playbook!$D$4:$D$17,MATCH($AF35,Playbook!$A$4:$A$17,0)),"") -> — | AQ35: =IFERROR(INDEX(Playbook!$E$4:$E$17,MATCH($AF35,Playbook!$A$4:$A$17,0)),"") -> Row read and a contact channel exists | AR35: =IFERROR(INDEX(Playbook!$G$4:$G$17,MATCH($AF35,Playbook!$A$4:$A$17,0)),0) -> 0 | AS35: =IFERROR(INDEX('Pricing & Pilot'!$D$4:$D$6,MATCH($D35,'Pricing & Pilot'!$A$4:$A$6,0)),0) -> 2160 | AT35: =AS35*AR35 -> 0 | AU35: =IF(AL35="","",TODAY()-AL35) | AV35: =IF(AM35="","",IF(AND(AM35<TODAY(),$AF35<>"Customer",$AF35<>"Lost",$AF35<>"Not a fit"),"OVERDUE","")) | AW35: =IF(AV35="OVERDUE","RED",IF($AF35="Not started","—",IF($AF35="Customer","GREEN",IF(OR($AF35="Lost",$AF35="Not a fit"),"CLOSED","AMBER")))) -> —
A36: 35 | B36: B | C36: =IF(OR(B36="A",B36="B"),"Yes","No") -> Yes | D36: S2 | E36: Grupo Mg Reformas Baix Llobregat S.C.P. | F36: Grupo Mg Reformas Baix Llobregat | G36: J67590273 | H36: 4101 | I36: Construction of buildings (developer-builder) | J36: S.C.P. | K36: Castelldefels | L36: Barcelona | M36: 58.8 | N36: Medium | O36: L0–L1 | P36: renovation-led 41.2 general construction | Q36: Sector-default only (Verifactu 2027 + quarterly filing cycle; no firm-specific signal in this extraction) | R36: civil-partnership form, distant from the S.L. reference; CNAE 4101 read as sector-confirming. | U36: Administrative distance from the S.L. reference form (governance/liability question the pitch has to answer first) | AC36: https://jobtoday.com/es/company/reformas-integrales-en-general-mg-reformas-baix-ll-WrjAg5, https://www.axesor.es/Informes-Empresas/10434362/GRUPO_MG_REFORMAS_BAIX_LLOBREGAT_SCP.html, https://www.einforma.com/informacion-empresa/grupo-mg-reformas-baix-llobregat | AD36: =COUNTA(V36:AA36) -> 0 | AF36: Not started | AO36: =IFERROR(INDEX(Playbook!$C$4:$C$17,MATCH($AF36,Playbook!$A$4:$A$17,0)),"") -> Read the row: tier, segment, trigger, reason we lose them. Check contact coverage; if 0, enrich before anything else. | AP36: =IFERROR(INDEX(Playbook!$D$4:$D$17,MATCH($AF36,Playbook!$A$4:$A$17,0)),"") -> — | AQ36: =IFERROR(INDEX(Playbook!$E$4:$E$17,MATCH($AF36,Playbook!$A$4:$A$17,0)),"") -> Row read and a contact channel exists | AR36: =IFERROR(INDEX(Playbook!$G$4:$G$17,MATCH($AF36,Playbook!$A$4:$A$17,0)),0) -> 0 | AS36: =IFERROR(INDEX('Pricing & Pilot'!$D$4:$D$6,MATCH($D36,'Pricing & Pilot'!$A$4:$A$6,0)),0) -> 6480 | AT36: =AS36*AR36 -> 0 | AU36: =IF(AL36="","",TODAY()-AL36) | AV36: =IF(AM36="","",IF(AND(AM36<TODAY(),$AF36<>"Customer",$AF36<>"Lost",$AF36<>"Not a fit"),"OVERDUE","")) | AW36: =IF(AV36="OVERDUE","RED",IF($AF36="Not started","—",IF($AF36="Customer","GREEN",IF(OR($AF36="Lost",$AF36="Not a fit"),"CLOSED","AMBER")))) -> —
A37: 36 | B37: B | C37: =IF(OR(B37="A",B37="B"),"Yes","No") -> Yes | D37: S3 | E37: J & E Reformas Mollet S.C.P. | F37: J & E Reformas Mollet | G37: J64615891 | H37: 4399 | I37: Other specialised construction activities | J37: S.C.P. | K37: Mollet del Vallès | L37: Barcelona | M37: 58.8 | N37: Medium | O37: L0–L1 | P37: target 43.3/43.9 finishing family | Q37: Sector-default only (Verifactu 2027 + quarterly filing cycle; no firm-specific signal in this extraction) | R37: civil-partnership form, distant from the S.L. reference; CNAE 4399 read as sector-confirming. | U37: Administrative distance from the S.L. reference form (governance/liability question the pitch has to answer first) | AC37: https://www.einforma.com/informacion-empresa/je-reformas-mollet | AD37: =COUNTA(V37:AA37) -> 0 | AF37: Not started | AO37: =IFERROR(INDEX(Playbook!$C$4:$C$17,MATCH($AF37,Playbook!$A$4:$A$17,0)),"") -> Read the row: tier, segment, trigger, reason we lose them. Check contact coverage; if 0, enrich before anything else. | AP37: =IFERROR(INDEX(Playbook!$D$4:$D$17,MATCH($AF37,Playbook!$A$4:$A$17,0)),"") -> — | AQ37: =IFERROR(INDEX(Playbook!$E$4:$E$17,MATCH($AF37,Playbook!$A$4:$A$17,0)),"") -> Row read and a contact channel exists | AR37: =IFERROR(INDEX(Playbook!$G$4:$G$17,MATCH($AF37,Playbook!$A$4:$A$17,0)),0) -> 0 | AS37: =IFERROR(INDEX('Pricing & Pilot'!$D$4:$D$6,MATCH($D37,'Pricing & Pilot'!$A$4:$A$6,0)),0) -> 2160 | AT37: =AS37*AR37 -> 0 | AU37: =IF(AL37="","",TODAY()-AL37) | AV37: =IF(AM37="","",IF(AND(AM37<TODAY(),$AF37<>"Customer",$AF37<>"Lost",$AF37<>"Not a fit"),"OVERDUE","")) | AW37: =IF(AV37="OVERDUE","RED",IF($AF37="Not started","—",IF($AF37="Customer","GREEN",IF(OR($AF37="Lost",$AF37="Not a fit"),"CLOSED","AMBER")))) -> —
A38: 37 | B38: B | C38: =IF(OR(B38="A",B38="B"),"Yes","No") -> Yes | D38: S3 | E38: Reformas Lizarran S.C.P. | F38: Reformas Lizarran | G38: J64592900 | H38: 4399 | I38: Other specialised construction activities | J38: S.C.P. | K38: Sabadell | L38: Barcelona | M38: 58.8 | N38: Medium | O38: L0–L1 | P38: target 43.3/43.9 finishing family | Q38: Sector-default only (Verifactu 2027 + quarterly filing cycle; no firm-specific signal in this extraction) | R38: civil-partnership form, distant from the S.L. reference; CNAE 4399 read as sector-confirming. | U38: Administrative distance from the S.L. reference form (governance/liability question the pitch has to answer first) | AC38: https://www.einforma.com/informacion-empresa/reformas-lizarran | AD38: =COUNTA(V38:AA38) -> 0 | AF38: Not started | AO38: =IFERROR(INDEX(Playbook!$C$4:$C$17,MATCH($AF38,Playbook!$A$4:$A$17,0)),"") -> Read the row: tier, segment, trigger, reason we lose them. Check contact coverage; if 0, enrich before anything else. | AP38: =IFERROR(INDEX(Playbook!$D$4:$D$17,MATCH($AF38,Playbook!$A$4:$A$17,0)),"") -> — | AQ38: =IFERROR(INDEX(Playbook!$E$4:$E$17,MATCH($AF38,Playbook!$A$4:$A$17,0)),"") -> Row read and a contact channel exists | AR38: =IFERROR(INDEX(Playbook!$G$4:$G$17,MATCH($AF38,Playbook!$A$4:$A$17,0)),0) -> 0 | AS38: =IFERROR(INDEX('Pricing & Pilot'!$D$4:$D$6,MATCH($D38,'Pricing & Pilot'!$A$4:$A$6,0)),0) -> 2160 | AT38: =AS38*AR38 -> 0 | AU38: =IF(AL38="","",TODAY()-AL38) | AV38: =IF(AM38="","",IF(AND(AM38<TODAY(),$AF38<>"Customer",$AF38<>"Lost",$AF38<>"Not a fit"),"OVERDUE","")) | AW38: =IF(AV38="OVERDUE","RED",IF($AF38="Not started","—",IF($AF38="Customer","GREEN",IF(OR($AF38="Lost",$AF38="Not a fit"),"CLOSED","AMBER")))) -> —
A39: 38 | B39: C | C39: =IF(OR(B39="A",B39="B"),"Yes","No") -> No | E39: FM&M Reformas E Instalaciones S.L. | F39: FM&M Reformas E Instalaciones | H39: 4324 | I39: Division 43 — specialised construction | J39: S.L. | K39: L'Hospitalet de Llobregat | L39: Barcelona | M39: 55.6 | N39: Medium | O39: L1 | P39: 43.2x installer family — maintenance-mix unknown | Q39: Sector-default only (Verifactu 2027 + quarterly filing cycle; no firm-specific signal in this extraction) | R39: Installer-coded (CNAE or name); project-work chapters transfer, but a maintenance-revenue share (unconfirmed) forces a recurring-contract object the vertical layer lacks. | U39: Investment case — Pack 1 — a recurring-contract and work-order capability for project-led installers (8 firms) | AC39: https://www.einforma.com/informacion-empresa/fm-m-reformas-instalaciones | AD39: =COUNTA(V39:AA39) -> 0 | AF39: Not started | AO39: =IFERROR(INDEX(Playbook!$C$4:$C$17,MATCH($AF39,Playbook!$A$4:$A$17,0)),"") -> Read the row: tier, segment, trigger, reason we lose them. Check contact coverage; if 0, enrich before anything else. | AP39: =IFERROR(INDEX(Playbook!$D$4:$D$17,MATCH($AF39,Playbook!$A$4:$A$17,0)),"") -> — | AQ39: =IFERROR(INDEX(Playbook!$E$4:$E$17,MATCH($AF39,Playbook!$A$4:$A$17,0)),"") -> Row read and a contact channel exists | AR39: =IFERROR(INDEX(Playbook!$G$4:$G$17,MATCH($AF39,Playbook!$A$4:$A$17,0)),0) -> 0 | AS39: =IFERROR(INDEX('Pricing & Pilot'!$D$4:$D$6,MATCH($D39,'Pricing & Pilot'!$A$4:$A$6,0)),0) -> 0 | AT39: =AS39*AR39 -> 0 | AU39: =IF(AL39="","",TODAY()-AL39) | AV39: =IF(AM39="","",IF(AND(AM39<TODAY(),$AF39<>"Customer",$AF39<>"Lost",$AF39<>"Not a fit"),"OVERDUE","")) | AW39: =IF(AV39="OVERDUE","RED",IF($AF39="Not started","—",IF($AF39="Customer","GREEN",IF(OR($AF39="Lost",$AF39="Not a fit"),"CLOSED","AMBER")))) -> —
A40: 39 | B40: C | C40: =IF(OR(B40="A",B40="B"),"Yes","No") -> No | E40: Instalaciones Y Reformas Serrano SL | F40: Instalaciones Y Reformas Serrano | G40: B60789930 | H40: 4321 | I40: Electrical installation | J40: S.L. | K40: Sabadell | L40: Barcelona | M40: 55.6 | N40: Medium | O40: L1 | P40: 43.2x installer family — maintenance-mix unknown | Q40: Sector-default only (Verifactu 2027 + quarterly filing cycle; no firm-specific signal in this extraction) | R40: Installer-coded (CNAE or name); project-work chapters transfer, but a maintenance-revenue share (unconfirmed) forces a recurring-contract object the vertical layer lacks. | U40: Investment case — Pack 1 — a recurring-contract and work-order capability for project-led installers (8 firms) | AC40: https://www.einforma.com/informacion-empresa/instalaciones-reformas-serrano | AD40: =COUNTA(V40:AA40) -> 0 | AF40: Not started | AO40: =IFERROR(INDEX(Playbook!$C$4:$C$17,MATCH($AF40,Playbook!$A$4:$A$17,0)),"") -> Read the row: tier, segment, trigger, reason we lose them. Check contact coverage; if 0, enrich before anything else. | AP40: =IFERROR(INDEX(Playbook!$D$4:$D$17,MATCH($AF40,Playbook!$A$4:$A$17,0)),"") -> — | AQ40: =IFERROR(INDEX(Playbook!$E$4:$E$17,MATCH($AF40,Playbook!$A$4:$A$17,0)),"") -> Row read and a contact channel exists | AR40: =IFERROR(INDEX(Playbook!$G$4:$G$17,MATCH($AF40,Playbook!$A$4:$A$17,0)),0) -> 0 | AS40: =IFERROR(INDEX('Pricing & Pilot'!$D$4:$D$6,MATCH($D40,'Pricing & Pilot'!$A$4:$A$6,0)),0) -> 0 | AT40: =AS40*AR40 -> 0 | AU40: =IF(AL40="","",TODAY()-AL40) | AV40: =IF(AM40="","",IF(AND(AM40<TODAY(),$AF40<>"Customer",$AF40<>"Lost",$AF40<>"Not a fit"),"OVERDUE","")) | AW40: =IF(AV40="OVERDUE","RED",IF($AF40="Not started","—",IF($AF40="Customer","GREEN",IF(OR($AF40="Lost",$AF40="Not a fit"),"CLOSED","AMBER")))) -> —
A41: 40 | B41: C | C41: =IF(OR(B41="A",B41="B"),"Yes","No") -> No | E41: Proyectos Y Excavaciones Rubi S.L. | F41: Proyectos Y Excavaciones Rubi | H41: 4312 | I41: Site preparation | J41: S.L. | K41: Rubí | L41: Barcelona | M41: 55.6 | N41: Medium | O41: L1 | P41: 43.1x demolition/site-prep — enabling trade, not full quote spine | Q41: Sector-default only (Verifactu 2027 + quarterly filing cycle; no firm-specific signal in this extraction) | R41: CNAE 43.12 site-preparation/demolition is an enabling trade, not the chaptered-quote spine the product is built around. | U41: Investment case — Pack 2 — a civil-engineering and site-preparation bridge (2 firms; recommend against investment) | AC41: https://www.einforma.com/informacion-empresa/proyectos-excavaciones-rubi | AD41: =COUNTA(V41:AA41) -> 0 | AF41: Not started | AO41: =IFERROR(INDEX(Playbook!$C$4:$C$17,MATCH($AF41,Playbook!$A$4:$A$17,0)),"") -> Read the row: tier, segment, trigger, reason we lose them. Check contact coverage; if 0, enrich before anything else. | AP41: =IFERROR(INDEX(Playbook!$D$4:$D$17,MATCH($AF41,Playbook!$A$4:$A$17,0)),"") -> — | AQ41: =IFERROR(INDEX(Playbook!$E$4:$E$17,MATCH($AF41,Playbook!$A$4:$A$17,0)),"") -> Row read and a contact channel exists | AR41: =IFERROR(INDEX(Playbook!$G$4:$G$17,MATCH($AF41,Playbook!$A$4:$A$17,0)),0) -> 0 | AS41: =IFERROR(INDEX('Pricing & Pilot'!$D$4:$D$6,MATCH($D41,'Pricing & Pilot'!$A$4:$A$6,0)),0) -> 0 | AT41: =AS41*AR41 -> 0 | AU41: =IF(AL41="","",TODAY()-AL41) | AV41: =IF(AM41="","",IF(AND(AM41<TODAY(),$AF41<>"Customer",$AF41<>"Lost",$AF41<>"Not a fit"),"OVERDUE","")) | AW41: =IF(AV41="OVERDUE","RED",IF($AF41="Not started","—",IF($AF41="Customer","GREEN",IF(OR($AF41="Lost",$AF41="Not a fit"),"CLOSED","AMBER")))) -> —
A42: 41 | B42: C | C42: =IF(OR(B42="A",B42="B"),"Yes","No") -> No | E42: Reformas Barcelona Low Cost SL | F42: Reformas Barcelona Low Cost | G42: B65314726 | H42: 4329 | I42: Other construction installation | J42: S.L. | K42: Barcelona | L42: Barcelona | M42: 55.6 | N42: Medium | O42: L1 | P42: 43.2x installer family — maintenance-mix unknown | Q42: Sector-default only; review_count=355 (unweighted, possible high-volume/low-ticket profile) | R42: Installer-coded (CNAE or name); project-work chapters transfer, but a maintenance-revenue share (unconfirmed) forces a recurring-contract object the vertical layer lacks. | U42: Investment case — Pack 1 — a recurring-contract and work-order capability for project-led installers (8 firms) | V42: 936024861 | AC42: https://empresite.eleconomista.es/REFORMAS-BARCELONA-LOW-COST.html, https://infonif.economia3.com/ficha-empresa/reformas-barcelona-low-cost-sl, https://www.einforma.com/informacion-empresa/reformas-barcelona-low-cost | AD42: =COUNTA(V42:AA42) -> 1 | AF42: Not started | AO42: =IFERROR(INDEX(Playbook!$C$4:$C$17,MATCH($AF42,Playbook!$A$4:$A$17,0)),"") -> Read the row: tier, segment, trigger, reason we lose them. Check contact coverage; if 0, enrich before anything else. | AP42: =IFERROR(INDEX(Playbook!$D$4:$D$17,MATCH($AF42,Playbook!$A$4:$A$17,0)),"") -> — | AQ42: =IFERROR(INDEX(Playbook!$E$4:$E$17,MATCH($AF42,Playbook!$A$4:$A$17,0)),"") -> Row read and a contact channel exists | AR42: =IFERROR(INDEX(Playbook!$G$4:$G$17,MATCH($AF42,Playbook!$A$4:$A$17,0)),0) -> 0 | AS42: =IFERROR(INDEX('Pricing & Pilot'!$D$4:$D$6,MATCH($D42,'Pricing & Pilot'!$A$4:$A$6,0)),0) -> 0 | AT42: =AS42*AR42 -> 0 | AU42: =IF(AL42="","",TODAY()-AL42) | AV42: =IF(AM42="","",IF(AND(AM42<TODAY(),$AF42<>"Customer",$AF42<>"Lost",$AF42<>"Not a fit"),"OVERDUE","")) | AW42: =IF(AV42="OVERDUE","RED",IF($AF42="Not started","—",IF($AF42="Customer","GREEN",IF(OR($AF42="Lost",$AF42="Not a fit"),"CLOSED","AMBER")))) -> —
A43: 42 | B43: C | C43: =IF(OR(B43="A",B43="B"),"Yes","No") -> No | E43: Reformas El Masnou SL | F43: Reformas El Masnou | H43: 4329 | I43: Other construction installation | J43: S.L. | K43: El Masnou | L43: Barcelona | M43: 55.6 | N43: Medium | O43: L1 | P43: 43.2x installer family — maintenance-mix unknown | Q43: Sector-default only (Verifactu 2027 + quarterly filing cycle; no firm-specific signal in this extraction) | R43: Installer-coded (CNAE or name); project-work chapters transfer, but a maintenance-revenue share (unconfirmed) forces a recurring-contract object the vertical layer lacks. | U43: Investment case — Pack 1 — a recurring-contract and work-order capability for project-led installers (8 firms) | V43: 935647867 | AC43: https://www.einforma.com/informacion-empresa/reformas-masnou | AD43: =COUNTA(V43:AA43) -> 1 | AF43: Not started | AO43: =IFERROR(INDEX(Playbook!$C$4:$C$17,MATCH($AF43,Playbook!$A$4:$A$17,0)),"") -> Read the row: tier, segment, trigger, reason we lose them. Check contact coverage; if 0, enrich before anything else. | AP43: =IFERROR(INDEX(Playbook!$D$4:$D$17,MATCH($AF43,Playbook!$A$4:$A$17,0)),"") -> — | AQ43: =IFERROR(INDEX(Playbook!$E$4:$E$17,MATCH($AF43,Playbook!$A$4:$A$17,0)),"") -> Row read and a contact channel exists | AR43: =IFERROR(INDEX(Playbook!$G$4:$G$17,MATCH($AF43,Playbook!$A$4:$A$17,0)),0) -> 0 | AS43: =IFERROR(INDEX('Pricing & Pilot'!$D$4:$D$6,MATCH($D43,'Pricing & Pilot'!$A$4:$A$6,0)),0) -> 0 | AT43: =AS43*AR43 -> 0 | AU43: =IF(AL43="","",TODAY()-AL43) | AV43: =IF(AM43="","",IF(AND(AM43<TODAY(),$AF43<>"Customer",$AF43<>"Lost",$AF43<>"Not a fit"),"OVERDUE","")) | AW43: =IF(AV43="OVERDUE","RED",IF($AF43="Not started","—",IF($AF43="Customer","GREEN",IF(OR($AF43="Lost",$AF43="Not a fit"),"CLOSED","AMBER")))) -> —
A44: 43 | B44: C | C44: =IF(OR(B44="A",B44="B"),"Yes","No") -> No | E44: Terramajor Reformas Y Construcciones SL | F44: Terramajor Reformas Y Construcciones | G44: B66511270 | H44: 4329 | I44: Other construction installation | J44: S.L. | K44: Terrassa | L44: Barcelona | M44: 55.6 | N44: Medium | O44: L1 | P44: 43.2x installer family — maintenance-mix unknown | Q44: Sector-default only (Verifactu 2027 + quarterly filing cycle; no firm-specific signal in this extraction) | R44: Installer-coded (CNAE or name); project-work chapters transfer, but a maintenance-revenue share (unconfirmed) forces a recurring-contract object the vertical layer lacks. | U44: Investment case — Pack 1 — a recurring-contract and work-order capability for project-led installers (8 firms) | AC44: https://www.einforma.com/informacion-empresa/terramajor-reformas-construcciones | AD44: =COUNTA(V44:AA44) -> 0 | AF44: Not started | AO44: =IFERROR(INDEX(Playbook!$C$4:$C$17,MATCH($AF44,Playbook!$A$4:$A$17,0)),"") -> Read the row: tier, segment, trigger, reason we lose them. Check contact coverage; if 0, enrich before anything else. | AP44: =IFERROR(INDEX(Playbook!$D$4:$D$17,MATCH($AF44,Playbook!$A$4:$A$17,0)),"") -> — | AQ44: =IFERROR(INDEX(Playbook!$E$4:$E$17,MATCH($AF44,Playbook!$A$4:$A$17,0)),"") -> Row read and a contact channel exists | AR44: =IFERROR(INDEX(Playbook!$G$4:$G$17,MATCH($AF44,Playbook!$A$4:$A$17,0)),0) -> 0 | AS44: =IFERROR(INDEX('Pricing & Pilot'!$D$4:$D$6,MATCH($D44,'Pricing & Pilot'!$A$4:$A$6,0)),0) -> 0 | AT44: =AS44*AR44 -> 0 | AU44: =IF(AL44="","",TODAY()-AL44) | AV44: =IF(AM44="","",IF(AND(AM44<TODAY(),$AF44<>"Customer",$AF44<>"Lost",$AF44<>"Not a fit"),"OVERDUE","")) | AW44: =IF(AV44="OVERDUE","RED",IF($AF44="Not started","—",IF($AF44="Customer","GREEN",IF(OR($AF44="Lost",$AF44="Not a fit"),"CLOSED","AMBER")))) -> —
A45: 44 | B45: C | C45: =IF(OR(B45="A",B45="B"),"Yes","No") -> No | E45: Instalaciones Y Reformas Megar SL | F45: Instalaciones Y Reformas Megar | J45: S.L. | K45: Terrassa | L45: Barcelona | M45: 51.6 | N45: Low | O45: L1 | P45: name-inferred installer — no CNAE | Q45: Sector-default only (Verifactu 2027 + quarterly filing cycle; no firm-specific signal in this extraction) | R45: Installer-coded (CNAE or name); project-work chapters transfer, but a maintenance-revenue share (unconfirmed) forces a recurring-contract object the vertical layer lacks. | U45: Investment case — Pack 1 — a recurring-contract and work-order capability for project-led installers (8 firms) | AC45: https://empresite.eleconomista.es/4PEOPLE-MEDIA.html | AD45: =COUNTA(V45:AA45) -> 0 | AF45: Not started | AO45: =IFERROR(INDEX(Playbook!$C$4:$C$17,MATCH($AF45,Playbook!$A$4:$A$17,0)),"") -> Read the row: tier, segment, trigger, reason we lose them. Check contact coverage; if 0, enrich before anything else. | AP45: =IFERROR(INDEX(Playbook!$D$4:$D$17,MATCH($AF45,Playbook!$A$4:$A$17,0)),"") -> — | AQ45: =IFERROR(INDEX(Playbook!$E$4:$E$17,MATCH($AF45,Playbook!$A$4:$A$17,0)),"") -> Row read and a contact channel exists | AR45: =IFERROR(INDEX(Playbook!$G$4:$G$17,MATCH($AF45,Playbook!$A$4:$A$17,0)),0) -> 0 | AS45: =IFERROR(INDEX('Pricing & Pilot'!$D$4:$D$6,MATCH($D45,'Pricing & Pilot'!$A$4:$A$6,0)),0) -> 0 | AT45: =AS45*AR45 -> 0 | AU45: =IF(AL45="","",TODAY()-AL45) | AV45: =IF(AM45="","",IF(AND(AM45<TODAY(),$AF45<>"Customer",$AF45<>"Lost",$AF45<>"Not a fit"),"OVERDUE","")) | AW45: =IF(AV45="OVERDUE","RED",IF($AF45="Not started","—",IF($AF45="Customer","GREEN",IF(OR($AF45="Lost",$AF45="Not a fit"),"CLOSED","AMBER")))) -> —
A46: 45 | B46: C | C46: =IF(OR(B46="A",B46="B"),"Yes","No") -> No | E46: Instalmar Castelldefels S.L. | F46: Instalmar Castelldefels | J46: S.L. | K46: Castelldefels | L46: Barcelona | M46: 51.6 | N46: Low | O46: L1 | P46: name-inferred installer — no CNAE | Q46: Sector-default only (Verifactu 2027 + quarterly filing cycle; no firm-specific signal in this extraction) | R46: Installer-coded (CNAE or name); project-work chapters transfer, but a maintenance-revenue share (unconfirmed) forces a recurring-contract object the vertical layer lacks. | U46: Investment case — Pack 1 — a recurring-contract and work-order capability for project-led installers (8 firms) | AC46: https://www.einforma.com/informacion-empresa/instalmar-castelldefels | AD46: =COUNTA(V46:AA46) -> 0 | AF46: Not started | AO46: =IFERROR(INDEX(Playbook!$C$4:$C$17,MATCH($AF46,Playbook!$A$4:$A$17,0)),"") -> Read the row: tier, segment, trigger, reason we lose them. Check contact coverage; if 0, enrich before anything else. | AP46: =IFERROR(INDEX(Playbook!$D$4:$D$17,MATCH($AF46,Playbook!$A$4:$A$17,0)),"") -> — | AQ46: =IFERROR(INDEX(Playbook!$E$4:$E$17,MATCH($AF46,Playbook!$A$4:$A$17,0)),"") -> Row read and a contact channel exists | AR46: =IFERROR(INDEX(Playbook!$G$4:$G$17,MATCH($AF46,Playbook!$A$4:$A$17,0)),0) -> 0 | AS46: =IFERROR(INDEX('Pricing & Pilot'!$D$4:$D$6,MATCH($D46,'Pricing & Pilot'!$A$4:$A$6,0)),0) -> 0 | AT46: =AS46*AR46 -> 0 | AU46: =IF(AL46="","",TODAY()-AL46) | AV46: =IF(AM46="","",IF(AND(AM46<TODAY(),$AF46<>"Customer",$AF46<>"Lost",$AF46<>"Not a fit"),"OVERDUE","")) | AW46: =IF(AV46="OVERDUE","RED",IF($AF46="Not started","—",IF($AF46="Customer","GREEN",IF(OR($AF46="Lost",$AF46="Not a fit"),"CLOSED","AMBER")))) -> —
A47: 46 | B47: C | C47: =IF(OR(B47="A",B47="B"),"Yes","No") -> No | E47: Izquierdo Instalaciones Y Reformas S.L. | F47: Izquierdo Instalaciones Y Reformas | G47: B66777459 | J47: S.L. | K47: L'Hospitalet de Llobregat | L47: Barcelona | M47: 51.6 | N47: Low | O47: L1 | P47: name-inferred installer — no CNAE | Q47: Sector-default only (Verifactu 2027 + quarterly filing cycle; no firm-specific signal in this extraction) | R47: Installer-coded (CNAE or name); project-work chapters transfer, but a maintenance-revenue share (unconfirmed) forces a recurring-contract object the vertical layer lacks. | U47: Investment case — Pack 1 — a recurring-contract and work-order capability for project-led installers (8 firms) | V47: 933381548 | X47: http://www.reformasizquierdo.com | AC47: https://infonif.economia3.com/ficha-empresa/izquierdo-instalaciones-y-reformas-sl, https://www.einforma.com/informacion-empresa/izquierdo-instalaciones-reformas | AD47: =COUNTA(V47:AA47) -> 2 | AF47: Not started | AO47: =IFERROR(INDEX(Playbook!$C$4:$C$17,MATCH($AF47,Playbook!$A$4:$A$17,0)),"") -> Read the row: tier, segment, trigger, reason we lose them. Check contact coverage; if 0, enrich before anything else. | AP47: =IFERROR(INDEX(Playbook!$D$4:$D$17,MATCH($AF47,Playbook!$A$4:$A$17,0)),"") -> — | AQ47: =IFERROR(INDEX(Playbook!$E$4:$E$17,MATCH($AF47,Playbook!$A$4:$A$17,0)),"") -> Row read and a contact channel exists | AR47: =IFERROR(INDEX(Playbook!$G$4:$G$17,MATCH($AF47,Playbook!$A$4:$A$17,0)),0) -> 0 | AS47: =IFERROR(INDEX('Pricing & Pilot'!$D$4:$D$6,MATCH($D47,'Pricing & Pilot'!$A$4:$A$6,0)),0) -> 0 | AT47: =AS47*AR47 -> 0 | AU47: =IF(AL47="","",TODAY()-AL47) | AV47: =IF(AM47="","",IF(AND(AM47<TODAY(),$AF47<>"Customer",$AF47<>"Lost",$AF47<>"Not a fit"),"OVERDUE","")) | AW47: =IF(AV47="OVERDUE","RED",IF($AF47="Not started","—",IF($AF47="Customer","GREEN",IF(OR($AF47="Lost",$AF47="Not a fit"),"CLOSED","AMBER")))) -> —
A48: 47 | B48: C | C48: =IF(OR(B48="A",B48="B"),"Yes","No") -> No | E48: Binder Meridian SL | F48: Binder Meridian | J48: S.L. | K48: Barcelona | L48: Barcelona | M48: 47.6 | N48: Low | O48: L2 | Q48: Sector-default only (Verifactu 2027 + quarterly filing cycle; no firm-specific signal in this extraction) | R48: QA found this entity to be a real-estate business, not a reformas/construction contractor. | U48: Investment case — Pack 3 — a promoción/real-estate capability (3 firms; recommend against investment) | AC48: https://www.einforma.com/informacion-empresa/binder-meridian | AD48: =COUNTA(V48:AA48) -> 0 | AF48: Not started | AO48: =IFERROR(INDEX(Playbook!$C$4:$C$17,MATCH($AF48,Playbook!$A$4:$A$17,0)),"") -> Read the row: tier, segment, trigger, reason we lose them. Check contact coverage; if 0, enrich before anything else. | AP48: =IFERROR(INDEX(Playbook!$D$4:$D$17,MATCH($AF48,Playbook!$A$4:$A$17,0)),"") -> — | AQ48: =IFERROR(INDEX(Playbook!$E$4:$E$17,MATCH($AF48,Playbook!$A$4:$A$17,0)),"") -> Row read and a contact channel exists | AR48: =IFERROR(INDEX(Playbook!$G$4:$G$17,MATCH($AF48,Playbook!$A$4:$A$17,0)),0) -> 0 | AS48: =IFERROR(INDEX('Pricing & Pilot'!$D$4:$D$6,MATCH($D48,'Pricing & Pilot'!$A$4:$A$6,0)),0) -> 0 | AT48: =AS48*AR48 -> 0 | AU48: =IF(AL48="","",TODAY()-AL48) | AV48: =IF(AM48="","",IF(AND(AM48<TODAY(),$AF48<>"Customer",$AF48<>"Lost",$AF48<>"Not a fit"),"OVERDUE","")) | AW48: =IF(AV48="OVERDUE","RED",IF($AF48="Not started","—",IF($AF48="Customer","GREEN",IF(OR($AF48="Lost",$AF48="Not a fit"),"CLOSED","AMBER")))) -> —
A49: 48 | B49: C | C49: =IF(OR(B49="A",B49="B"),"Yes","No") -> No | E49: Group Arfil SL | F49: Group Arfil | J49: S.L. | K49: Barcelona | L49: Barcelona | M49: 47.6 | N49: Low | O49: L2 | Q49: Sector-default only (Verifactu 2027 + quarterly filing cycle; no firm-specific signal in this extraction) | R49: QA found this entity to be a real-estate business, not a reformas/construction contractor. | U49: Investment case — Pack 3 — a promoción/real-estate capability (3 firms; recommend against investment) | AC49: https://www.einforma.com/informacion-empresa/group-arfil | AD49: =COUNTA(V49:AA49) -> 0 | AF49: Not started | AO49: =IFERROR(INDEX(Playbook!$C$4:$C$17,MATCH($AF49,Playbook!$A$4:$A$17,0)),"") -> Read the row: tier, segment, trigger, reason we lose them. Check contact coverage; if 0, enrich before anything else. | AP49: =IFERROR(INDEX(Playbook!$D$4:$D$17,MATCH($AF49,Playbook!$A$4:$A$17,0)),"") -> — | AQ49: =IFERROR(INDEX(Playbook!$E$4:$E$17,MATCH($AF49,Playbook!$A$4:$A$17,0)),"") -> Row read and a contact channel exists | AR49: =IFERROR(INDEX(Playbook!$G$4:$G$17,MATCH($AF49,Playbook!$A$4:$A$17,0)),0) -> 0 | AS49: =IFERROR(INDEX('Pricing & Pilot'!$D$4:$D$6,MATCH($D49,'Pricing & Pilot'!$A$4:$A$6,0)),0) -> 0 | AT49: =AS49*AR49 -> 0 | AU49: =IF(AL49="","",TODAY()-AL49) | AV49: =IF(AM49="","",IF(AND(AM49<TODAY(),$AF49<>"Customer",$AF49<>"Lost",$AF49<>"Not a fit"),"OVERDUE","")) | AW49: =IF(AV49="OVERDUE","RED",IF($AF49="Not started","—",IF($AF49="Customer","GREEN",IF(OR($AF49="Lost",$AF49="Not a fit"),"CLOSED","AMBER")))) -> —
A50: 49 | B50: C | C50: =IF(OR(B50="A",B50="B"),"Yes","No") -> No | E50: Reforma Integral Granollers Interiorisme SL | F50: Reforma Integral Granollers Interiorisme | H50: 4755 | J50: S.L. | K50: Granollers | L50: Barcelona | M50: 47.6 | N50: Medium | O50: L2 | Q50: Sector-default only (Verifactu 2027 + quarterly filing cycle; no firm-specific signal in this extraction) | R50: CNAE 47.55 is retail trade (household furnishings), not a construction contractor. | U50: Investment case — Pack 3 — a promoción/real-estate capability (3 firms; recommend against investment) | AC50: https://www.einforma.com/informacion-empresa/reforma-integral-granollers-interiorisme | AD50: =COUNTA(V50:AA50) -> 0 | AF50: Not started | AO50: =IFERROR(INDEX(Playbook!$C$4:$C$17,MATCH($AF50,Playbook!$A$4:$A$17,0)),"") -> Read the row: tier, segment, trigger, reason we lose them. Check contact coverage; if 0, enrich before anything else. | AP50: =IFERROR(INDEX(Playbook!$D$4:$D$17,MATCH($AF50,Playbook!$A$4:$A$17,0)),"") -> — | AQ50: =IFERROR(INDEX(Playbook!$E$4:$E$17,MATCH($AF50,Playbook!$A$4:$A$17,0)),"") -> Row read and a contact channel exists | AR50: =IFERROR(INDEX(Playbook!$G$4:$G$17,MATCH($AF50,Playbook!$A$4:$A$17,0)),0) -> 0 | AS50: =IFERROR(INDEX('Pricing & Pilot'!$D$4:$D$6,MATCH($D50,'Pricing & Pilot'!$A$4:$A$6,0)),0) -> 0 | AT50: =AS50*AR50 -> 0 | AU50: =IF(AL50="","",TODAY()-AL50) | AV50: =IF(AM50="","",IF(AND(AM50<TODAY(),$AF50<>"Customer",$AF50<>"Lost",$AF50<>"Not a fit"),"OVERDUE","")) | AW50: =IF(AV50="OVERDUE","RED",IF($AF50="Not started","—",IF($AF50="Customer","GREEN",IF(OR($AF50="Lost",$AF50="Not a fit"),"CLOSED","AMBER")))) -> —
A51: 50 | B51: C | C51: =IF(OR(B51="A",B51="B"),"Yes","No") -> No | E51: Rubinense De Albañileria Y Construcciones S.L. | F51: Rubinense De Albañileria Y Construcciones | H51: 4299 | J51: S.L. | K51: Rubí | L51: Barcelona | M51: 47.6 | N51: Medium | O51: L2 | P51: 42.x civil engineering — excluded segment per ICP A.1 | Q51: Sector-default only (Verifactu 2027 + quarterly filing cycle; no firm-specific signal in this extraction) | R51: CNAE 42.99 (civil engineering) sits outside the ICP's construction-CNAE band; name suggests masonry, so this may be a mis-registration. | U51: Investment case — Pack 2 — a civil-engineering and site-preparation bridge (2 firms; recommend against investment) | AC51: https://www.einforma.com/informacion-empresa/rubinense-albanileria-construcciones | AD51: =COUNTA(V51:AA51) -> 0 | AF51: Not started | AO51: =IFERROR(INDEX(Playbook!$C$4:$C$17,MATCH($AF51,Playbook!$A$4:$A$17,0)),"") -> Read the row: tier, segment, trigger, reason we lose them. Check contact coverage; if 0, enrich before anything else. | AP51: =IFERROR(INDEX(Playbook!$D$4:$D$17,MATCH($AF51,Playbook!$A$4:$A$17,0)),"") -> — | AQ51: =IFERROR(INDEX(Playbook!$E$4:$E$17,MATCH($AF51,Playbook!$A$4:$A$17,0)),"") -> Row read and a contact channel exists | AR51: =IFERROR(INDEX(Playbook!$G$4:$G$17,MATCH($AF51,Playbook!$A$4:$A$17,0)),0) -> 0 | AS51: =IFERROR(INDEX('Pricing & Pilot'!$D$4:$D$6,MATCH($D51,'Pricing & Pilot'!$A$4:$A$6,0)),0) -> 0 | AT51: =AS51*AR51 -> 0 | AU51: =IF(AL51="","",TODAY()-AL51) | AV51: =IF(AM51="","",IF(AND(AM51<TODAY(),$AF51<>"Customer",$AF51<>"Lost",$AF51<>"Not a fit"),"OVERDUE","")) | AW51: =IF(AV51="OVERDUE","RED",IF($AF51="Not started","—",IF($AF51="Customer","GREEN",IF(OR($AF51="Lost",$AF51="Not a fit"),"CLOSED","AMBER")))) -> —
A52: 51 | B52: D | C52: =IF(OR(B52="A",B52="B"),"Yes","No") -> No | E52: CONIFER S.A. | F52: Conifer | H52: 4399 | I52: Other specialised construction activities | J52: S.A. | K52: Sant Cugat del Vallès | L52: Barcelona | M52: 62 | N52: Medium | O52: L0–L1 | P52: target 43.3/43.9 finishing family | Q52: Sector-default only (Verifactu 2027 + quarterly filing cycle; no firm-specific signal in this extraction) | R52: S.A. form, acceptable only if small; CNAE 4399 read as sector-confirming. | U52: Declined — Thin, isolated signal | AC52: https://www.einforma.com/informacion-empresa/conifer | AD52: =COUNTA(V52:AA52) -> 0 | AF52: Not started | AO52: =IFERROR(INDEX(Playbook!$C$4:$C$17,MATCH($AF52,Playbook!$A$4:$A$17,0)),"") -> Read the row: tier, segment, trigger, reason we lose them. Check contact coverage; if 0, enrich before anything else. | AP52: =IFERROR(INDEX(Playbook!$D$4:$D$17,MATCH($AF52,Playbook!$A$4:$A$17,0)),"") -> — | AQ52: =IFERROR(INDEX(Playbook!$E$4:$E$17,MATCH($AF52,Playbook!$A$4:$A$17,0)),"") -> Row read and a contact channel exists | AR52: =IFERROR(INDEX(Playbook!$G$4:$G$17,MATCH($AF52,Playbook!$A$4:$A$17,0)),0) -> 0 | AS52: =IFERROR(INDEX('Pricing & Pilot'!$D$4:$D$6,MATCH($D52,'Pricing & Pilot'!$A$4:$A$6,0)),0) -> 0 | AT52: =AS52*AR52 -> 0 | AU52: =IF(AL52="","",TODAY()-AL52) | AV52: =IF(AM52="","",IF(AND(AM52<TODAY(),$AF52<>"Customer",$AF52<>"Lost",$AF52<>"Not a fit"),"OVERDUE","")) | AW52: =IF(AV52="OVERDUE","RED",IF($AF52="Not started","—",IF($AF52="Customer","GREEN",IF(OR($AF52="Lost",$AF52="Not a fit"),"CLOSED","AMBER")))) -> —
A53: 52 | B53: D | C53: =IF(OR(B53="A",B53="B"),"Yes","No") -> No | E53: A Y D Construcciones Y Reformas Sabadell SL | F53: A Y D Construcciones Y Reformas Sabadell | J53: S.L. | K53: Sabadell | L53: Barcelona | M53: 55.6 | N53: Low | O53: L0–L1 | P53: name-inferred renovation — no CNAE | Q53: Sector-default only (Verifactu 2027 + quarterly filing cycle; no firm-specific signal in this extraction) | R53: S.L. form matches the reference tenant; no CNAE recovered — sector fit inferred from the trading name only. | AC53: https://empresite.eleconomista.es/AYD-CONSTRUCCIONES-REFORMAS-SABADELL.html | AD53: =COUNTA(V53:AA53) -> 0 | AF53: Not started | AO53: =IFERROR(INDEX(Playbook!$C$4:$C$17,MATCH($AF53,Playbook!$A$4:$A$17,0)),"") -> Read the row: tier, segment, trigger, reason we lose them. Check contact coverage; if 0, enrich before anything else. | AP53: =IFERROR(INDEX(Playbook!$D$4:$D$17,MATCH($AF53,Playbook!$A$4:$A$17,0)),"") -> — | AQ53: =IFERROR(INDEX(Playbook!$E$4:$E$17,MATCH($AF53,Playbook!$A$4:$A$17,0)),"") -> Row read and a contact channel exists | AR53: =IFERROR(INDEX(Playbook!$G$4:$G$17,MATCH($AF53,Playbook!$A$4:$A$17,0)),0) -> 0 | AS53: =IFERROR(INDEX('Pricing & Pilot'!$D$4:$D$6,MATCH($D53,'Pricing & Pilot'!$A$4:$A$6,0)),0) -> 0 | AT53: =AS53*AR53 -> 0 | AU53: =IF(AL53="","",TODAY()-AL53) | AV53: =IF(AM53="","",IF(AND(AM53<TODAY(),$AF53<>"Customer",$AF53<>"Lost",$AF53<>"Not a fit"),"OVERDUE","")) | AW53: =IF(AV53="OVERDUE","RED",IF($AF53="Not started","—",IF($AF53="Customer","GREEN",IF(OR($AF53="Lost",$AF53="Not a fit"),"CLOSED","AMBER")))) -> —
A54: 53 | B54: D | C54: =IF(OR(B54="A",B54="B"),"Yes","No") -> No | E54: Actua 2011 S.L. | F54: Actua 2011 | J54: S.L. | K54: Viladecans | L54: Barcelona | M54: 55.6 | N54: Low | O54: L0–L1 | P54: assumed from sourcing frame — no CNAE, no keyword | Q54: Sector-default only (Verifactu 2027 + quarterly filing cycle; no firm-specific signal in this extraction) | R54: S.L. form matches the reference tenant; no CNAE recovered — sector fit inferred from the trading name only. | X54: https://actua2011.es | AC54: https://actua2011.es/ | AD54: =COUNTA(V54:AA54) -> 1 | AF54: Not started | AO54: =IFERROR(INDEX(Playbook!$C$4:$C$17,MATCH($AF54,Playbook!$A$4:$A$17,0)),"") -> Read the row: tier, segment, trigger, reason we lose them. Check contact coverage; if 0, enrich before anything else. | AP54: =IFERROR(INDEX(Playbook!$D$4:$D$17,MATCH($AF54,Playbook!$A$4:$A$17,0)),"") -> — | AQ54: =IFERROR(INDEX(Playbook!$E$4:$E$17,MATCH($AF54,Playbook!$A$4:$A$17,0)),"") -> Row read and a contact channel exists | AR54: =IFERROR(INDEX(Playbook!$G$4:$G$17,MATCH($AF54,Playbook!$A$4:$A$17,0)),0) -> 0 | AS54: =IFERROR(INDEX('Pricing & Pilot'!$D$4:$D$6,MATCH($D54,'Pricing & Pilot'!$A$4:$A$6,0)),0) -> 0 | AT54: =AS54*AR54 -> 0 | AU54: =IF(AL54="","",TODAY()-AL54) | AV54: =IF(AM54="","",IF(AND(AM54<TODAY(),$AF54<>"Customer",$AF54<>"Lost",$AF54<>"Not a fit"),"OVERDUE","")) | AW54: =IF(AV54="OVERDUE","RED",IF($AF54="Not started","—",IF($AF54="Customer","GREEN",IF(OR($AF54="Lost",$AF54="Not a fit"),"CLOSED","AMBER")))) -> —
A55: 54 | B55: D | C55: =IF(OR(B55="A",B55="B"),"Yes","No") -> No | E55: Building Barcelona 2021 SL | F55: Building Barcelona 2021 | J55: S.L. | K55: Barcelona | L55: Barcelona | M55: 55.6 | N55: Low | O55: L0–L1 | P55: assumed from sourcing frame — no CNAE, no keyword | Q55: Sector-default only (Verifactu 2027 + quarterly filing cycle; no firm-specific signal in this extraction) | R55: S.L. form matches the reference tenant; no CNAE recovered — sector fit inferred from the trading name only. | AC55: https://www.einforma.com/informacion-empresa/building-barcelona-2021 | AD55: =COUNTA(V55:AA55) -> 0 | AF55: Not started | AO55: =IFERROR(INDEX(Playbook!$C$4:$C$17,MATCH($AF55,Playbook!$A$4:$A$17,0)),"") -> Read the row: tier, segment, trigger, reason we lose them. Check contact coverage; if 0, enrich before anything else. | AP55: =IFERROR(INDEX(Playbook!$D$4:$D$17,MATCH($AF55,Playbook!$A$4:$A$17,0)),"") -> — | AQ55: =IFERROR(INDEX(Playbook!$E$4:$E$17,MATCH($AF55,Playbook!$A$4:$A$17,0)),"") -> Row read and a contact channel exists | AR55: =IFERROR(INDEX(Playbook!$G$4:$G$17,MATCH($AF55,Playbook!$A$4:$A$17,0)),0) -> 0 | AS55: =IFERROR(INDEX('Pricing & Pilot'!$D$4:$D$6,MATCH($D55,'Pricing & Pilot'!$A$4:$A$6,0)),0) -> 0 | AT55: =AS55*AR55 -> 0 | AU55: =IF(AL55="","",TODAY()-AL55) | AV55: =IF(AM55="","",IF(AND(AM55<TODAY(),$AF55<>"Customer",$AF55<>"Lost",$AF55<>"Not a fit"),"OVERDUE","")) | AW55: =IF(AV55="OVERDUE","RED",IF($AF55="Not started","—",IF($AF55="Customer","GREEN",IF(OR($AF55="Lost",$AF55="Not a fit"),"CLOSED","AMBER")))) -> —
A56: 55 | B56: D | C56: =IF(OR(B56="A",B56="B"),"Yes","No") -> No | E56: Construcat Reformes I Serveis SL | F56: Construcat Reformes | G56: B13902903 | J56: S.L. | K56: Barcelona | L56: Barcelona | M56: 55.6 | N56: Low | O56: L0–L1 | P56: name-inferred renovation — no CNAE | Q56: Sector-default only (Verifactu 2027 + quarterly filing cycle; no firm-specific signal in this extraction) | R56: S.L. form matches the reference tenant; no CNAE recovered — sector fit inferred from the trading name only. | AC56: https://infonif.economia3.com/ficha-empresa/construcat-reformes-i-serveis-sl | AD56: =COUNTA(V56:AA56) -> 0 | AF56: Not started | AO56: =IFERROR(INDEX(Playbook!$C$4:$C$17,MATCH($AF56,Playbook!$A$4:$A$17,0)),"") -> Read the row: tier, segment, trigger, reason we lose them. Check contact coverage; if 0, enrich before anything else. | AP56: =IFERROR(INDEX(Playbook!$D$4:$D$17,MATCH($AF56,Playbook!$A$4:$A$17,0)),"") -> — | AQ56: =IFERROR(INDEX(Playbook!$E$4:$E$17,MATCH($AF56,Playbook!$A$4:$A$17,0)),"") -> Row read and a contact channel exists | AR56: =IFERROR(INDEX(Playbook!$G$4:$G$17,MATCH($AF56,Playbook!$A$4:$A$17,0)),0) -> 0 | AS56: =IFERROR(INDEX('Pricing & Pilot'!$D$4:$D$6,MATCH($D56,'Pricing & Pilot'!$A$4:$A$6,0)),0) -> 0 | AT56: =AS56*AR56 -> 0 | AU56: =IF(AL56="","",TODAY()-AL56) | AV56: =IF(AM56="","",IF(AND(AM56<TODAY(),$AF56<>"Customer",$AF56<>"Lost",$AF56<>"Not a fit"),"OVERDUE","")) | AW56: =IF(AV56="OVERDUE","RED",IF($AF56="Not started","—",IF($AF56="Customer","GREEN",IF(OR($AF56="Lost",$AF56="Not a fit"),"CLOSED","AMBER")))) -> —
A57: 56 | B57: D | C57: =IF(OR(B57="A",B57="B"),"Yes","No") -> No | E57: Construccialia Obras y Reformas SL | F57: Construccialia | J57: S.L. | K57: Barcelona | L57: Barcelona | M57: 55.6 | N57: Low | O57: L0–L1 | P57: name-inferred renovation — no CNAE | Q57: Sector-default only (Verifactu 2027 + quarterly filing cycle; no firm-specific signal in this extraction) | R57: S.L. form matches the reference tenant; no CNAE recovered — sector fit inferred from the trading name only. | AC57: https://www.axesor.es/Informes-Empresas/4980883/CONSTRUCCIALIA_OBRAS_Y_REFORMAS_SL.html | AD57: =COUNTA(V57:AA57) -> 0 | AF57: Not started | AO57: =IFERROR(INDEX(Playbook!$C$4:$C$17,MATCH($AF57,Playbook!$A$4:$A$17,0)),"") -> Read the row: tier, segment, trigger, reason we lose them. Check contact coverage; if 0, enrich before anything else. | AP57: =IFERROR(INDEX(Playbook!$D$4:$D$17,MATCH($AF57,Playbook!$A$4:$A$17,0)),"") -> — | AQ57: =IFERROR(INDEX(Playbook!$E$4:$E$17,MATCH($AF57,Playbook!$A$4:$A$17,0)),"") -> Row read and a contact channel exists | AR57: =IFERROR(INDEX(Playbook!$G$4:$G$17,MATCH($AF57,Playbook!$A$4:$A$17,0)),0) -> 0 | AS57: =IFERROR(INDEX('Pricing & Pilot'!$D$4:$D$6,MATCH($D57,'Pricing & Pilot'!$A$4:$A$6,0)),0) -> 0 | AT57: =AS57*AR57 -> 0 | AU57: =IF(AL57="","",TODAY()-AL57) | AV57: =IF(AM57="","",IF(AND(AM57<TODAY(),$AF57<>"Customer",$AF57<>"Lost",$AF57<>"Not a fit"),"OVERDUE","")) | AW57: =IF(AV57="OVERDUE","RED",IF($AF57="Not started","—",IF($AF57="Customer","GREEN",IF(OR($AF57="Lost",$AF57="Not a fit"),"CLOSED","AMBER")))) -> —
A58: 57 | B58: D | C58: =IF(OR(B58="A",B58="B"),"Yes","No") -> No | E58: Construcciones Metalicas Castelldefels S.L. | F58: Construcciones Metalicas Castelldefels | J58: S.L. | K58: Castelldefels | L58: Barcelona | M58: 55.6 | N58: Low | O58: L0–L1 | P58: name-inferred general construction — no CNAE | Q58: Sector-default only (Verifactu 2027 + quarterly filing cycle; no firm-specific signal in this extraction) | R58: S.L. form matches the reference tenant; no CNAE recovered — sector fit inferred from the trading name only. | AC58: https://www.einforma.com/informacion-empresa/construcciones-metalicas-castelldefels | AD58: =COUNTA(V58:AA58) -> 0 | AF58: Not started | AO58: =IFERROR(INDEX(Playbook!$C$4:$C$17,MATCH($AF58,Playbook!$A$4:$A$17,0)),"") -> Read the row: tier, segment, trigger, reason we lose them. Check contact coverage; if 0, enrich before anything else. | AP58: =IFERROR(INDEX(Playbook!$D$4:$D$17,MATCH($AF58,Playbook!$A$4:$A$17,0)),"") -> — | AQ58: =IFERROR(INDEX(Playbook!$E$4:$E$17,MATCH($AF58,Playbook!$A$4:$A$17,0)),"") -> Row read and a contact channel exists | AR58: =IFERROR(INDEX(Playbook!$G$4:$G$17,MATCH($AF58,Playbook!$A$4:$A$17,0)),0) -> 0 | AS58: =IFERROR(INDEX('Pricing & Pilot'!$D$4:$D$6,MATCH($D58,'Pricing & Pilot'!$A$4:$A$6,0)),0) -> 0 | AT58: =AS58*AR58 -> 0 | AU58: =IF(AL58="","",TODAY()-AL58) | AV58: =IF(AM58="","",IF(AND(AM58<TODAY(),$AF58<>"Customer",$AF58<>"Lost",$AF58<>"Not a fit"),"OVERDUE","")) | AW58: =IF(AV58="OVERDUE","RED",IF($AF58="Not started","—",IF($AF58="Customer","GREEN",IF(OR($AF58="Lost",$AF58="Not a fit"),"CLOSED","AMBER")))) -> —
A59: 58 | B59: D | C59: =IF(OR(B59="A",B59="B"),"Yes","No") -> No | E59: Construcciones Reformas y Fachadas Condal SL | F59: Construcciones Reformas y Fachadas Condal | J59: S.L. | K59: Barcelona | L59: Barcelona | M59: 55.6 | N59: Low | O59: L0–L1 | P59: name-inferred renovation — no CNAE | Q59: Sector-default only (Verifactu 2027 + quarterly filing cycle; no firm-specific signal in this extraction) | R59: S.L. form matches the reference tenant; no CNAE recovered — sector fit inferred from the trading name only. | AC59: https://www.axesor.es/Informes-Empresas/5408525/CONSTRUCCIONES_REFORMAS_Y_FACHADAS_CONDAL_SL.html | AD59: =COUNTA(V59:AA59) -> 0 | AF59: Not started | AO59: =IFERROR(INDEX(Playbook!$C$4:$C$17,MATCH($AF59,Playbook!$A$4:$A$17,0)),"") -> Read the row: tier, segment, trigger, reason we lose them. Check contact coverage; if 0, enrich before anything else. | AP59: =IFERROR(INDEX(Playbook!$D$4:$D$17,MATCH($AF59,Playbook!$A$4:$A$17,0)),"") -> — | AQ59: =IFERROR(INDEX(Playbook!$E$4:$E$17,MATCH($AF59,Playbook!$A$4:$A$17,0)),"") -> Row read and a contact channel exists | AR59: =IFERROR(INDEX(Playbook!$G$4:$G$17,MATCH($AF59,Playbook!$A$4:$A$17,0)),0) -> 0 | AS59: =IFERROR(INDEX('Pricing & Pilot'!$D$4:$D$6,MATCH($D59,'Pricing & Pilot'!$A$4:$A$6,0)),0) -> 0 | AT59: =AS59*AR59 -> 0 | AU59: =IF(AL59="","",TODAY()-AL59) | AV59: =IF(AM59="","",IF(AND(AM59<TODAY(),$AF59<>"Customer",$AF59<>"Lost",$AF59<>"Not a fit"),"OVERDUE","")) | AW59: =IF(AV59="OVERDUE","RED",IF($AF59="Not started","—",IF($AF59="Customer","GREEN",IF(OR($AF59="Lost",$AF59="Not a fit"),"CLOSED","AMBER")))) -> —
A60: 59 | B60: D | C60: =IF(OR(B60="A",B60="B"),"Yes","No") -> No | E60: Construcciones Trivia Rubi S.L. | F60: Construcciones Trivia Rubi | J60: S.L. | K60: Rubí | L60: Barcelona | M60: 55.6 | N60: Low | O60: L0–L1 | P60: name-inferred general construction — no CNAE | Q60: Sector-default only (Verifactu 2027 + quarterly filing cycle; no firm-specific signal in this extraction) | R60: S.L. form matches the reference tenant; no CNAE recovered — sector fit inferred from the trading name only. | AC60: https://www.einforma.com/informacion-empresa/construcciones-trivia-rubi | AD60: =COUNTA(V60:AA60) -> 0 | AF60: Not started | AO60: =IFERROR(INDEX(Playbook!$C$4:$C$17,MATCH($AF60,Playbook!$A$4:$A$17,0)),"") -> Read the row: tier, segment, trigger, reason we lose them. Check contact coverage; if 0, enrich before anything else. | AP60: =IFERROR(INDEX(Playbook!$D$4:$D$17,MATCH($AF60,Playbook!$A$4:$A$17,0)),"") -> — | AQ60: =IFERROR(INDEX(Playbook!$E$4:$E$17,MATCH($AF60,Playbook!$A$4:$A$17,0)),"") -> Row read and a contact channel exists | AR60: =IFERROR(INDEX(Playbook!$G$4:$G$17,MATCH($AF60,Playbook!$A$4:$A$17,0)),0) -> 0 | AS60: =IFERROR(INDEX('Pricing & Pilot'!$D$4:$D$6,MATCH($D60,'Pricing & Pilot'!$A$4:$A$6,0)),0) -> 0 | AT60: =AS60*AR60 -> 0 | AU60: =IF(AL60="","",TODAY()-AL60) | AV60: =IF(AM60="","",IF(AND(AM60<TODAY(),$AF60<>"Customer",$AF60<>"Lost",$AF60<>"Not a fit"),"OVERDUE","")) | AW60: =IF(AV60="OVERDUE","RED",IF($AF60="Not started","—",IF($AF60="Customer","GREEN",IF(OR($AF60="Lost",$AF60="Not a fit"),"CLOSED","AMBER")))) -> —
A61: 60 | B61: D | C61: =IF(OR(B61="A",B61="B"),"Yes","No") -> No | E61: Construcciones Y Reformas Amrah Gold SL | F61: Construcciones Y Reformas Amrah Gold | J61: S.L. | K61: Granollers | L61: Barcelona | M61: 55.6 | N61: Low | O61: L0–L1 | P61: name-inferred renovation — no CNAE | Q61: Sector-default only (Verifactu 2027 + quarterly filing cycle; no firm-specific signal in this extraction) | R61: S.L. form matches the reference tenant; no CNAE recovered — sector fit inferred from the trading name only. | AC61: https://www.einforma.com/informacion-empresa/construcciones-reformas-amrah-gold | AD61: =COUNTA(V61:AA61) -> 0 | AF61: Not started | AO61: =IFERROR(INDEX(Playbook!$C$4:$C$17,MATCH($AF61,Playbook!$A$4:$A$17,0)),"") -> Read the row: tier, segment, trigger, reason we lose them. Check contact coverage; if 0, enrich before anything else. | AP61: =IFERROR(INDEX(Playbook!$D$4:$D$17,MATCH($AF61,Playbook!$A$4:$A$17,0)),"") -> — | AQ61: =IFERROR(INDEX(Playbook!$E$4:$E$17,MATCH($AF61,Playbook!$A$4:$A$17,0)),"") -> Row read and a contact channel exists | AR61: =IFERROR(INDEX(Playbook!$G$4:$G$17,MATCH($AF61,Playbook!$A$4:$A$17,0)),0) -> 0 | AS61: =IFERROR(INDEX('Pricing & Pilot'!$D$4:$D$6,MATCH($D61,'Pricing & Pilot'!$A$4:$A$6,0)),0) -> 0 | AT61: =AS61*AR61 -> 0 | AU61: =IF(AL61="","",TODAY()-AL61) | AV61: =IF(AM61="","",IF(AND(AM61<TODAY(),$AF61<>"Customer",$AF61<>"Lost",$AF61<>"Not a fit"),"OVERDUE","")) | AW61: =IF(AV61="OVERDUE","RED",IF($AF61="Not started","—",IF($AF61="Customer","GREEN",IF(OR($AF61="Lost",$AF61="Not a fit"),"CLOSED","AMBER")))) -> —
A62: 61 | B62: D | C62: =IF(OR(B62="A",B62="B"),"Yes","No") -> No | E62: Construcciones y Reformas Barna Valles SL | F62: Construcciones y Reformas Barna Valles | J62: S.L. | K62: Barcelona | L62: Barcelona | M62: 55.6 | N62: Low | O62: L0–L1 | P62: name-inferred renovation — no CNAE | Q62: Sector-default only (Verifactu 2027 + quarterly filing cycle; no firm-specific signal in this extraction) | R62: S.L. form matches the reference tenant; no CNAE recovered — sector fit inferred from the trading name only. | AC62: https://www.axesor.es/Informes-Empresas/2681080/CONSTRUCCIONES_Y_REFORMAS_BARNA_VALLES_SL.html | AD62: =COUNTA(V62:AA62) -> 0 | AF62: Not started | AO62: =IFERROR(INDEX(Playbook!$C$4:$C$17,MATCH($AF62,Playbook!$A$4:$A$17,0)),"") -> Read the row: tier, segment, trigger, reason we lose them. Check contact coverage; if 0, enrich before anything else. | AP62: =IFERROR(INDEX(Playbook!$D$4:$D$17,MATCH($AF62,Playbook!$A$4:$A$17,0)),"") -> — | AQ62: =IFERROR(INDEX(Playbook!$E$4:$E$17,MATCH($AF62,Playbook!$A$4:$A$17,0)),"") -> Row read and a contact channel exists | AR62: =IFERROR(INDEX(Playbook!$G$4:$G$17,MATCH($AF62,Playbook!$A$4:$A$17,0)),0) -> 0 | AS62: =IFERROR(INDEX('Pricing & Pilot'!$D$4:$D$6,MATCH($D62,'Pricing & Pilot'!$A$4:$A$6,0)),0) -> 0 | AT62: =AS62*AR62 -> 0 | AU62: =IF(AL62="","",TODAY()-AL62) | AV62: =IF(AM62="","",IF(AND(AM62<TODAY(),$AF62<>"Customer",$AF62<>"Lost",$AF62<>"Not a fit"),"OVERDUE","")) | AW62: =IF(AV62="OVERDUE","RED",IF($AF62="Not started","—",IF($AF62="Customer","GREEN",IF(OR($AF62="Lost",$AF62="Not a fit"),"CLOSED","AMBER")))) -> —
A63: 62 | B63: D | C63: =IF(OR(B63="A",B63="B"),"Yes","No") -> No | E63: Construcciones y Reformas Comahe SL | F63: Construcciones y Reformas Comahe | J63: S.L. | K63: Barcelona | L63: Barcelona | M63: 55.6 | N63: Low | O63: L0–L1 | P63: name-inferred renovation — no CNAE | Q63: Sector-default only (Verifactu 2027 + quarterly filing cycle; no firm-specific signal in this extraction) | R63: S.L. form matches the reference tenant; no CNAE recovered — sector fit inferred from the trading name only. | AC63: https://ranking-empresas.eleconomista.es/CONSTRUCCIONES-REFORMAS-COMAHE.html | AD63: =COUNTA(V63:AA63) -> 0 | AF63: Not started | AO63: =IFERROR(INDEX(Playbook!$C$4:$C$17,MATCH($AF63,Playbook!$A$4:$A$17,0)),"") -> Read the row: tier, segment, trigger, reason we lose them. Check contact coverage; if 0, enrich before anything else. | AP63: =IFERROR(INDEX(Playbook!$D$4:$D$17,MATCH($AF63,Playbook!$A$4:$A$17,0)),"") -> — | AQ63: =IFERROR(INDEX(Playbook!$E$4:$E$17,MATCH($AF63,Playbook!$A$4:$A$17,0)),"") -> Row read and a contact channel exists | AR63: =IFERROR(INDEX(Playbook!$G$4:$G$17,MATCH($AF63,Playbook!$A$4:$A$17,0)),0) -> 0 | AS63: =IFERROR(INDEX('Pricing & Pilot'!$D$4:$D$6,MATCH($D63,'Pricing & Pilot'!$A$4:$A$6,0)),0) -> 0 | AT63: =AS63*AR63 -> 0 | AU63: =IF(AL63="","",TODAY()-AL63) | AV63: =IF(AM63="","",IF(AND(AM63<TODAY(),$AF63<>"Customer",$AF63<>"Lost",$AF63<>"Not a fit"),"OVERDUE","")) | AW63: =IF(AV63="OVERDUE","RED",IF($AF63="Not started","—",IF($AF63="Customer","GREEN",IF(OR($AF63="Lost",$AF63="Not a fit"),"CLOSED","AMBER")))) -> —
A64: 63 | B64: D | C64: =IF(OR(B64="A",B64="B"),"Yes","No") -> No | E64: Construcciones y Reformas Leus SL | F64: Construcciones y Reformas Leus | J64: S.L. | K64: Barcelona | L64: Barcelona | M64: 55.6 | N64: Low | O64: L0–L1 | P64: name-inferred renovation — no CNAE | Q64: Sector-default only (Verifactu 2027 + quarterly filing cycle; no firm-specific signal in this extraction) | R64: S.L. form matches the reference tenant; no CNAE recovered — sector fit inferred from the trading name only. | AC64: https://www.axesor.es/Informes-Empresas/11312148/CONSTRUCCIONES_Y_REFORMAS_LEUS_SL.html, https://www.einforma.com/informacion-empresa/construcciones-reformas-leus | AD64: =COUNTA(V64:AA64) -> 0 | AF64: Not started | AO64: =IFERROR(INDEX(Playbook!$C$4:$C$17,MATCH($AF64,Playbook!$A$4:$A$17,0)),"") -> Read the row: tier, segment, trigger, reason we lose them. Check contact coverage; if 0, enrich before anything else. | AP64: =IFERROR(INDEX(Playbook!$D$4:$D$17,MATCH($AF64,Playbook!$A$4:$A$17,0)),"") -> — | AQ64: =IFERROR(INDEX(Playbook!$E$4:$E$17,MATCH($AF64,Playbook!$A$4:$A$17,0)),"") -> Row read and a contact channel exists | AR64: =IFERROR(INDEX(Playbook!$G$4:$G$17,MATCH($AF64,Playbook!$A$4:$A$17,0)),0) -> 0 | AS64: =IFERROR(INDEX('Pricing & Pilot'!$D$4:$D$6,MATCH($D64,'Pricing & Pilot'!$A$4:$A$6,0)),0) -> 0 | AT64: =AS64*AR64 -> 0 | AU64: =IF(AL64="","",TODAY()-AL64) | AV64: =IF(AM64="","",IF(AND(AM64<TODAY(),$AF64<>"Customer",$AF64<>"Lost",$AF64<>"Not a fit"),"OVERDUE","")) | AW64: =IF(AV64="OVERDUE","RED",IF($AF64="Not started","—",IF($AF64="Customer","GREEN",IF(OR($AF64="Lost",$AF64="Not a fit"),"CLOSED","AMBER")))) -> —
A65: 64 | B65: D | C65: =IF(OR(B65="A",B65="B"),"Yes","No") -> No | E65: Construcciones y Reformas Macias S.L. | F65: Construcciones y Reformas Macias | G65: B63228753 | J65: S.L. | K65: Cornellà de Llobregat | L65: Barcelona | M65: 55.6 | N65: Low | O65: L0–L1 | P65: name-inferred renovation — no CNAE | Q65: Sector-default only (Verifactu 2027 + quarterly filing cycle; no firm-specific signal in this extraction) | R65: S.L. form matches the reference tenant; no CNAE recovered — sector fit inferred from the trading name only. | AC65: https://empresite.eleconomista.es/CONSTRUCCIONES-REFORMAS-MACIAS.html, https://www.einforma.com/informacion-empresa/construcciones-reformas-macias | AD65: =COUNTA(V65:AA65) -> 0 | AF65: Not started | AO65: =IFERROR(INDEX(Playbook!$C$4:$C$17,MATCH($AF65,Playbook!$A$4:$A$17,0)),"") -> Read the row: tier, segment, trigger, reason we lose them. Check contact coverage; if 0, enrich before anything else. | AP65: =IFERROR(INDEX(Playbook!$D$4:$D$17,MATCH($AF65,Playbook!$A$4:$A$17,0)),"") -> — | AQ65: =IFERROR(INDEX(Playbook!$E$4:$E$17,MATCH($AF65,Playbook!$A$4:$A$17,0)),"") -> Row read and a contact channel exists | AR65: =IFERROR(INDEX(Playbook!$G$4:$G$17,MATCH($AF65,Playbook!$A$4:$A$17,0)),0) -> 0 | AS65: =IFERROR(INDEX('Pricing & Pilot'!$D$4:$D$6,MATCH($D65,'Pricing & Pilot'!$A$4:$A$6,0)),0) -> 0 | AT65: =AS65*AR65 -> 0 | AU65: =IF(AL65="","",TODAY()-AL65) | AV65: =IF(AM65="","",IF(AND(AM65<TODAY(),$AF65<>"Customer",$AF65<>"Lost",$AF65<>"Not a fit"),"OVERDUE","")) | AW65: =IF(AV65="OVERDUE","RED",IF($AF65="Not started","—",IF($AF65="Customer","GREEN",IF(OR($AF65="Lost",$AF65="Not a fit"),"CLOSED","AMBER")))) -> —
A66: 65 | B66: D | C66: =IF(OR(B66="A",B66="B"),"Yes","No") -> No | E66: Construcciones Y Reformas Manresa SL | F66: Construcciones Y Reformas Manresa | G66: B61066163 | J66: S.L. | K66: Manresa | L66: Barcelona | M66: 55.6 | N66: Low | O66: L0–L1 | P66: name-inferred renovation — no CNAE | Q66: Sector-default only (Verifactu 2027 + quarterly filing cycle; no firm-specific signal in this extraction) | R66: S.L. form matches the reference tenant; no CNAE recovered — sector fit inferred from the trading name only. | AC66: https://empresite.eleconomista.es/CONSTRUCCIONES-REFORMAS-MANRESA.html | AD66: =COUNTA(V66:AA66) -> 0 | AF66: Not started | AO66: =IFERROR(INDEX(Playbook!$C$4:$C$17,MATCH($AF66,Playbook!$A$4:$A$17,0)),"") -> Read the row: tier, segment, trigger, reason we lose them. Check contact coverage; if 0, enrich before anything else. | AP66: =IFERROR(INDEX(Playbook!$D$4:$D$17,MATCH($AF66,Playbook!$A$4:$A$17,0)),"") -> — | AQ66: =IFERROR(INDEX(Playbook!$E$4:$E$17,MATCH($AF66,Playbook!$A$4:$A$17,0)),"") -> Row read and a contact channel exists | AR66: =IFERROR(INDEX(Playbook!$G$4:$G$17,MATCH($AF66,Playbook!$A$4:$A$17,0)),0) -> 0 | AS66: =IFERROR(INDEX('Pricing & Pilot'!$D$4:$D$6,MATCH($D66,'Pricing & Pilot'!$A$4:$A$6,0)),0) -> 0 | AT66: =AS66*AR66 -> 0 | AU66: =IF(AL66="","",TODAY()-AL66) | AV66: =IF(AM66="","",IF(AND(AM66<TODAY(),$AF66<>"Customer",$AF66<>"Lost",$AF66<>"Not a fit"),"OVERDUE","")) | AW66: =IF(AV66="OVERDUE","RED",IF($AF66="Not started","—",IF($AF66="Customer","GREEN",IF(OR($AF66="Lost",$AF66="Not a fit"),"CLOSED","AMBER")))) -> —
A67: 66 | B67: D | C67: =IF(OR(B67="A",B67="B"),"Yes","No") -> No | E67: Construcciones y Reformas Perfil SL | F67: Construcciones y Reformas Perfil | J67: S.L. | K67: Barcelona | L67: Barcelona | M67: 55.6 | N67: Low | O67: L0–L1 | P67: name-inferred renovation — no CNAE | Q67: Sector-default only (Verifactu 2027 + quarterly filing cycle; no firm-specific signal in this extraction) | R67: S.L. form matches the reference tenant; no CNAE recovered — sector fit inferred from the trading name only. | AC67: https://www.axesor.es/Informes-Empresas/1454862/CONSTRUCCIONES_Y_REFORMAS_PERFIL_SL.html | AD67: =COUNTA(V67:AA67) -> 0 | AF67: Not started | AO67: =IFERROR(INDEX(Playbook!$C$4:$C$17,MATCH($AF67,Playbook!$A$4:$A$17,0)),"") -> Read the row: tier, segment, trigger, reason we lose them. Check contact coverage; if 0, enrich before anything else. | AP67: =IFERROR(INDEX(Playbook!$D$4:$D$17,MATCH($AF67,Playbook!$A$4:$A$17,0)),"") -> — | AQ67: =IFERROR(INDEX(Playbook!$E$4:$E$17,MATCH($AF67,Playbook!$A$4:$A$17,0)),"") -> Row read and a contact channel exists | AR67: =IFERROR(INDEX(Playbook!$G$4:$G$17,MATCH($AF67,Playbook!$A$4:$A$17,0)),0) -> 0 | AS67: =IFERROR(INDEX('Pricing & Pilot'!$D$4:$D$6,MATCH($D67,'Pricing & Pilot'!$A$4:$A$6,0)),0) -> 0 | AT67: =AS67*AR67 -> 0 | AU67: =IF(AL67="","",TODAY()-AL67) | AV67: =IF(AM67="","",IF(AND(AM67<TODAY(),$AF67<>"Customer",$AF67<>"Lost",$AF67<>"Not a fit"),"OVERDUE","")) | AW67: =IF(AV67="OVERDUE","RED",IF($AF67="Not started","—",IF($AF67="Customer","GREEN",IF(OR($AF67="Lost",$AF67="Not a fit"),"CLOSED","AMBER")))) -> —
A68: 67 | B68: D | C68: =IF(OR(B68="A",B68="B"),"Yes","No") -> No | E68: Construmarket Gavà 3000 S.L. | F68: Construmarket Gavà 3000 | J68: S.L. | K68: Gavà | L68: Barcelona | M68: 55.6 | N68: Low | O68: L0–L1 | P68: assumed from sourcing frame — no CNAE, no keyword | Q68: Sector-default only (Verifactu 2027 + quarterly filing cycle; no firm-specific signal in this extraction) | R68: S.L. form matches the reference tenant; no CNAE recovered — sector fit inferred from the trading name only. | V68: 936629180 | AC68: https://www.einforma.com/informacion-empresa/construmarket-gava-3000 | AD68: =COUNTA(V68:AA68) -> 1 | AF68: Not started | AO68: =IFERROR(INDEX(Playbook!$C$4:$C$17,MATCH($AF68,Playbook!$A$4:$A$17,0)),"") -> Read the row: tier, segment, trigger, reason we lose them. Check contact coverage; if 0, enrich before anything else. | AP68: =IFERROR(INDEX(Playbook!$D$4:$D$17,MATCH($AF68,Playbook!$A$4:$A$17,0)),"") -> — | AQ68: =IFERROR(INDEX(Playbook!$E$4:$E$17,MATCH($AF68,Playbook!$A$4:$A$17,0)),"") -> Row read and a contact channel exists | AR68: =IFERROR(INDEX(Playbook!$G$4:$G$17,MATCH($AF68,Playbook!$A$4:$A$17,0)),0) -> 0 | AS68: =IFERROR(INDEX('Pricing & Pilot'!$D$4:$D$6,MATCH($D68,'Pricing & Pilot'!$A$4:$A$6,0)),0) -> 0 | AT68: =AS68*AR68 -> 0 | AU68: =IF(AL68="","",TODAY()-AL68) | AV68: =IF(AM68="","",IF(AND(AM68<TODAY(),$AF68<>"Customer",$AF68<>"Lost",$AF68<>"Not a fit"),"OVERDUE","")) | AW68: =IF(AV68="OVERDUE","RED",IF($AF68="Not started","—",IF($AF68="Customer","GREEN",IF(OR($AF68="Lost",$AF68="Not a fit"),"CLOSED","AMBER")))) -> —
A69: 68 | B69: D | C69: =IF(OR(B69="A",B69="B"),"Yes","No") -> No | E69: Eco Reformas De Barcelona SL | F69: Eco Reformas De Barcelona | J69: S.L. | K69: Barcelona | L69: Barcelona | M69: 55.6 | N69: Low | O69: L0–L1 | P69: name-inferred renovation — no CNAE | Q69: Sector-default only (Verifactu 2027 + quarterly filing cycle; no firm-specific signal in this extraction) | R69: S.L. form matches the reference tenant; no CNAE recovered — sector fit inferred from the trading name only. | AC69: https://www.einforma.com/informacion-empresa/eco-reformas-barcelona | AD69: =COUNTA(V69:AA69) -> 0 | AF69: Not started | AO69: =IFERROR(INDEX(Playbook!$C$4:$C$17,MATCH($AF69,Playbook!$A$4:$A$17,0)),"") -> Read the row: tier, segment, trigger, reason we lose them. Check contact coverage; if 0, enrich before anything else. | AP69: =IFERROR(INDEX(Playbook!$D$4:$D$17,MATCH($AF69,Playbook!$A$4:$A$17,0)),"") -> — | AQ69: =IFERROR(INDEX(Playbook!$E$4:$E$17,MATCH($AF69,Playbook!$A$4:$A$17,0)),"") -> Row read and a contact channel exists | AR69: =IFERROR(INDEX(Playbook!$G$4:$G$17,MATCH($AF69,Playbook!$A$4:$A$17,0)),0) -> 0 | AS69: =IFERROR(INDEX('Pricing & Pilot'!$D$4:$D$6,MATCH($D69,'Pricing & Pilot'!$A$4:$A$6,0)),0) -> 0 | AT69: =AS69*AR69 -> 0 | AU69: =IF(AL69="","",TODAY()-AL69) | AV69: =IF(AM69="","",IF(AND(AM69<TODAY(),$AF69<>"Customer",$AF69<>"Lost",$AF69<>"Not a fit"),"OVERDUE","")) | AW69: =IF(AV69="OVERDUE","RED",IF($AF69="Not started","—",IF($AF69="Customer","GREEN",IF(OR($AF69="Lost",$AF69="Not a fit"),"CLOSED","AMBER")))) -> —
A70: 69 | B70: D | C70: =IF(OR(B70="A",B70="B"),"Yes","No") -> No | E70: Estudio Reformas Barcelona SL | F70: Estudio Reformas Barcelona | G70: B09831157 | J70: S.L. | K70: Barcelona | L70: Barcelona | M70: 55.6 | N70: Low | O70: L0–L1 | P70: name-inferred renovation — no CNAE | Q70: Sector-default only (Verifactu 2027 + quarterly filing cycle; no firm-specific signal in this extraction) | R70: S.L. form matches the reference tenant; no CNAE recovered — sector fit inferred from the trading name only. | AC70: https://www.datoscif.es/empresa/estudio-reformas-barcelona-sl, https://www.einforma.com/informacion-empresa/estudio-reformas-barcelona | AD70: =COUNTA(V70:AA70) -> 0 | AF70: Not started | AO70: =IFERROR(INDEX(Playbook!$C$4:$C$17,MATCH($AF70,Playbook!$A$4:$A$17,0)),"") -> Read the row: tier, segment, trigger, reason we lose them. Check contact coverage; if 0, enrich before anything else. | AP70: =IFERROR(INDEX(Playbook!$D$4:$D$17,MATCH($AF70,Playbook!$A$4:$A$17,0)),"") -> — | AQ70: =IFERROR(INDEX(Playbook!$E$4:$E$17,MATCH($AF70,Playbook!$A$4:$A$17,0)),"") -> Row read and a contact channel exists | AR70: =IFERROR(INDEX(Playbook!$G$4:$G$17,MATCH($AF70,Playbook!$A$4:$A$17,0)),0) -> 0 | AS70: =IFERROR(INDEX('Pricing & Pilot'!$D$4:$D$6,MATCH($D70,'Pricing & Pilot'!$A$4:$A$6,0)),0) -> 0 | AT70: =AS70*AR70 -> 0 | AU70: =IF(AL70="","",TODAY()-AL70) | AV70: =IF(AM70="","",IF(AND(AM70<TODAY(),$AF70<>"Customer",$AF70<>"Lost",$AF70<>"Not a fit"),"OVERDUE","")) | AW70: =IF(AV70="OVERDUE","RED",IF($AF70="Not started","—",IF($AF70="Customer","GREEN",IF(OR($AF70="Lost",$AF70="Not a fit"),"CLOSED","AMBER")))) -> —
A71: 70 | B71: D | C71: =IF(OR(B71="A",B71="B"),"Yes","No") -> No | E71: G&L Reformas Generales SL | F71: G&L Reformas Generales | J71: S.L. | K71: Granollers | L71: Barcelona | M71: 55.6 | N71: Low | O71: L0–L1 | P71: name-inferred renovation — no CNAE | Q71: Sector-default only (Verifactu 2027 + quarterly filing cycle; no firm-specific signal in this extraction) | R71: S.L. form matches the reference tenant; no CNAE recovered — sector fit inferred from the trading name only. | AC71: https://www.einforma.com/informacion-empresa/gl-reformas-generales | AD71: =COUNTA(V71:AA71) -> 0 | AF71: Not started | AO71: =IFERROR(INDEX(Playbook!$C$4:$C$17,MATCH($AF71,Playbook!$A$4:$A$17,0)),"") -> Read the row: tier, segment, trigger, reason we lose them. Check contact coverage; if 0, enrich before anything else. | AP71: =IFERROR(INDEX(Playbook!$D$4:$D$17,MATCH($AF71,Playbook!$A$4:$A$17,0)),"") -> — | AQ71: =IFERROR(INDEX(Playbook!$E$4:$E$17,MATCH($AF71,Playbook!$A$4:$A$17,0)),"") -> Row read and a contact channel exists | AR71: =IFERROR(INDEX(Playbook!$G$4:$G$17,MATCH($AF71,Playbook!$A$4:$A$17,0)),0) -> 0 | AS71: =IFERROR(INDEX('Pricing & Pilot'!$D$4:$D$6,MATCH($D71,'Pricing & Pilot'!$A$4:$A$6,0)),0) -> 0 | AT71: =AS71*AR71 -> 0 | AU71: =IF(AL71="","",TODAY()-AL71) | AV71: =IF(AM71="","",IF(AND(AM71<TODAY(),$AF71<>"Customer",$AF71<>"Lost",$AF71<>"Not a fit"),"OVERDUE","")) | AW71: =IF(AV71="OVERDUE","RED",IF($AF71="Not started","—",IF($AF71="Customer","GREEN",IF(OR($AF71="Lost",$AF71="Not a fit"),"CLOSED","AMBER")))) -> —
A72: 71 | B72: D | C72: =IF(OR(B72="A",B72="B"),"Yes","No") -> No | E72: Garle Reformas Integrales SL | F72: Garle Reformas Integrales | J72: S.L. | K72: Granollers | L72: Barcelona | M72: 55.6 | N72: Low | O72: L0–L1 | P72: name-inferred renovation — no CNAE | Q72: Sector-default only (Verifactu 2027 + quarterly filing cycle; no firm-specific signal in this extraction) | R72: S.L. form matches the reference tenant; no CNAE recovered — sector fit inferred from the trading name only. | AC72: https://www.einforma.com/informacion-empresa/garle-reformas-integrales | AD72: =COUNTA(V72:AA72) -> 0 | AF72: Not started | AO72: =IFERROR(INDEX(Playbook!$C$4:$C$17,MATCH($AF72,Playbook!$A$4:$A$17,0)),"") -> Read the row: tier, segment, trigger, reason we lose them. Check contact coverage; if 0, enrich before anything else. | AP72: =IFERROR(INDEX(Playbook!$D$4:$D$17,MATCH($AF72,Playbook!$A$4:$A$17,0)),"") -> — | AQ72: =IFERROR(INDEX(Playbook!$E$4:$E$17,MATCH($AF72,Playbook!$A$4:$A$17,0)),"") -> Row read and a contact channel exists | AR72: =IFERROR(INDEX(Playbook!$G$4:$G$17,MATCH($AF72,Playbook!$A$4:$A$17,0)),0) -> 0 | AS72: =IFERROR(INDEX('Pricing & Pilot'!$D$4:$D$6,MATCH($D72,'Pricing & Pilot'!$A$4:$A$6,0)),0) -> 0 | AT72: =AS72*AR72 -> 0 | AU72: =IF(AL72="","",TODAY()-AL72) | AV72: =IF(AM72="","",IF(AND(AM72<TODAY(),$AF72<>"Customer",$AF72<>"Lost",$AF72<>"Not a fit"),"OVERDUE","")) | AW72: =IF(AV72="OVERDUE","RED",IF($AF72="Not started","—",IF($AF72="Customer","GREEN",IF(OR($AF72="Lost",$AF72="Not a fit"),"CLOSED","AMBER")))) -> —
A73: 72 | B73: D | C73: =IF(OR(B73="A",B73="B"),"Yes","No") -> No | E73: HOUSFY REFORMAS SL | F73: HOUSFY REFORMAS | J73: S.L. | K73: Barcelona | L73: Barcelona | M73: 55.6 | N73: Low | O73: L0–L1 | P73: name-inferred renovation — no CNAE | Q73: Sector-default only (Verifactu 2027 + quarterly filing cycle; no firm-specific signal in this extraction) | R73: S.L. form matches the reference tenant; no CNAE recovered — sector fit inferred from the trading name only. | X73: https://www.houzz.es/profesionales/empresas-de-diseno-y-construccion/housfy-reformas-pfvwes-pf~2083973293 | AC73: https://www.houzz.es/profesionales/empresas-de-diseno-y-construccion/housfy-reformas-pfvwes-pf~2083973293 | AD73: =COUNTA(V73:AA73) -> 1 | AF73: Not started | AO73: =IFERROR(INDEX(Playbook!$C$4:$C$17,MATCH($AF73,Playbook!$A$4:$A$17,0)),"") -> Read the row: tier, segment, trigger, reason we lose them. Check contact coverage; if 0, enrich before anything else. | AP73: =IFERROR(INDEX(Playbook!$D$4:$D$17,MATCH($AF73,Playbook!$A$4:$A$17,0)),"") -> — | AQ73: =IFERROR(INDEX(Playbook!$E$4:$E$17,MATCH($AF73,Playbook!$A$4:$A$17,0)),"") -> Row read and a contact channel exists | AR73: =IFERROR(INDEX(Playbook!$G$4:$G$17,MATCH($AF73,Playbook!$A$4:$A$17,0)),0) -> 0 | AS73: =IFERROR(INDEX('Pricing & Pilot'!$D$4:$D$6,MATCH($D73,'Pricing & Pilot'!$A$4:$A$6,0)),0) -> 0 | AT73: =AS73*AR73 -> 0 | AU73: =IF(AL73="","",TODAY()-AL73) | AV73: =IF(AM73="","",IF(AND(AM73<TODAY(),$AF73<>"Customer",$AF73<>"Lost",$AF73<>"Not a fit"),"OVERDUE","")) | AW73: =IF(AV73="OVERDUE","RED",IF($AF73="Not started","—",IF($AF73="Customer","GREEN",IF(OR($AF73="Lost",$AF73="Not a fit"),"CLOSED","AMBER")))) -> —
A74: 73 | B74: D | C74: =IF(OR(B74="A",B74="B"),"Yes","No") -> No | E74: Innova Reformas Barcelona SL | F74: Innova Reformas | J74: S.L. | K74: Barcelona | L74: Barcelona | M74: 55.6 | N74: Low | O74: L0–L1 | P74: name-inferred renovation — no CNAE | Q74: Sector-default only (Verifactu 2027 + quarterly filing cycle; no firm-specific signal in this extraction) | R74: S.L. form matches the reference tenant; no CNAE recovered — sector fit inferred from the trading name only. | X74: https://www.innovareformes.es | AC74: https://barcelona.cool/categorias/reformas/innova-reformas-barcelona, https://www.innovareformes.es, https://www.reformasinnova.com/ | AD74: =COUNTA(V74:AA74) -> 1 | AF74: Not started | AO74: =IFERROR(INDEX(Playbook!$C$4:$C$17,MATCH($AF74,Playbook!$A$4:$A$17,0)),"") -> Read the row: tier, segment, trigger, reason we lose them. Check contact coverage; if 0, enrich before anything else. | AP74: =IFERROR(INDEX(Playbook!$D$4:$D$17,MATCH($AF74,Playbook!$A$4:$A$17,0)),"") -> — | AQ74: =IFERROR(INDEX(Playbook!$E$4:$E$17,MATCH($AF74,Playbook!$A$4:$A$17,0)),"") -> Row read and a contact channel exists | AR74: =IFERROR(INDEX(Playbook!$G$4:$G$17,MATCH($AF74,Playbook!$A$4:$A$17,0)),0) -> 0 | AS74: =IFERROR(INDEX('Pricing & Pilot'!$D$4:$D$6,MATCH($D74,'Pricing & Pilot'!$A$4:$A$6,0)),0) -> 0 | AT74: =AS74*AR74 -> 0 | AU74: =IF(AL74="","",TODAY()-AL74) | AV74: =IF(AM74="","",IF(AND(AM74<TODAY(),$AF74<>"Customer",$AF74<>"Lost",$AF74<>"Not a fit"),"OVERDUE","")) | AW74: =IF(AV74="OVERDUE","RED",IF($AF74="Not started","—",IF($AF74="Customer","GREEN",IF(OR($AF74="Lost",$AF74="Not a fit"),"CLOSED","AMBER")))) -> —
A75: 74 | B75: D | C75: =IF(OR(B75="A",B75="B"),"Yes","No") -> No | E75: JK Reformas Y Renovacion SL | F75: JK Reformas Y Renovacion | J75: S.L. | K75: Barcelona | L75: Barcelona | M75: 55.6 | N75: Low | O75: L0–L1 | P75: name-inferred renovation — no CNAE | Q75: Sector-default only (Verifactu 2027 + quarterly filing cycle; no firm-specific signal in this extraction) | R75: S.L. form matches the reference tenant; no CNAE recovered — sector fit inferred from the trading name only. | AC75: https://www.einforma.com/informacion-empresa/jk-reformas-renovacion | AD75: =COUNTA(V75:AA75) -> 0 | AF75: Not started | AO75: =IFERROR(INDEX(Playbook!$C$4:$C$17,MATCH($AF75,Playbook!$A$4:$A$17,0)),"") -> Read the row: tier, segment, trigger, reason we lose them. Check contact coverage; if 0, enrich before anything else. | AP75: =IFERROR(INDEX(Playbook!$D$4:$D$17,MATCH($AF75,Playbook!$A$4:$A$17,0)),"") -> — | AQ75: =IFERROR(INDEX(Playbook!$E$4:$E$17,MATCH($AF75,Playbook!$A$4:$A$17,0)),"") -> Row read and a contact channel exists | AR75: =IFERROR(INDEX(Playbook!$G$4:$G$17,MATCH($AF75,Playbook!$A$4:$A$17,0)),0) -> 0 | AS75: =IFERROR(INDEX('Pricing & Pilot'!$D$4:$D$6,MATCH($D75,'Pricing & Pilot'!$A$4:$A$6,0)),0) -> 0 | AT75: =AS75*AR75 -> 0 | AU75: =IF(AL75="","",TODAY()-AL75) | AV75: =IF(AM75="","",IF(AND(AM75<TODAY(),$AF75<>"Customer",$AF75<>"Lost",$AF75<>"Not a fit"),"OVERDUE","")) | AW75: =IF(AV75="OVERDUE","RED",IF($AF75="Not started","—",IF($AF75="Customer","GREEN",IF(OR($AF75="Lost",$AF75="Not a fit"),"CLOSED","AMBER")))) -> —
A76: 75 | B76: D | C76: =IF(OR(B76="A",B76="B"),"Yes","No") -> No | E76: L & C Reformas SL | F76: L & C Reformas | G76: B67385104 | J76: S.L. | K76: Mollet del Vallès | L76: Barcelona | M76: 55.6 | N76: Low | O76: L0–L1 | P76: name-inferred renovation — no CNAE | Q76: Sector-default only (Verifactu 2027 + quarterly filing cycle; no firm-specific signal in this extraction) | R76: S.L. form matches the reference tenant; no CNAE recovered — sector fit inferred from the trading name only. | AC76: https://www.einforma.com/informacion-empresa/lc-reformas-barcelona | AD76: =COUNTA(V76:AA76) -> 0 | AF76: Not started | AO76: =IFERROR(INDEX(Playbook!$C$4:$C$17,MATCH($AF76,Playbook!$A$4:$A$17,0)),"") -> Read the row: tier, segment, trigger, reason we lose them. Check contact coverage; if 0, enrich before anything else. | AP76: =IFERROR(INDEX(Playbook!$D$4:$D$17,MATCH($AF76,Playbook!$A$4:$A$17,0)),"") -> — | AQ76: =IFERROR(INDEX(Playbook!$E$4:$E$17,MATCH($AF76,Playbook!$A$4:$A$17,0)),"") -> Row read and a contact channel exists | AR76: =IFERROR(INDEX(Playbook!$G$4:$G$17,MATCH($AF76,Playbook!$A$4:$A$17,0)),0) -> 0 | AS76: =IFERROR(INDEX('Pricing & Pilot'!$D$4:$D$6,MATCH($D76,'Pricing & Pilot'!$A$4:$A$6,0)),0) -> 0 | AT76: =AS76*AR76 -> 0 | AU76: =IF(AL76="","",TODAY()-AL76) | AV76: =IF(AM76="","",IF(AND(AM76<TODAY(),$AF76<>"Customer",$AF76<>"Lost",$AF76<>"Not a fit"),"OVERDUE","")) | AW76: =IF(AV76="OVERDUE","RED",IF($AF76="Not started","—",IF($AF76="Customer","GREEN",IF(OR($AF76="Lost",$AF76="Not a fit"),"CLOSED","AMBER")))) -> —
A77: 76 | B77: D | C77: =IF(OR(B77="A",B77="B"),"Yes","No") -> No | E77: L A Reformas Llobregat S.L. | F77: L A Reformas Llobregat | G77: B64875248 | J77: S.L. | K77: Viladecans | L77: Barcelona | M77: 55.6 | N77: Low | O77: L0–L1 | P77: name-inferred renovation — no CNAE | Q77: Sector-default only (Verifactu 2027 + quarterly filing cycle; no firm-specific signal in this extraction) | R77: S.L. form matches the reference tenant; no CNAE recovered — sector fit inferred from the trading name only. | V77: 930075648 | X77: https://www.lareformasllobregat.com | AC77: https://empresite.eleconomista.es/LA-REFORMAS-LLOBREGAT.html, https://www.einforma.com/informacion-empresa/la-reformas-llobregat | AD77: =COUNTA(V77:AA77) -> 2 | AF77: Not started | AO77: =IFERROR(INDEX(Playbook!$C$4:$C$17,MATCH($AF77,Playbook!$A$4:$A$17,0)),"") -> Read the row: tier, segment, trigger, reason we lose them. Check contact coverage; if 0, enrich before anything else. | AP77: =IFERROR(INDEX(Playbook!$D$4:$D$17,MATCH($AF77,Playbook!$A$4:$A$17,0)),"") -> — | AQ77: =IFERROR(INDEX(Playbook!$E$4:$E$17,MATCH($AF77,Playbook!$A$4:$A$17,0)),"") -> Row read and a contact channel exists | AR77: =IFERROR(INDEX(Playbook!$G$4:$G$17,MATCH($AF77,Playbook!$A$4:$A$17,0)),0) -> 0 | AS77: =IFERROR(INDEX('Pricing & Pilot'!$D$4:$D$6,MATCH($D77,'Pricing & Pilot'!$A$4:$A$6,0)),0) -> 0 | AT77: =AS77*AR77 -> 0 | AU77: =IF(AL77="","",TODAY()-AL77) | AV77: =IF(AM77="","",IF(AND(AM77<TODAY(),$AF77<>"Customer",$AF77<>"Lost",$AF77<>"Not a fit"),"OVERDUE","")) | AW77: =IF(AV77="OVERDUE","RED",IF($AF77="Not started","—",IF($AF77="Customer","GREEN",IF(OR($AF77="Lost",$AF77="Not a fit"),"CLOSED","AMBER")))) -> —
A78: 77 | B78: D | C78: =IF(OR(B78="A",B78="B"),"Yes","No") -> No | E78: Lascol Reformas Y Servicios SL | F78: Lascol Reformas Y Servicios | J78: S.L. | K78: Badalona | L78: Barcelona | M78: 55.6 | N78: Low | O78: L0–L1 | P78: name-inferred renovation — no CNAE | Q78: Sector-default only (Verifactu 2027 + quarterly filing cycle; no firm-specific signal in this extraction) | R78: S.L. form matches the reference tenant; no CNAE recovered — sector fit inferred from the trading name only. | AC78: https://www.einforma.com/informacion-empresa/lascol-reformas-servicios | AD78: =COUNTA(V78:AA78) -> 0 | AF78: Not started | AO78: =IFERROR(INDEX(Playbook!$C$4:$C$17,MATCH($AF78,Playbook!$A$4:$A$17,0)),"") -> Read the row: tier, segment, trigger, reason we lose them. Check contact coverage; if 0, enrich before anything else. | AP78: =IFERROR(INDEX(Playbook!$D$4:$D$17,MATCH($AF78,Playbook!$A$4:$A$17,0)),"") -> — | AQ78: =IFERROR(INDEX(Playbook!$E$4:$E$17,MATCH($AF78,Playbook!$A$4:$A$17,0)),"") -> Row read and a contact channel exists | AR78: =IFERROR(INDEX(Playbook!$G$4:$G$17,MATCH($AF78,Playbook!$A$4:$A$17,0)),0) -> 0 | AS78: =IFERROR(INDEX('Pricing & Pilot'!$D$4:$D$6,MATCH($D78,'Pricing & Pilot'!$A$4:$A$6,0)),0) -> 0 | AT78: =AS78*AR78 -> 0 | AU78: =IF(AL78="","",TODAY()-AL78) | AV78: =IF(AM78="","",IF(AND(AM78<TODAY(),$AF78<>"Customer",$AF78<>"Lost",$AF78<>"Not a fit"),"OVERDUE","")) | AW78: =IF(AV78="OVERDUE","RED",IF($AF78="Not started","—",IF($AF78="Customer","GREEN",IF(OR($AF78="Lost",$AF78="Not a fit"),"CLOSED","AMBER")))) -> —
A79: 78 | B79: D | C79: =IF(OR(B79="A",B79="B"),"Yes","No") -> No | E79: LEBA REFORMAS S.L. | F79: Leba Reformas | G79: B67481994 | J79: S.L. | K79: Cornellà de Llobregat | L79: Barcelona | M79: 55.6 | N79: Low | O79: L0–L1 | P79: name-inferred renovation — no CNAE | Q79: Sector-default only (Verifactu 2027 + quarterly filing cycle; no firm-specific signal in this extraction) | R79: S.L. form matches the reference tenant; no CNAE recovered — sector fit inferred from the trading name only. | AC79: https://www.einforma.com/informacion-empresa/leba-reformas | AD79: =COUNTA(V79:AA79) -> 0 | AF79: Not started | AO79: =IFERROR(INDEX(Playbook!$C$4:$C$17,MATCH($AF79,Playbook!$A$4:$A$17,0)),"") -> Read the row: tier, segment, trigger, reason we lose them. Check contact coverage; if 0, enrich before anything else. | AP79: =IFERROR(INDEX(Playbook!$D$4:$D$17,MATCH($AF79,Playbook!$A$4:$A$17,0)),"") -> — | AQ79: =IFERROR(INDEX(Playbook!$E$4:$E$17,MATCH($AF79,Playbook!$A$4:$A$17,0)),"") -> Row read and a contact channel exists | AR79: =IFERROR(INDEX(Playbook!$G$4:$G$17,MATCH($AF79,Playbook!$A$4:$A$17,0)),0) -> 0 | AS79: =IFERROR(INDEX('Pricing & Pilot'!$D$4:$D$6,MATCH($D79,'Pricing & Pilot'!$A$4:$A$6,0)),0) -> 0 | AT79: =AS79*AR79 -> 0 | AU79: =IF(AL79="","",TODAY()-AL79) | AV79: =IF(AM79="","",IF(AND(AM79<TODAY(),$AF79<>"Customer",$AF79<>"Lost",$AF79<>"Not a fit"),"OVERDUE","")) | AW79: =IF(AV79="OVERDUE","RED",IF($AF79="Not started","—",IF($AF79="Customer","GREEN",IF(OR($AF79="Lost",$AF79="Not a fit"),"CLOSED","AMBER")))) -> —
A80: 79 | B80: D | C80: =IF(OR(B80="A",B80="B"),"Yes","No") -> No | E80: Medir Reformas SL | F80: Medir Reformas | J80: S.L. | K80: Badalona | L80: Barcelona | M80: 55.6 | N80: Low | O80: L0–L1 | P80: name-inferred renovation — no CNAE | Q80: Sector-default only (Verifactu 2027 + quarterly filing cycle; no firm-specific signal in this extraction) | R80: S.L. form matches the reference tenant; no CNAE recovered — sector fit inferred from the trading name only. | AC80: https://www.einforma.com/informacion-empresa/medir-reformas | AD80: =COUNTA(V80:AA80) -> 0 | AF80: Not started | AO80: =IFERROR(INDEX(Playbook!$C$4:$C$17,MATCH($AF80,Playbook!$A$4:$A$17,0)),"") -> Read the row: tier, segment, trigger, reason we lose them. Check contact coverage; if 0, enrich before anything else. | AP80: =IFERROR(INDEX(Playbook!$D$4:$D$17,MATCH($AF80,Playbook!$A$4:$A$17,0)),"") -> — | AQ80: =IFERROR(INDEX(Playbook!$E$4:$E$17,MATCH($AF80,Playbook!$A$4:$A$17,0)),"") -> Row read and a contact channel exists | AR80: =IFERROR(INDEX(Playbook!$G$4:$G$17,MATCH($AF80,Playbook!$A$4:$A$17,0)),0) -> 0 | AS80: =IFERROR(INDEX('Pricing & Pilot'!$D$4:$D$6,MATCH($D80,'Pricing & Pilot'!$A$4:$A$6,0)),0) -> 0 | AT80: =AS80*AR80 -> 0 | AU80: =IF(AL80="","",TODAY()-AL80) | AV80: =IF(AM80="","",IF(AND(AM80<TODAY(),$AF80<>"Customer",$AF80<>"Lost",$AF80<>"Not a fit"),"OVERDUE","")) | AW80: =IF(AV80="OVERDUE","RED",IF($AF80="Not started","—",IF($AF80="Customer","GREEN",IF(OR($AF80="Lost",$AF80="Not a fit"),"CLOSED","AMBER")))) -> —
A81: 80 | B81: D | C81: =IF(OR(B81="A",B81="B"),"Yes","No") -> No | E81: NAB Construcciones Y Reformas S.L. | F81: NAB Construcciones Y Reformas | G81: B56625247 | J81: S.L. | K81: Barcelona | L81: Barcelona | M81: 55.6 | N81: Low | O81: L0–L1 | P81: name-inferred renovation — no CNAE | Q81: Sector-default only (Verifactu 2027 + quarterly filing cycle; no firm-specific signal in this extraction) | R81: S.L. form matches the reference tenant; no CNAE recovered — sector fit inferred from the trading name only. | AC81: https://www.einforma.com/informacion-empresa/nab-construcciones-reformas | AD81: =COUNTA(V81:AA81) -> 0 | AF81: Not started | AO81: =IFERROR(INDEX(Playbook!$C$4:$C$17,MATCH($AF81,Playbook!$A$4:$A$17,0)),"") -> Read the row: tier, segment, trigger, reason we lose them. Check contact coverage; if 0, enrich before anything else. | AP81: =IFERROR(INDEX(Playbook!$D$4:$D$17,MATCH($AF81,Playbook!$A$4:$A$17,0)),"") -> — | AQ81: =IFERROR(INDEX(Playbook!$E$4:$E$17,MATCH($AF81,Playbook!$A$4:$A$17,0)),"") -> Row read and a contact channel exists | AR81: =IFERROR(INDEX(Playbook!$G$4:$G$17,MATCH($AF81,Playbook!$A$4:$A$17,0)),0) -> 0 | AS81: =IFERROR(INDEX('Pricing & Pilot'!$D$4:$D$6,MATCH($D81,'Pricing & Pilot'!$A$4:$A$6,0)),0) -> 0 | AT81: =AS81*AR81 -> 0 | AU81: =IF(AL81="","",TODAY()-AL81) | AV81: =IF(AM81="","",IF(AND(AM81<TODAY(),$AF81<>"Customer",$AF81<>"Lost",$AF81<>"Not a fit"),"OVERDUE","")) | AW81: =IF(AV81="OVERDUE","RED",IF($AF81="Not started","—",IF($AF81="Customer","GREEN",IF(OR($AF81="Lost",$AF81="Not a fit"),"CLOSED","AMBER")))) -> —
A82: 81 | B82: D | C82: =IF(OR(B82="A",B82="B"),"Yes","No") -> No | E82: Nova Reforma Barcelona SL | F82: Nova Reforma Barcelona | J82: S.L. | K82: Barcelona | L82: Barcelona | M82: 55.6 | N82: Low | O82: L0–L1 | P82: name-inferred renovation — no CNAE | Q82: Sector-default only; sole contact is a mobile-shaped number (QA: possible personal line, verify before outreach) | R82: S.L. form matches the reference tenant; no CNAE recovered — sector fit inferred from the trading name only. | V82: +34-690-757075 | X82: https://barcelonayreformas.com | AC82: https://barcelonayreformas.com/, https://empresite.eleconomista.es/NOVA-REFORMA-BARCELONA.html | AD82: =COUNTA(V82:AA82) -> 2 | AF82: Not started | AO82: =IFERROR(INDEX(Playbook!$C$4:$C$17,MATCH($AF82,Playbook!$A$4:$A$17,0)),"") -> Read the row: tier, segment, trigger, reason we lose them. Check contact coverage; if 0, enrich before anything else. | AP82: =IFERROR(INDEX(Playbook!$D$4:$D$17,MATCH($AF82,Playbook!$A$4:$A$17,0)),"") -> — | AQ82: =IFERROR(INDEX(Playbook!$E$4:$E$17,MATCH($AF82,Playbook!$A$4:$A$17,0)),"") -> Row read and a contact channel exists | AR82: =IFERROR(INDEX(Playbook!$G$4:$G$17,MATCH($AF82,Playbook!$A$4:$A$17,0)),0) -> 0 | AS82: =IFERROR(INDEX('Pricing & Pilot'!$D$4:$D$6,MATCH($D82,'Pricing & Pilot'!$A$4:$A$6,0)),0) -> 0 | AT82: =AS82*AR82 -> 0 | AU82: =IF(AL82="","",TODAY()-AL82) | AV82: =IF(AM82="","",IF(AND(AM82<TODAY(),$AF82<>"Customer",$AF82<>"Lost",$AF82<>"Not a fit"),"OVERDUE","")) | AW82: =IF(AV82="OVERDUE","RED",IF($AF82="Not started","—",IF($AF82="Customer","GREEN",IF(OR($AF82="Lost",$AF82="Not a fit"),"CLOSED","AMBER")))) -> —
A83: 82 | B83: D | C83: =IF(OR(B83="A",B83="B"),"Yes","No") -> No | E83: Obras Y Reformas Baix Llobregat S.L. | F83: Obras y Reformas Baix Llobregat | G83: B62547500 | J83: S.L. | K83: Castelldefels | L83: Barcelona | M83: 55.6 | N83: Low | O83: L0–L1 | P83: name-inferred renovation — no CNAE | Q83: Sector-default only (Verifactu 2027 + quarterly filing cycle; no firm-specific signal in this extraction) | R83: S.L. form matches the reference tenant; no CNAE recovered — sector fit inferred from the trading name only. | AC83: https://www.einforma.com/informacion-empresa/obras-reformas-baix-llobregat | AD83: =COUNTA(V83:AA83) -> 0 | AF83: Not started | AO83: =IFERROR(INDEX(Playbook!$C$4:$C$17,MATCH($AF83,Playbook!$A$4:$A$17,0)),"") -> Read the row: tier, segment, trigger, reason we lose them. Check contact coverage; if 0, enrich before anything else. | AP83: =IFERROR(INDEX(Playbook!$D$4:$D$17,MATCH($AF83,Playbook!$A$4:$A$17,0)),"") -> — | AQ83: =IFERROR(INDEX(Playbook!$E$4:$E$17,MATCH($AF83,Playbook!$A$4:$A$17,0)),"") -> Row read and a contact channel exists | AR83: =IFERROR(INDEX(Playbook!$G$4:$G$17,MATCH($AF83,Playbook!$A$4:$A$17,0)),0) -> 0 | AS83: =IFERROR(INDEX('Pricing & Pilot'!$D$4:$D$6,MATCH($D83,'Pricing & Pilot'!$A$4:$A$6,0)),0) -> 0 | AT83: =AS83*AR83 -> 0 | AU83: =IF(AL83="","",TODAY()-AL83) | AV83: =IF(AM83="","",IF(AND(AM83<TODAY(),$AF83<>"Customer",$AF83<>"Lost",$AF83<>"Not a fit"),"OVERDUE","")) | AW83: =IF(AV83="OVERDUE","RED",IF($AF83="Not started","—",IF($AF83="Customer","GREEN",IF(OR($AF83="Lost",$AF83="Not a fit"),"CLOSED","AMBER")))) -> —
A84: 83 | B84: D | C84: =IF(OR(B84="A",B84="B"),"Yes","No") -> No | E84: Obras Y Reformas Canovelles SL | F84: Obras Y Reformas Canovelles | J84: S.L. | K84: Granollers | L84: Barcelona | M84: 55.6 | N84: Low | O84: L0–L1 | P84: name-inferred renovation — no CNAE | Q84: Sector-default only (Verifactu 2027 + quarterly filing cycle; no firm-specific signal in this extraction) | R84: S.L. form matches the reference tenant; no CNAE recovered — sector fit inferred from the trading name only. | AC84: https://www.einforma.com/informacion-empresa/obras-reformas-canovelles | AD84: =COUNTA(V84:AA84) -> 0 | AF84: Not started | AO84: =IFERROR(INDEX(Playbook!$C$4:$C$17,MATCH($AF84,Playbook!$A$4:$A$17,0)),"") -> Read the row: tier, segment, trigger, reason we lose them. Check contact coverage; if 0, enrich before anything else. | AP84: =IFERROR(INDEX(Playbook!$D$4:$D$17,MATCH($AF84,Playbook!$A$4:$A$17,0)),"") -> — | AQ84: =IFERROR(INDEX(Playbook!$E$4:$E$17,MATCH($AF84,Playbook!$A$4:$A$17,0)),"") -> Row read and a contact channel exists | AR84: =IFERROR(INDEX(Playbook!$G$4:$G$17,MATCH($AF84,Playbook!$A$4:$A$17,0)),0) -> 0 | AS84: =IFERROR(INDEX('Pricing & Pilot'!$D$4:$D$6,MATCH($D84,'Pricing & Pilot'!$A$4:$A$6,0)),0) -> 0 | AT84: =AS84*AR84 -> 0 | AU84: =IF(AL84="","",TODAY()-AL84) | AV84: =IF(AM84="","",IF(AND(AM84<TODAY(),$AF84<>"Customer",$AF84<>"Lost",$AF84<>"Not a fit"),"OVERDUE","")) | AW84: =IF(AV84="OVERDUE","RED",IF($AF84="Not started","—",IF($AF84="Customer","GREEN",IF(OR($AF84="Lost",$AF84="Not a fit"),"CLOSED","AMBER")))) -> —
A85: 84 | B85: D | C85: =IF(OR(B85="A",B85="B"),"Yes","No") -> No | E85: Obras Y Servicios Barro S.L. | F85: Obras Y Servicios Barro | G85: B66924341 | J85: S.L. | K85: Castelldefels | L85: Barcelona | M85: 55.6 | N85: Low | O85: L0–L1 | P85: name-inferred general construction — no CNAE | Q85: Sector-default only (Verifactu 2027 + quarterly filing cycle; no firm-specific signal in this extraction) | R85: S.L. form matches the reference tenant; no CNAE recovered — sector fit inferred from the trading name only. | AC85: https://www.einforma.com/informacion-empresa/obras-servicios-barro | AD85: =COUNTA(V85:AA85) -> 0 | AF85: Not started | AO85: =IFERROR(INDEX(Playbook!$C$4:$C$17,MATCH($AF85,Playbook!$A$4:$A$17,0)),"") -> Read the row: tier, segment, trigger, reason we lose them. Check contact coverage; if 0, enrich before anything else. | AP85: =IFERROR(INDEX(Playbook!$D$4:$D$17,MATCH($AF85,Playbook!$A$4:$A$17,0)),"") -> — | AQ85: =IFERROR(INDEX(Playbook!$E$4:$E$17,MATCH($AF85,Playbook!$A$4:$A$17,0)),"") -> Row read and a contact channel exists | AR85: =IFERROR(INDEX(Playbook!$G$4:$G$17,MATCH($AF85,Playbook!$A$4:$A$17,0)),0) -> 0 | AS85: =IFERROR(INDEX('Pricing & Pilot'!$D$4:$D$6,MATCH($D85,'Pricing & Pilot'!$A$4:$A$6,0)),0) -> 0 | AT85: =AS85*AR85 -> 0 | AU85: =IF(AL85="","",TODAY()-AL85) | AV85: =IF(AM85="","",IF(AND(AM85<TODAY(),$AF85<>"Customer",$AF85<>"Lost",$AF85<>"Not a fit"),"OVERDUE","")) | AW85: =IF(AV85="OVERDUE","RED",IF($AF85="Not started","—",IF($AF85="Customer","GREEN",IF(OR($AF85="Lost",$AF85="Not a fit"),"CLOSED","AMBER")))) -> —
A86: 85 | B86: D | C86: =IF(OR(B86="A",B86="B"),"Yes","No") -> No | E86: Refinaments Sabadell SL | F86: Refinaments Sabadell | J86: S.L. | K86: Sabadell | L86: Barcelona | M86: 55.6 | N86: Low | O86: L0–L1 | P86: name-inferred renovation — no CNAE | Q86: Sector-default only (Verifactu 2027 + quarterly filing cycle; no firm-specific signal in this extraction) | R86: S.L. form matches the reference tenant; no CNAE recovered — sector fit inferred from the trading name only. | AC86: https://www.einforma.com/informacion-empresa/refinaments-sabadell | AD86: =COUNTA(V86:AA86) -> 0 | AF86: Not started | AO86: =IFERROR(INDEX(Playbook!$C$4:$C$17,MATCH($AF86,Playbook!$A$4:$A$17,0)),"") -> Read the row: tier, segment, trigger, reason we lose them. Check contact coverage; if 0, enrich before anything else. | AP86: =IFERROR(INDEX(Playbook!$D$4:$D$17,MATCH($AF86,Playbook!$A$4:$A$17,0)),"") -> — | AQ86: =IFERROR(INDEX(Playbook!$E$4:$E$17,MATCH($AF86,Playbook!$A$4:$A$17,0)),"") -> Row read and a contact channel exists | AR86: =IFERROR(INDEX(Playbook!$G$4:$G$17,MATCH($AF86,Playbook!$A$4:$A$17,0)),0) -> 0 | AS86: =IFERROR(INDEX('Pricing & Pilot'!$D$4:$D$6,MATCH($D86,'Pricing & Pilot'!$A$4:$A$6,0)),0) -> 0 | AT86: =AS86*AR86 -> 0 | AU86: =IF(AL86="","",TODAY()-AL86) | AV86: =IF(AM86="","",IF(AND(AM86<TODAY(),$AF86<>"Customer",$AF86<>"Lost",$AF86<>"Not a fit"),"OVERDUE","")) | AW86: =IF(AV86="OVERDUE","RED",IF($AF86="Not started","—",IF($AF86="Customer","GREEN",IF(OR($AF86="Lost",$AF86="Not a fit"),"CLOSED","AMBER")))) -> —
A87: 86 | B87: D | C87: =IF(OR(B87="A",B87="B"),"Yes","No") -> No | E87: Reforma Integral Granollers SL | F87: Reforma Integral Granollers | J87: S.L. | K87: Granollers | L87: Barcelona | M87: 55.6 | N87: Low | O87: L0–L1 | P87: name-inferred renovation — no CNAE | Q87: Sector-default only (Verifactu 2027 + quarterly filing cycle; no firm-specific signal in this extraction) | R87: S.L. form matches the reference tenant; no CNAE recovered — sector fit inferred from the trading name only. | AC87: https://www.einforma.com/informacion-empresa/reforma-integral-granollers | AD87: =COUNTA(V87:AA87) -> 0 | AF87: Not started | AO87: =IFERROR(INDEX(Playbook!$C$4:$C$17,MATCH($AF87,Playbook!$A$4:$A$17,0)),"") -> Read the row: tier, segment, trigger, reason we lose them. Check contact coverage; if 0, enrich before anything else. | AP87: =IFERROR(INDEX(Playbook!$D$4:$D$17,MATCH($AF87,Playbook!$A$4:$A$17,0)),"") -> — | AQ87: =IFERROR(INDEX(Playbook!$E$4:$E$17,MATCH($AF87,Playbook!$A$4:$A$17,0)),"") -> Row read and a contact channel exists | AR87: =IFERROR(INDEX(Playbook!$G$4:$G$17,MATCH($AF87,Playbook!$A$4:$A$17,0)),0) -> 0 | AS87: =IFERROR(INDEX('Pricing & Pilot'!$D$4:$D$6,MATCH($D87,'Pricing & Pilot'!$A$4:$A$6,0)),0) -> 0 | AT87: =AS87*AR87 -> 0 | AU87: =IF(AL87="","",TODAY()-AL87) | AV87: =IF(AM87="","",IF(AND(AM87<TODAY(),$AF87<>"Customer",$AF87<>"Lost",$AF87<>"Not a fit"),"OVERDUE","")) | AW87: =IF(AV87="OVERDUE","RED",IF($AF87="Not started","—",IF($AF87="Customer","GREEN",IF(OR($AF87="Lost",$AF87="Not a fit"),"CLOSED","AMBER")))) -> —
A88: 87 | B88: D | C88: =IF(OR(B88="A",B88="B"),"Yes","No") -> No | E88: Reformas 2011 Montcada SL | F88: Reformas 2011 Montcada | J88: S.L. | K88: Montcada i Reixac | L88: Barcelona | M88: 55.6 | N88: Low | O88: L0–L1 | P88: name-inferred renovation — no CNAE | Q88: Sector-default only (Verifactu 2027 + quarterly filing cycle; no firm-specific signal in this extraction) | R88: S.L. form matches the reference tenant; no CNAE recovered — sector fit inferred from the trading name only. | AC88: https://www.einforma.com/informacion-empresa/reformas-2011-montcada | AD88: =COUNTA(V88:AA88) -> 0 | AF88: Not started | AO88: =IFERROR(INDEX(Playbook!$C$4:$C$17,MATCH($AF88,Playbook!$A$4:$A$17,0)),"") -> Read the row: tier, segment, trigger, reason we lose them. Check contact coverage; if 0, enrich before anything else. | AP88: =IFERROR(INDEX(Playbook!$D$4:$D$17,MATCH($AF88,Playbook!$A$4:$A$17,0)),"") -> — | AQ88: =IFERROR(INDEX(Playbook!$E$4:$E$17,MATCH($AF88,Playbook!$A$4:$A$17,0)),"") -> Row read and a contact channel exists | AR88: =IFERROR(INDEX(Playbook!$G$4:$G$17,MATCH($AF88,Playbook!$A$4:$A$17,0)),0) -> 0 | AS88: =IFERROR(INDEX('Pricing & Pilot'!$D$4:$D$6,MATCH($D88,'Pricing & Pilot'!$A$4:$A$6,0)),0) -> 0 | AT88: =AS88*AR88 -> 0 | AU88: =IF(AL88="","",TODAY()-AL88) | AV88: =IF(AM88="","",IF(AND(AM88<TODAY(),$AF88<>"Customer",$AF88<>"Lost",$AF88<>"Not a fit"),"OVERDUE","")) | AW88: =IF(AV88="OVERDUE","RED",IF($AF88="Not started","—",IF($AF88="Customer","GREEN",IF(OR($AF88="Lost",$AF88="Not a fit"),"CLOSED","AMBER")))) -> —
A89: 88 | B89: D | C89: =IF(OR(B89="A",B89="B"),"Yes","No") -> No | E89: REFORMAS 2030 ETC S.L. | F89: Reformas 2030 ETC | G89: B75663948 | J89: S.L. | K89: Cornellà de Llobregat | L89: Barcelona | M89: 55.6 | N89: Low | O89: L0–L1 | P89: name-inferred renovation — no CNAE | Q89: Sector-default only (Verifactu 2027 + quarterly filing cycle; no firm-specific signal in this extraction) | R89: S.L. form matches the reference tenant; no CNAE recovered — sector fit inferred from the trading name only. | AC89: https://www.einforma.com/informacion-empresa/reformas-2030-etc | AD89: =COUNTA(V89:AA89) -> 0 | AF89: Not started | AO89: =IFERROR(INDEX(Playbook!$C$4:$C$17,MATCH($AF89,Playbook!$A$4:$A$17,0)),"") -> Read the row: tier, segment, trigger, reason we lose them. Check contact coverage; if 0, enrich before anything else. | AP89: =IFERROR(INDEX(Playbook!$D$4:$D$17,MATCH($AF89,Playbook!$A$4:$A$17,0)),"") -> — | AQ89: =IFERROR(INDEX(Playbook!$E$4:$E$17,MATCH($AF89,Playbook!$A$4:$A$17,0)),"") -> Row read and a contact channel exists | AR89: =IFERROR(INDEX(Playbook!$G$4:$G$17,MATCH($AF89,Playbook!$A$4:$A$17,0)),0) -> 0 | AS89: =IFERROR(INDEX('Pricing & Pilot'!$D$4:$D$6,MATCH($D89,'Pricing & Pilot'!$A$4:$A$6,0)),0) -> 0 | AT89: =AS89*AR89 -> 0 | AU89: =IF(AL89="","",TODAY()-AL89) | AV89: =IF(AM89="","",IF(AND(AM89<TODAY(),$AF89<>"Customer",$AF89<>"Lost",$AF89<>"Not a fit"),"OVERDUE","")) | AW89: =IF(AV89="OVERDUE","RED",IF($AF89="Not started","—",IF($AF89="Customer","GREEN",IF(OR($AF89="Lost",$AF89="Not a fit"),"CLOSED","AMBER")))) -> —
A90: 89 | B90: D | C90: =IF(OR(B90="A",B90="B"),"Yes","No") -> No | E90: Reformas Alta Calidad Bcn SL | F90: Reformas Alta Calidad Bcn | J90: S.L. | K90: Barcelona | L90: Barcelona | M90: 55.6 | N90: Low | O90: L0–L1 | P90: name-inferred renovation — no CNAE | Q90: Sector-default only (Verifactu 2027 + quarterly filing cycle; no firm-specific signal in this extraction) | R90: S.L. form matches the reference tenant; no CNAE recovered — sector fit inferred from the trading name only. | AC90: https://www.einforma.com/informacion-empresa/reformas-alta-calidad-bcn | AD90: =COUNTA(V90:AA90) -> 0 | AF90: Not started | AO90: =IFERROR(INDEX(Playbook!$C$4:$C$17,MATCH($AF90,Playbook!$A$4:$A$17,0)),"") -> Read the row: tier, segment, trigger, reason we lose them. Check contact coverage; if 0, enrich before anything else. | AP90: =IFERROR(INDEX(Playbook!$D$4:$D$17,MATCH($AF90,Playbook!$A$4:$A$17,0)),"") -> — | AQ90: =IFERROR(INDEX(Playbook!$E$4:$E$17,MATCH($AF90,Playbook!$A$4:$A$17,0)),"") -> Row read and a contact channel exists | AR90: =IFERROR(INDEX(Playbook!$G$4:$G$17,MATCH($AF90,Playbook!$A$4:$A$17,0)),0) -> 0 | AS90: =IFERROR(INDEX('Pricing & Pilot'!$D$4:$D$6,MATCH($D90,'Pricing & Pilot'!$A$4:$A$6,0)),0) -> 0 | AT90: =AS90*AR90 -> 0 | AU90: =IF(AL90="","",TODAY()-AL90) | AV90: =IF(AM90="","",IF(AND(AM90<TODAY(),$AF90<>"Customer",$AF90<>"Lost",$AF90<>"Not a fit"),"OVERDUE","")) | AW90: =IF(AV90="OVERDUE","RED",IF($AF90="Not started","—",IF($AF90="Customer","GREEN",IF(OR($AF90="Lost",$AF90="Not a fit"),"CLOSED","AMBER")))) -> —
A91: 90 | B91: D | C91: =IF(OR(B91="A",B91="B"),"Yes","No") -> No | E91: Reformas Badalona 2000 SL | F91: Reformas Badalona 2000 | J91: S.L. | K91: Badalona | L91: Barcelona | M91: 55.6 | N91: Low | O91: L0–L1 | P91: name-inferred renovation — no CNAE | Q91: Sector-default only (Verifactu 2027 + quarterly filing cycle; no firm-specific signal in this extraction) | R91: S.L. form matches the reference tenant; no CNAE recovered — sector fit inferred from the trading name only. | AC91: https://www.einforma.com/informacion-empresa/reformas-badalona-2000 | AD91: =COUNTA(V91:AA91) -> 0 | AF91: Not started | AO91: =IFERROR(INDEX(Playbook!$C$4:$C$17,MATCH($AF91,Playbook!$A$4:$A$17,0)),"") -> Read the row: tier, segment, trigger, reason we lose them. Check contact coverage; if 0, enrich before anything else. | AP91: =IFERROR(INDEX(Playbook!$D$4:$D$17,MATCH($AF91,Playbook!$A$4:$A$17,0)),"") -> — | AQ91: =IFERROR(INDEX(Playbook!$E$4:$E$17,MATCH($AF91,Playbook!$A$4:$A$17,0)),"") -> Row read and a contact channel exists | AR91: =IFERROR(INDEX(Playbook!$G$4:$G$17,MATCH($AF91,Playbook!$A$4:$A$17,0)),0) -> 0 | AS91: =IFERROR(INDEX('Pricing & Pilot'!$D$4:$D$6,MATCH($D91,'Pricing & Pilot'!$A$4:$A$6,0)),0) -> 0 | AT91: =AS91*AR91 -> 0 | AU91: =IF(AL91="","",TODAY()-AL91) | AV91: =IF(AM91="","",IF(AND(AM91<TODAY(),$AF91<>"Customer",$AF91<>"Lost",$AF91<>"Not a fit"),"OVERDUE","")) | AW91: =IF(AV91="OVERDUE","RED",IF($AF91="Not started","—",IF($AF91="Customer","GREEN",IF(OR($AF91="Lost",$AF91="Not a fit"),"CLOSED","AMBER")))) -> —
A92: 91 | B92: D | C92: =IF(OR(B92="A",B92="B"),"Yes","No") -> No | E92: Reformas Barcelona Grupo Técnico SL | F92: Grupo Técnico | G92: B66772625 | J92: S.L. | K92: Barcelona | L92: Barcelona | M92: 55.6 | N92: Low | O92: L0–L1 | P92: name-inferred renovation — no CNAE | Q92: Sector-default only; contact email is consumer webmail (QA gray-zone, verify before outreach) | R92: S.L. form matches the reference tenant; no CNAE recovered — sector fit inferred from the trading name only. | V92: 931426082 | W92: grupotecnico82@gmail.com | X92: http://www.grupotecnicobarcelona.com | AC92: https://empresite.eleconomista.es/REFORMAS-BARCELONA-GRUPOTECNICO.html, https://infonif.economia3.com/ficha-empresa/reformas-barcelona-grupotecnico-sl, https://www.houzz.es/profesionales/renovacion-de-cocinas-y-banos/reformas-barcelona-grupo-tecnico-s-l-pfvwes-pf~691744371 | AD92: =COUNTA(V92:AA92) -> 3 | AF92: Not started | AO92: =IFERROR(INDEX(Playbook!$C$4:$C$17,MATCH($AF92,Playbook!$A$4:$A$17,0)),"") -> Read the row: tier, segment, trigger, reason we lose them. Check contact coverage; if 0, enrich before anything else. | AP92: =IFERROR(INDEX(Playbook!$D$4:$D$17,MATCH($AF92,Playbook!$A$4:$A$17,0)),"") -> — | AQ92: =IFERROR(INDEX(Playbook!$E$4:$E$17,MATCH($AF92,Playbook!$A$4:$A$17,0)),"") -> Row read and a contact channel exists | AR92: =IFERROR(INDEX(Playbook!$G$4:$G$17,MATCH($AF92,Playbook!$A$4:$A$17,0)),0) -> 0 | AS92: =IFERROR(INDEX('Pricing & Pilot'!$D$4:$D$6,MATCH($D92,'Pricing & Pilot'!$A$4:$A$6,0)),0) -> 0 | AT92: =AS92*AR92 -> 0 | AU92: =IF(AL92="","",TODAY()-AL92) | AV92: =IF(AM92="","",IF(AND(AM92<TODAY(),$AF92<>"Customer",$AF92<>"Lost",$AF92<>"Not a fit"),"OVERDUE","")) | AW92: =IF(AV92="OVERDUE","RED",IF($AF92="Not started","—",IF($AF92="Customer","GREEN",IF(OR($AF92="Lost",$AF92="Not a fit"),"CLOSED","AMBER")))) -> —
A93: 92 | B93: D | C93: =IF(OR(B93="A",B93="B"),"Yes","No") -> No | E93: Reformas Barcelona Rubio SL | F93: Reformas Barcelona Rubio | G93: B66684077 | J93: S.L. | K93: Barcelona | L93: Barcelona | M93: 55.6 | N93: Low | O93: L0–L1 | P93: name-inferred renovation — no CNAE | Q93: Sector-default only (Verifactu 2027 + quarterly filing cycle; no firm-specific signal in this extraction) | R93: S.L. form matches the reference tenant; no CNAE recovered — sector fit inferred from the trading name only. | AC93: https://infonif.economia3.com/ficha-empresa/reformas-barcelona-rubio-sl, https://www.einforma.com/informacion-empresa/reformas-barcelona-rubio | AD93: =COUNTA(V93:AA93) -> 0 | AF93: Not started | AO93: =IFERROR(INDEX(Playbook!$C$4:$C$17,MATCH($AF93,Playbook!$A$4:$A$17,0)),"") -> Read the row: tier, segment, trigger, reason we lose them. Check contact coverage; if 0, enrich before anything else. | AP93: =IFERROR(INDEX(Playbook!$D$4:$D$17,MATCH($AF93,Playbook!$A$4:$A$17,0)),"") -> — | AQ93: =IFERROR(INDEX(Playbook!$E$4:$E$17,MATCH($AF93,Playbook!$A$4:$A$17,0)),"") -> Row read and a contact channel exists | AR93: =IFERROR(INDEX(Playbook!$G$4:$G$17,MATCH($AF93,Playbook!$A$4:$A$17,0)),0) -> 0 | AS93: =IFERROR(INDEX('Pricing & Pilot'!$D$4:$D$6,MATCH($D93,'Pricing & Pilot'!$A$4:$A$6,0)),0) -> 0 | AT93: =AS93*AR93 -> 0 | AU93: =IF(AL93="","",TODAY()-AL93) | AV93: =IF(AM93="","",IF(AND(AM93<TODAY(),$AF93<>"Customer",$AF93<>"Lost",$AF93<>"Not a fit"),"OVERDUE","")) | AW93: =IF(AV93="OVERDUE","RED",IF($AF93="Not started","—",IF($AF93="Customer","GREEN",IF(OR($AF93="Lost",$AF93="Not a fit"),"CLOSED","AMBER")))) -> —
A94: 93 | B94: D | C94: =IF(OR(B94="A",B94="B"),"Yes","No") -> No | E94: Reformas Carrera S.L. | F94: Reformas Carrera | J94: S.L. | K94: Gavà | L94: Barcelona | M94: 55.6 | N94: Low | O94: L0–L1 | P94: name-inferred renovation — no CNAE | Q94: Sector-default only (Verifactu 2027 + quarterly filing cycle; no firm-specific signal in this extraction) | R94: S.L. form matches the reference tenant; no CNAE recovered — sector fit inferred from the trading name only. | V94: 936620042 | AC94: https://www.einforma.com/informacion-empresa/reformas-carrera | AD94: =COUNTA(V94:AA94) -> 1 | AF94: Not started | AO94: =IFERROR(INDEX(Playbook!$C$4:$C$17,MATCH($AF94,Playbook!$A$4:$A$17,0)),"") -> Read the row: tier, segment, trigger, reason we lose them. Check contact coverage; if 0, enrich before anything else. | AP94: =IFERROR(INDEX(Playbook!$D$4:$D$17,MATCH($AF94,Playbook!$A$4:$A$17,0)),"") -> — | AQ94: =IFERROR(INDEX(Playbook!$E$4:$E$17,MATCH($AF94,Playbook!$A$4:$A$17,0)),"") -> Row read and a contact channel exists | AR94: =IFERROR(INDEX(Playbook!$G$4:$G$17,MATCH($AF94,Playbook!$A$4:$A$17,0)),0) -> 0 | AS94: =IFERROR(INDEX('Pricing & Pilot'!$D$4:$D$6,MATCH($D94,'Pricing & Pilot'!$A$4:$A$6,0)),0) -> 0 | AT94: =AS94*AR94 -> 0 | AU94: =IF(AL94="","",TODAY()-AL94) | AV94: =IF(AM94="","",IF(AND(AM94<TODAY(),$AF94<>"Customer",$AF94<>"Lost",$AF94<>"Not a fit"),"OVERDUE","")) | AW94: =IF(AV94="OVERDUE","RED",IF($AF94="Not started","—",IF($AF94="Customer","GREEN",IF(OR($AF94="Lost",$AF94="Not a fit"),"CLOSED","AMBER")))) -> —
A95: 94 | B95: D | C95: =IF(OR(B95="A",B95="B"),"Yes","No") -> No | E95: Reformas Casa Luz SL | F95: Reformas Casa Luz | G95: B02906188 | J95: S.L. | K95: Sabadell | L95: Barcelona | M95: 55.6 | N95: Low | O95: L0–L1 | P95: name-inferred renovation — no CNAE | Q95: Sector-default only (Verifactu 2027 + quarterly filing cycle; no firm-specific signal in this extraction) | R95: S.L. form matches the reference tenant; no CNAE recovered — sector fit inferred from the trading name only. | AC95: https://www.einforma.com/informacion-empresa/reformas-casa-luz | AD95: =COUNTA(V95:AA95) -> 0 | AF95: Not started | AO95: =IFERROR(INDEX(Playbook!$C$4:$C$17,MATCH($AF95,Playbook!$A$4:$A$17,0)),"") -> Read the row: tier, segment, trigger, reason we lose them. Check contact coverage; if 0, enrich before anything else. | AP95: =IFERROR(INDEX(Playbook!$D$4:$D$17,MATCH($AF95,Playbook!$A$4:$A$17,0)),"") -> — | AQ95: =IFERROR(INDEX(Playbook!$E$4:$E$17,MATCH($AF95,Playbook!$A$4:$A$17,0)),"") -> Row read and a contact channel exists | AR95: =IFERROR(INDEX(Playbook!$G$4:$G$17,MATCH($AF95,Playbook!$A$4:$A$17,0)),0) -> 0 | AS95: =IFERROR(INDEX('Pricing & Pilot'!$D$4:$D$6,MATCH($D95,'Pricing & Pilot'!$A$4:$A$6,0)),0) -> 0 | AT95: =AS95*AR95 -> 0 | AU95: =IF(AL95="","",TODAY()-AL95) | AV95: =IF(AM95="","",IF(AND(AM95<TODAY(),$AF95<>"Customer",$AF95<>"Lost",$AF95<>"Not a fit"),"OVERDUE","")) | AW95: =IF(AV95="OVERDUE","RED",IF($AF95="Not started","—",IF($AF95="Customer","GREEN",IF(OR($AF95="Lost",$AF95="Not a fit"),"CLOSED","AMBER")))) -> —
A96: 95 | B96: D | C96: =IF(OR(B96="A",B96="B"),"Yes","No") -> No | E96: Reformas Dimari SL | F96: Reformas Dimari | J96: S.L. | K96: Barcelona | L96: Barcelona | M96: 55.6 | N96: Low | O96: L0–L1 | P96: name-inferred renovation — no CNAE | Q96: Sector-default only (Verifactu 2027 + quarterly filing cycle; no firm-specific signal in this extraction) | R96: S.L. form matches the reference tenant; no CNAE recovered — sector fit inferred from the trading name only. | X96: https://reformasdimari.com | AC96: https://reformasdimari.com/, https://www.instagram.com/reformasdimari/ | AD96: =COUNTA(V96:AA96) -> 1 | AF96: Not started | AO96: =IFERROR(INDEX(Playbook!$C$4:$C$17,MATCH($AF96,Playbook!$A$4:$A$17,0)),"") -> Read the row: tier, segment, trigger, reason we lose them. Check contact coverage; if 0, enrich before anything else. | AP96: =IFERROR(INDEX(Playbook!$D$4:$D$17,MATCH($AF96,Playbook!$A$4:$A$17,0)),"") -> — | AQ96: =IFERROR(INDEX(Playbook!$E$4:$E$17,MATCH($AF96,Playbook!$A$4:$A$17,0)),"") -> Row read and a contact channel exists | AR96: =IFERROR(INDEX(Playbook!$G$4:$G$17,MATCH($AF96,Playbook!$A$4:$A$17,0)),0) -> 0 | AS96: =IFERROR(INDEX('Pricing & Pilot'!$D$4:$D$6,MATCH($D96,'Pricing & Pilot'!$A$4:$A$6,0)),0) -> 0 | AT96: =AS96*AR96 -> 0 | AU96: =IF(AL96="","",TODAY()-AL96) | AV96: =IF(AM96="","",IF(AND(AM96<TODAY(),$AF96<>"Customer",$AF96<>"Lost",$AF96<>"Not a fit"),"OVERDUE","")) | AW96: =IF(AV96="OVERDUE","RED",IF($AF96="Not started","—",IF($AF96="Customer","GREEN",IF(OR($AF96="Lost",$AF96="Not a fit"),"CLOSED","AMBER")))) -> —
A97: 96 | B97: D | C97: =IF(OR(B97="A",B97="B"),"Yes","No") -> No | E97: Reformas DSQ SL | F97: Reformas DSQ | J97: S.L. | K97: Barcelona | L97: Barcelona | M97: 55.6 | N97: Low | O97: L0–L1 | P97: name-inferred renovation — no CNAE | Q97: Sector-default only (Verifactu 2027 + quarterly filing cycle; no firm-specific signal in this extraction) | R97: S.L. form matches the reference tenant; no CNAE recovered — sector fit inferred from the trading name only. | AC97: https://www.einforma.com/informacion-empresa/reformas-dsq-barcelona | AD97: =COUNTA(V97:AA97) -> 0 | AF97: Not started | AO97: =IFERROR(INDEX(Playbook!$C$4:$C$17,MATCH($AF97,Playbook!$A$4:$A$17,0)),"") -> Read the row: tier, segment, trigger, reason we lose them. Check contact coverage; if 0, enrich before anything else. | AP97: =IFERROR(INDEX(Playbook!$D$4:$D$17,MATCH($AF97,Playbook!$A$4:$A$17,0)),"") -> — | AQ97: =IFERROR(INDEX(Playbook!$E$4:$E$17,MATCH($AF97,Playbook!$A$4:$A$17,0)),"") -> Row read and a contact channel exists | AR97: =IFERROR(INDEX(Playbook!$G$4:$G$17,MATCH($AF97,Playbook!$A$4:$A$17,0)),0) -> 0 | AS97: =IFERROR(INDEX('Pricing & Pilot'!$D$4:$D$6,MATCH($D97,'Pricing & Pilot'!$A$4:$A$6,0)),0) -> 0 | AT97: =AS97*AR97 -> 0 | AU97: =IF(AL97="","",TODAY()-AL97) | AV97: =IF(AM97="","",IF(AND(AM97<TODAY(),$AF97<>"Customer",$AF97<>"Lost",$AF97<>"Not a fit"),"OVERDUE","")) | AW97: =IF(AV97="OVERDUE","RED",IF($AF97="Not started","—",IF($AF97="Customer","GREEN",IF(OR($AF97="Lost",$AF97="Not a fit"),"CLOSED","AMBER")))) -> —
A98: 97 | B98: D | C98: =IF(OR(B98="A",B98="B"),"Yes","No") -> No | E98: Reformas Grig Barcelona SL | F98: GRIG | G98: B70653902 | J98: S.L. | K98: Barcelona | L98: Barcelona | M98: 55.6 | N98: Low | O98: L0–L1 | P98: name-inferred renovation — no CNAE | Q98: Sector-default only (Verifactu 2027 + quarterly filing cycle; no firm-specific signal in this extraction) | R98: S.L. form matches the reference tenant; no CNAE recovered — sector fit inferred from the trading name only. | V98: +34-931792019 | X98: https://grig.es | AC98: https://grig.es/, https://www.einforma.com/informacion-empresa/reformas-grig-barcelona | AD98: =COUNTA(V98:AA98) -> 2 | AF98: Not started | AO98: =IFERROR(INDEX(Playbook!$C$4:$C$17,MATCH($AF98,Playbook!$A$4:$A$17,0)),"") -> Read the row: tier, segment, trigger, reason we lose them. Check contact coverage; if 0, enrich before anything else. | AP98: =IFERROR(INDEX(Playbook!$D$4:$D$17,MATCH($AF98,Playbook!$A$4:$A$17,0)),"") -> — | AQ98: =IFERROR(INDEX(Playbook!$E$4:$E$17,MATCH($AF98,Playbook!$A$4:$A$17,0)),"") -> Row read and a contact channel exists | AR98: =IFERROR(INDEX(Playbook!$G$4:$G$17,MATCH($AF98,Playbook!$A$4:$A$17,0)),0) -> 0 | AS98: =IFERROR(INDEX('Pricing & Pilot'!$D$4:$D$6,MATCH($D98,'Pricing & Pilot'!$A$4:$A$6,0)),0) -> 0 | AT98: =AS98*AR98 -> 0 | AU98: =IF(AL98="","",TODAY()-AL98) | AV98: =IF(AM98="","",IF(AND(AM98<TODAY(),$AF98<>"Customer",$AF98<>"Lost",$AF98<>"Not a fit"),"OVERDUE","")) | AW98: =IF(AV98="OVERDUE","RED",IF($AF98="Not started","—",IF($AF98="Customer","GREEN",IF(OR($AF98="Lost",$AF98="Not a fit"),"CLOSED","AMBER")))) -> —
A99: 98 | B99: D | C99: =IF(OR(B99="A",B99="B"),"Yes","No") -> No | E99: Reformas Integrales F&R SL | F99: Reformas Integrales F&R | J99: S.L. | K99: Barcelona | L99: Barcelona | M99: 55.6 | N99: Low | O99: L0–L1 | P99: name-inferred renovation — no CNAE | Q99: Sector-default only (Verifactu 2027 + quarterly filing cycle; no firm-specific signal in this extraction) | R99: S.L. form matches the reference tenant; no CNAE recovered — sector fit inferred from the trading name only. | AC99: https://www.einforma.com/informacion-empresa/reformas-integrales-fr | AD99: =COUNTA(V99:AA99) -> 0 | AF99: Not started | AO99: =IFERROR(INDEX(Playbook!$C$4:$C$17,MATCH($AF99,Playbook!$A$4:$A$17,0)),"") -> Read the row: tier, segment, trigger, reason we lose them. Check contact coverage; if 0, enrich before anything else. | AP99: =IFERROR(INDEX(Playbook!$D$4:$D$17,MATCH($AF99,Playbook!$A$4:$A$17,0)),"") -> — | AQ99: =IFERROR(INDEX(Playbook!$E$4:$E$17,MATCH($AF99,Playbook!$A$4:$A$17,0)),"") -> Row read and a contact channel exists | AR99: =IFERROR(INDEX(Playbook!$G$4:$G$17,MATCH($AF99,Playbook!$A$4:$A$17,0)),0) -> 0 | AS99: =IFERROR(INDEX('Pricing & Pilot'!$D$4:$D$6,MATCH($D99,'Pricing & Pilot'!$A$4:$A$6,0)),0) -> 0 | AT99: =AS99*AR99 -> 0 | AU99: =IF(AL99="","",TODAY()-AL99) | AV99: =IF(AM99="","",IF(AND(AM99<TODAY(),$AF99<>"Customer",$AF99<>"Lost",$AF99<>"Not a fit"),"OVERDUE","")) | AW99: =IF(AV99="OVERDUE","RED",IF($AF99="Not started","—",IF($AF99="Customer","GREEN",IF(OR($AF99="Lost",$AF99="Not a fit"),"CLOSED","AMBER")))) -> —
A100: 99 | B100: D | C100: =IF(OR(B100="A",B100="B"),"Yes","No") -> No | E100: Reformas Integrales y Servicios RDR SL | F100: Reformas Integrales y Servicios RDR | J100: S.L. | K100: Barcelona | L100: Barcelona | M100: 55.6 | N100: Low | O100: L0–L1 | P100: name-inferred renovation — no CNAE | Q100: Sector-default only (Verifactu 2027 + quarterly filing cycle; no firm-specific signal in this extraction) | R100: S.L. form matches the reference tenant; no CNAE recovered — sector fit inferred from the trading name only. | AC100: https://www.axesor.es/Informes-Empresas/9165830/REFORMAS_INTEGRALES_Y_SERVICIOS_RDR_SL.html | AD100: =COUNTA(V100:AA100) -> 0 | AF100: Not started | AO100: =IFERROR(INDEX(Playbook!$C$4:$C$17,MATCH($AF100,Playbook!$A$4:$A$17,0)),"") -> Read the row: tier, segment, trigger, reason we lose them. Check contact coverage; if 0, enrich before anything else. | AP100: =IFERROR(INDEX(Playbook!$D$4:$D$17,MATCH($AF100,Playbook!$A$4:$A$17,0)),"") -> — | AQ100: =IFERROR(INDEX(Playbook!$E$4:$E$17,MATCH($AF100,Playbook!$A$4:$A$17,0)),"") -> Row read and a contact channel exists | AR100: =IFERROR(INDEX(Playbook!$G$4:$G$17,MATCH($AF100,Playbook!$A$4:$A$17,0)),0) -> 0 | AS100: =IFERROR(INDEX('Pricing & Pilot'!$D$4:$D$6,MATCH($D100,'Pricing & Pilot'!$A$4:$A$6,0)),0) -> 0 | AT100: =AS100*AR100 -> 0 | AU100: =IF(AL100="","",TODAY()-AL100) | AV100: =IF(AM100="","",IF(AND(AM100<TODAY(),$AF100<>"Customer",$AF100<>"Lost",$AF100<>"Not a fit"),"OVERDUE","")) | AW100: =IF(AV100="OVERDUE","RED",IF($AF100="Not started","—",IF($AF100="Customer","GREEN",IF(OR($AF100="Lost",$AF100="Not a fit"),"CLOSED","AMBER")))) -> —
...

Sheet Playbook
A1: Playbook — the selling process, stage by stage
A2: Pipeline's Next action, Script to use, Exit criterion and Probability are looked up from this table by Stage. Probabilities (blue) are assumptions — change them here, never in Pipeline.
A3: Stage | B3: Objective | C3: What to do (Next action) | D3: Script / asset to use | E3: Exit criterion — move on only when | F3: Typical duration | G3: Probability | H3: Next stage | I3: MEDDPICC check
A4: Not started | B4: Nothing done yet | C4: Read the row: tier, segment, trigger, reason we lose them. Check contact coverage; if 0, enrich before anything else. | D4: — | E4: Row read and a contact channel exists | F4: — | G4: 0 | H4: Research | I4: —
A5: Research | B5: Know one verifiable thing about their business | C5: Find a live site or permit, the owner's name if the FIRM publishes it, and which trigger applies. Fill Contact person, Preferred language and Trigger observed. | D5: Triggers sheet | E5: One verifiable, specific fact about their current work recorded in Notes | F5: 1 day | G5: 0.02 | H5: Cold call | I5: Identify Pain — which opener fits
A6: Cold call | B6: Earn 30 minutes on site | C6: Call the published number. Open with the trigger's one-sentence opener. Ask for the person who prepares the quarterly close. Aim for a site visit, not a demo. | D6: Scripts · 90-second pitch | E6: Prospect recognises the named pain as their own, or a visit is booked | F6: 1–3 attempts over 5 days | G6: 0.05 | H6: First-touch email | I6: Identify Pain · Economic Buyer named
A7: First-touch email | B7: Same ask, in writing, in their language | C7: Send the first-touch email (ES or CA) with every merge field verified. Log it. Set Next action due = +4 days. | D7: Scripts · First-touch email | E7: Sent with no square-bracketed field left, logged | F7: same day | G7: 0.05 | H7: Follow-up 1 | I7: —
A8: Follow-up 1 | B8: Second angle — the 2027 invoicing obligation | C8: Send Follow-up A. Try one more call at a different hour. | D8: Scripts · Follow-up A | E8: Reply, call taken, or 2 touches logged | F8: +4 days | G8: 0.08 | H8: Follow-up 2 | I8: Identify Pain
A9: Follow-up 2 | B9: Third angle — the quarter and the gestoría | C9: Send Follow-up B. If no reply after this, set Stage to Lost with reason 'no response' and revisit in 90 days. | D9: Scripts · Follow-up B | E9: Reply or meeting, else Lost | F9: +5 days | G9: 0.08 | H9: Meeting booked | I9: Champion — is there an admin person?
A10: Meeting booked | B10: A date on site with the owner(s) | C10: Confirm date, place and who attends — both owners if operations and administration are split. Prepare the three qualifying questions. | D10: Playbook · MEDDPICC checklist | E10: Date, place and attendees confirmed in writing | F10: ≤ 7 days out | G10: 0.15 | H10: Meeting held | I10: Economic Buyer (both) · Decision Process
A11: Meeting held | B11: Qualify — hard gates answered | C11: Run the qualifying questions: revenue mix, incumbent ledger, public-work exposure, bank, legal form, both Economic Buyers. Ask for one closed job's papers for the demo. | D11: Objections sheet · Leave-behind | E11: Hard-gate checklist answered; one closed job's documents obtained | F11: 1 meeting | G11: 0.25 | H11: Demo on their data | I11: Metrics · Decision Criteria · Competition
A12: Demo on their data | B12: Their name on a real document | C12: Build a quotation, contract and invoice bearing their firm's name, NIF and a sample of their catalogue. Costs 8–16 engineering hours today (07 §4) — book it, do not improvise. | D12: Pricing & Pilot sheet | E12: Both Economic Buyers have seen a document with their own name and figures | F12: 1–2 weeks incl. build | G12: 0.4 | H12: Pilot proposed | I12: Metrics — their numbers, not ours
A13: Pilot proposed | B13: Term sheet on the table | C13: Present the 90-day pilot: €900, three metrics on their numbers, baseline before install, kill criteria, processor agreement. Leave the term sheet. | D13: Pricing & Pilot · Term sheet | E13: Term sheet delivered; processor agreement drafted | F13: 1 week | G13: 0.55 | H13: Pilot running | I13: Paper Process — art. 28 agreement
A14: Pilot running | B14: Ninety days, measured | C14: Capture the three baselines BEFORE install. Weekly check-in. Watch the kill criteria. Max two pilots at once, each on its own stack. | D14: Pricing & Pilot · Term sheet | E14: Day-24 smoke test passed; metrics moving by day 75 | F14: 90 days | G14: 0.75 | H14: Customer | I14: Champion — the admin person is using it
A15: Customer | B15: Paid, first quarter closed in the product | C15: Convert to per-segment pricing. Ask for the reference (consent in writing). Log the CLV inputs. | D15: — | E15: First quarterly filing assembled from the product | F15: — | G15: 1 | H15: — | I15: —
... A17: Not a fit | B17: Declined by us | C17: Say so plainly and kindly. Record which disqualifier applied (Objections 3, 9 or 11 usually). | D17: Objections sheet | E17: Disqualifier recorded | F17: — | G17: 0 | H17: — | I17: —
A19: Exit criteria as written in the go-to-market plan (08-GTM-PLAN.md §4)
A20: # | B20: Stage in the plan | C20: Exit criterion and moving artefact
A21: 1 | B21: Trigger identification and first contact. | C21: Exit criterion: the prospect recognises the specific pain named in one of 03-TRIGGER-MAP.md's openers as their own Tuesday, not a generic software pitch. Moving artefact: the opener itself, delivered as the first-touch message docs/market/barcelona/ROADMAP.md's Phase 9 will draft, addressed to a named, verifiable fact about the firm rather than a template.
A22: 2 | B22: Qualifying call. | C22: Exit criterion: the hard-gate checklist of 02-ICP-AND-RUBRIC.md A.5 is answered — revenue mix (project versus recurring maintenance), incumbent ledger status, public-work exposure, bank, legal form, and both Economic Buyers identified where two exist. Moving artefact: a completed, dated qualification record against that six-item hard-gate list, because a deal that skips this stage is a deal that discovers a hard gate after money has been spent rather than before.
A23: 3 | B23: A demonstration on the prospect's own data — the pivot stage, addressed honestly below. | C23: Exit criterion: both Economic Buyers have seen a document — a quotation, a contract, or an invoice — bearing their own firm's name, tax identifier and at least a sample of their own catalogue, not a generic demo tenant's. Moving artefact: the demo tenant itself, and the PDF documents it produces.
A24: 4 | B24: Data-protection sign-off. | C24: Exit criterion: the processor agreement is signed and a retention position is stated, satisfying 02-ICP-AND-RUBRIC.md A.5's sixth hard gate before any real data moves. Moving artefact: the signed agreement, which for this buyer is very often the entire "Paper Process" the deal will ever produce.
A25: 5 | B25: Onboarding. | C25: Exit criterion: the smoke test named in 07-TAILORING-ECONOMICS.md §1 passes — a quotation, a contract and an invoice, each issued and downloaded — and a handover note is delivered. Moving artefact: the handover note itself, and the first real (not demo) document the firm has issued from the product.
A26: 6 | B26: Conversion to paid, and the first quarter closed inside the product. | C26: Exit criterion: the firm's first quarterly filing cycle is assembled from the product rather than reconstructed from paper — the moment 03-TRIGGER-MAP.md's second-ranked trigger stops being a monthly threat. Moving artefact: the export package for that first quarter, which doubles as the artefact a reference conversation can be built around.
A28: Qualification — MEDDPICC adapted to the owner-manager (08-GTM-PLAN.md §3)
A29: Letter | B29: How it applies to this buyer
A30: Metrics | B30: Not a generic ROI slide; the segment's own value-case arithmetic from 06-VALUE-CASE.md, asked as a question the prospect answers rather than told as a number they receive. The single most diagnostic question, stated directly in 06-VALUE-CASE.md §3.5's own conclusion for the hardest segment and applicable to all three, is whether the owner can name one completed job whose margin he could not explain afterwards. A firm that cannot name one has just told the seller its own Metrics; a firm that can name several has told the seller the deal is close to qualified before a single number has been quoted.
A31: Economic Buyer | B31: Usually a duo, not a hierarchy. Where two owners split operations and administration — the pattern 00-REFERENCE-CASE.md records and the product's own permission model is built around — both must be identified and both must agree, because a sale that wins one and loses the other stalls indefinitely rather than closing slowly. Where the firm is a true sole operator (Segment 3's modal case), the Economic Buyer is one person, and the qualification question shifts from "who else needs to agree" to "does this one person have forty owner-hours a year to give the product" (06-VALUE-CASE.md §3.5's own adoption-cost line).
A32: Decision Criteria | B32: Not a feature checklist scored against named competitors — there is usually no competing product under evaluation, because the incumbent is Excel and a gestoría, not a rival ERP (02-ICP-AND-RUBRIC.md A.3, "the incumbent is not a competitor product"). The real decision criterion, as 06-VALUE-CASE.md §3.7 states in pricing Segment 3 deliberately below the adviser's own monthly fee, is a psychological ceiling anchored on the gestoría's retainer, not a value-for-money comparison against alternative software.
A33: Decision Process | B33: Informal and short by construction, precisely because the committee, procurement function and written specification that lengthen a normal enterprise Decision Process are the same organisational features 02-ICP-AND-RUBRIC.md A.6 type 3 names as reasons to decline a firm (a controller, a payroll bureau, a comparison against named commercial products). The process for this buyer is a phone call, a demonstration, and a decision inside days rather than committee cycles — but exactly because there is no formal process, a stalled deal has no internal mechanism pushing it forward either, so the seller has to supply the cadence a committee would otherwise provide.
A34: Paper Process | B34: There is usually no legal department and no procurement portal. The paper that actually moves — and the piece of Paper Process this ICP takes seriously in a way a generic SME might not — is the GDPR/LOPDGDD processor agreement 02-ICP-AND-RUBRIC.md A.5's sixth hard gate names directly: real financial and employee data requires a signed processor agreement and a stated retention position before a pilot's baseline can even be measured, and a firm unwilling to sign either is disqualified from being a design partner regardless of how well it scores everywhere else.
A35: Identify Pain | B35: Use 03-TRIGGER-MAP.md's own openers verbatim as the diagnostic instrument, segment-adjusted: the Verifactu opener for the dated, universal pain every S.L. and S.A. shares, and the quarterly-reconstruction opener for the pain that is felt every ninety days regardless of any legal deadline. Both are written to be falsifiable in the room — the prospect either recognises the described Tuesday or does not — which is a better qualification signal than any question asked directly.
A36: Champion | B36: This is the letter that most visibly breaks, and the adaptation has to be stated rather than assumed away. 02-ICP-AND-RUBRIC.md A.4.2 calls a named administrative person who is not the operations owner the single most reliable organisational qualifier, precisely because MEDDPICC's Champion function — someone inside the account who carries the case internally — needs a second person to carry it to. Where that second person exists (most of Segment 1 and Segment 2), they are the Champion in the framework's own sense, and their engagement, not the owner's, is the leading indicator. Where no second person exists — Segment 3's modal firm, and 01-MARKET-MAP.md §4.1's own finding that the operations-versus-administration distinction is "inert" below roughly eight people — there is no one to carry the case internally, because the Economic Buyer, the user and the only candidate Champion are one exhausted person at the end of a working day. The honest adaptation is that Champion, in that case, is not a role a second person fills; it is a test of whether the owner will advocate the tool to his own future evening self, and the tell is the same one used for Metrics above — a named job whose margin he could not explain.
A37: Competition | B37: Not another ERP vendor in the overwhelming majority of deals — 02-ICP-AND-RUBRIC.md A.3 and 06-VALUE-CASE.md §4 both name the real incumbent as a spreadsheet and a gestoría — but the qualification question has to go one step further than that concession, because the sharpest live competitive threat identified anywhere in this roadmap is the gestoría's own emerging compliant billing tool, not a hypothetical rival. Scoring Competition honestly for this buyer means asking, directly, what the prospect's own adviser has told them about 2027 — because if the answer is "my gestoría is already handling it," that answer should be believed and tested, not argued past.

Sheet Scripts
A1: Scripts — Castellano and Català, side by side
A2: From 09-OUTREACH-KIT.md. Merge fields in [BRACKETS] must be resolved and verified before sending. Never invent a figure or a testimonial.
A3: Do not send until
A4: 1. | B4: Every merge field is resolved and verified. No square-bracketed capitals remain in the outgoing text. The site reference ([CARRER, MUNICIPI] / [CALLE, MUNICIPIO]) was checked on the firm's own website or the municipal works permit, not inferred from 04-PROSPECTS.jsonl, whose municipality field failed audit at 30.8% error. The name in the salutation appears in the Registro Mercantil or on the firm's website, or the salutation is the neutral form.
A5: 2. | B5: The contact channel is one the GDPR posture allows. Row 39's webmail address and row 70's mobile-shaped number get a manual look (04-EXTRACTION-QA.md); row 114's email field is the phone number duplicated and is not an address; Delgado & Dilla and Lluca have no recovered channel and are reached through the registry or a referral, not a guessed address.
A6: 3. | B6: Every consent placeholder is resolved. Each [REQUIRES CUSTOMER CONSENT] is either replaced with a quotation that a named customer approved in writing, or the line is deleted. The page prints without a testimonial before it prints with an unapproved one.
A7: 4. | B7: The 2027 wording is re-checked against 03-TRIGGER-MAP.md §1 on the day of sending. The date (1 January 2027 for an S.L.), the user's exposure (€50,000 per financial year) and the sentence "the hard half is built, the last mile to the tax authority is not" are still true. If the submission channel has shipped since this kit was written, the wording changes to what 03-TRIGGER-MAP.md then says, and not before. The word "compliant" does not appear in any language.
A8: 5. | B8: No figure from the value model has crept in. The 1.5% overpayment, the 30% of extras, the six days per quarter, the month-5 payback and the 9.7:1 ratio are modelled assumptions (06-VALUE-CASE.md §6) and are asked as questions about the prospect's own closed job, never stated about their firm.
A9: 6. | B9: The Català was read once by a native speaker before the first send to a Catalan-first prospect, and the person who will take the call is a Catalan speaker (08-GTM-PLAN.md §5).
A10: 7. | B10: The word counts hold. First-touch under 120 words per language, follow-ups under 100, LinkedIn under 300 characters, counted on the final merged text, not on this template.
